Workbook

Sheet Project Report
A1: Year | B1: Project Name | C1: Unit | D1: Backlog | E1: โอนแล้ว | F1: รวมลูกค้า Origin | G1: ลูกค้า Wyde | H1: %ขายWYDE | I1: มูลค่าPackage | J1: Backlog | K1: Book | L1: รายได้ Per/Bill | N1: ลค.ต้องติดตามต่อ | O1: FC | P1: Rev./BIll | Q1: Target Rev.
A2: 0 | B2: Origin Plug&Play Srinakarin | N2: (โอนแล้วยังไม่ซื้อWYDE) | O2: 0.8
A3: 2025 | B3: The Origin Praksa | C3: 827 | D3: 237 | E3: 216 | F3: =E3+D3 -> 453 | G3: 122 | H3: =G3/F3 -> 0.26931567 | I3: =SUM('ลค. Event'!E157:E237) -> 0 | L3: =I3/G3 -> 0 | N3: 117 | O3: =N3*O2 -> 93.6 | P3: 40000 | Q3: =O3*P3 -> 3744000
A4: 2025 | B4: The Origin Phahol 57 | C4: 432 | D4: 116 | E4: 168 | F4: =E4+D4 -> 284 | G4: 23 | H4: =G4/F4 -> 0.080985915 | I4: =SUM('ลค. Event'!E133:E155) -> 0 | L4: =I4/G4 -> 0 | N4: 263 | O4: =N4*O2 -> 210.4 | P4: 80000 | Q4: =O4*P4 -> 16832000
A5: 2025 | B5: Origin play Bangsaen | C5: 494 | D5: 87 | E5: 299 | F5: =E5+D5 -> 386 | G5: 34 | H5: =G5/F5 -> 0.088082902 | I5: =SUM('ลค. Event'!E2:E9) -> 0 | L5: =I5/G5 -> 0 | N5: 270 | O5: =N5*O2 -> 216 | P5: 80000 | Q5: =O5*P5 -> 17280000
A6: 2025 | B6: Origin play Bangkhunnon | C6: 477 | D6: 198 | E6: 255 | F6: =E6+D6 -> 453 | G6: 47 | H6: =G6/F6 -> 0.10375276 | I6: =SUM(#REF!) -> #REF! | L6: =I6/G6 -> #REF! | N6: ='ตามต่อบางขุนนท์'!B219 -> 215 | O6: =N6*O2 -> 172 | P6: 100000 | Q6: =O6*P6 -> 17200000
A7: 2025 | B7: The Origin Kathu-Patong | C7: 624 | D7: 325 | E7: 245 | F7: =E7+D7 -> 570 | G7: 30 | H7: =G7/F7 -> 0.052631579 | I7: =SUM('ลค. Event'!E103:E132) -> 0 | L7: =I7/G7 -> 0 | N7: 310 | O7: =N7*O2 -> 248 | P7: 120000 | Q7: =O7*P7 -> 29760000
A8: 2025 | B8: The Origin Bangkae | C8: 1485 | D8: 506 | E8: 212 | F8: =E8+D8 -> 718 | G8: 29 | H8: =G8/F8 -> 0.040389972 | I8: =SUM('ลค. Event'!E74:E102) -> 0 | L8: =I8/G8 -> 0 | N8: ='ติดตามต่อบางแค'!A191 -> 189 | O8: =N8*O2 -> 151.2 | P8: 150000 | Q8: =O8*P8 -> 22680000
A9: 2026 | B9: Origin Place Khonkaen | C9: 442 | D9: 167 | E9: 82 | F9: =E9+D9 -> 249 | G9: 17 | H9: =G9/F9 -> 0.068273092 | I9: =SUM(#REF!) -> #REF! | L9: =I9/G9 -> #REF! | N9: 268 | O9: =N9*O2 -> 214.4 | P9: 30000 | Q9: =O9*P9 -> 6432000
A10: 2026 | B10: So Origin Siriraj | C10: 256 | D10: 246 | E10: 0 | F10: =D10 -> 246 | G10: 22 | H10: =G10/F10 -> 0.089430894 | I10: =SUM('ลค. Event'!E239:E260) -> 0 | L10: =I10/G10 -> 0 | N10: =F10-G10 -> 224 | O10: =N10*O2 -> 179.2 | P10: 200000 | Q10: =O10*P10 -> 35840000 | R10: *ตามจากกลุมลูกค้าBACKLOG
A11: 2026 | B11: Origin Place Petkasem | C11: 353 | D11: 353 | E11: 0 | F11: =D11 -> 353 | G11: 28 | H11: =G11/F11 -> 0.079320113 | I11: 147000 | N11: =F11-G11 -> 325 | O11: =N11*O2 -> 260 | P11: 150000 | Q11: =O11*P11 -> 39000000
A12: 2026 | B12: So Origin Bangtao Beach | C12: 545 | D12: 326 | E12: 0 | F12: =D12 -> 326
A13: 2026 | B13: The Origin Center Phuket | C13: 701 | D13: 366 | E13: 0 | F13: =D13 -> 366
A14: 2026 | B14: The Origin Setthabut Station | C14: 530 | D14: 271 | E14: 0 | F14: =D14 -> 271
A15: 2026 | B15: Origin Thonglor world - IP | C15: 795 | D15: 332 | E15: 0 | F15: =D15 -> 332
C16: =SUM(C2:C15) -> 7961 | D16: =SUM(D3:D15) -> 3530 | E16: =SUM(E3:E15) -> 1477 | F16: =SUM(F3:F15) -> 5007 | G16: =SUM(G3:G15) -> 352 | H16: =G16/F16 -> 0.070301578 | I16: =SUM(I2:I15) -> #REF! | N16: =SUM(N3:N15) -> 2181 | O16: =SUM(O3:O15) -> 1744.8 | Q16: =SUM(Q3:Q15) -> 188768000
C19: พี่อ้อม | D19: =D11+D12+D13+D14+D7 -> 1641 | E19: ห้อง | N19: พี่เจี๊ยบ | O19: =N3+N4+N5+N6+N8+N9+N10 -> 1546 | P19: ห้อง
C20: คาดยอดขาย | D20: 200000000 | N20: คาดยอดขาย | O20: 350000000
D21: =D20/D19 -> 121876.9 | E21: บ/ห้อง | O21: =O20/O19 -> 226390.69 | P21: บ/ห้อง
C23: KPI | D23: BOOKING | N23: KPI | O23: BOOKING
C24: 1 | D24: =D20 -> 200000000 | N24: 1 | O24: =O20 -> 350000000
C25: 0.8 | D25: =D24*C25 -> 160000000 | N25: 0.8 | O25: =O24*N25 -> 280000000
C26: 0.5 | D26: =C26*D24 -> 100000000 | N26: 0.5 | O26: =N26*O24 -> 175000000
C28: Current | D28: 12000000 | E28: =D28/D20 -> 0.06 | N28: Current | O28: 38000000 | P28: =O28/O20 -> 0.10857143
C29: ทำเพิ่ม | D29: =D20-D28 -> 188000000 | N29: ทำเพิ่ม | O29: =O20-O28 -> 312000000
C32: มีเป้าหมายแล้ว ทำ กลยุทธ และ ทำKPI วัดผม
C33: 1.จัดทำSOP การบริหารจัดการกลยุทธการขาย >>> มีนโยบาย มีกลยุทธ แล้ว มีKPI /// การวางการขาย ในเล่มจะประกอบด้วย สร้างใหม่ รับนโยบายมา กลยุทธ ออกมาเป็น KPI แล้ววางแผนการขาย ยังไง เป็น 1 เล่ม
C34: (เอกสารSUBMIT KPI) ต้องคุยเรื่องทิศทางในการขาย กับProject Asia ว่ากลยุทธการขาย จะยังไง ไปในมุม Consult วางStructure คน ราคา งานจาก Project asia ไปเป็นConsult แนะนำ interior ให้Owner กับ อีกอัน แนวทางการหาลูกค้าของเรา มี กี่แนวทาง วิธีการบังไงบ้าง วัดผลยังไ
C35: เป็น Consult Interior ในหัวของProject Asia // หรือ เป็นบริษัทPartner ที่แนะนำ PJA แนะนำงาน
C36: 2.จัดทำ SOP การวางแผนการตลาด เขียนตามสิ่งที่ทำ เอกสารผู้มีอำนาจ อนุมัติ กรอบวงเงินMKT มีแบบฟอร์มเอกสาร ขั้นตอนยังไง ให้เขียน ไป เช่น จะไปออกอีเว้นต์ ต้องทำอะไรบ้าง ทำแพ๊กเกจขาย Head sales รับผิดชอบ ราคาขาย โปรโมชั่น ในอีเว้นต์ ใคร อนุมัติ ใครเป็นคนติดต่อสถานที่ ใครเป็นคนสรุปผลทางการตลาด เกิดpipelineไหมใน การขายนี้ ให้Claude คิด แล้ว เขียนเป็นSOP ออกมาให้ // เขียนข้อกำหนดรองรับในการให้ส่วนลดและโปรโมชั่น ส่วนลดต้องทำยังไง โปรโมชั่นต้องทำยังไง Deposit 5000 /10000 ต้องทำยังไง เช่น ขออนุมัติ manager ก็เขียนให้ละเอียด
C37: 3.ทำแบบฟอร์มการขึ้นทะเบียนลูกค้า (มีอยู่แล้ว)
C38: 4.ทำSOP การจัดทำสัญญาบริการ สำหรับงานที่มีมูลค่าสูง
C39: 5.ทำSOP การจัดการข้อร้องเรียนของลูกค้า (ใครเป็นคนรับข้อร้องเรียนลูกค้า เก็บสถิติยังไง )
C41: 6.มาตรฐานการทำงาน ว่าทำงานบนหลักเกณฑ์ อะไร เช่น มีวิศวกรควบคุม // เอกสารตรวจงาน ใช้มตรฐานอะไรมา ตรวจงานให้ลูกค้า // ข้อกำหนด ของ การดำเนิน รู้ว่าProcess ที่ทำ มีอะไรเป็นตัวกำหนด มาตรฐานบ้าง การตรวจงานQC reference จากอะไร
C42: Project spec standard // มาตรฐานวิชาชีพวิศวะกรรมในประเทศ // มาตรฐานสำหรับงานเฉพาะทาง // มาตรฐานค่าความคลาดเคลื่อนที่ยอมรับได้ // เช่น กระเบื้อง เคาะแล้ว ต้อง ไม่ป่อง เกิน 20% // คนที่ เดินงานระบบไฟ ได้ ต้องมีใบประกอบวิชาชีพ

Sheet ชีต26

Sheet KPI
B1: Sales Manager : Jeab | K1: Sales Manager : Aom
A2: Year | B2: Project | C2: Sales | D2: Target | E2: Actual | F2: Backlog | G2: Book | H2: New Case | J2: Year | K2: Project | L2: Sales | M2: Target | N2: Actual | O2: Backlog | P2: Book | Q2: New Case
B3: Park Origin Thonglor | C3: Ying | D3: 20 | F3: 1 | J3: 2026 | K3: The Origin Kathu-Patong | L3: Pon | M3: 100 | O3: 13 | P3: 0.8 | Q3: 8
B4: Park Origin Ratchathewi | C4: Pang | D4: 20 | F4: 4 | J4: 2026 | K4: SO Origin Bangtao Beach | L4: Pon | M4: 50
A5: 2024 | B5: Origin Plug&Play Sirindhorn Station | C5: Ying | D5: 15 | J5: 2026 | K5: The Origin Center-Phuket | L5: Pon | M5: 50
B6: Park 24 Juristic Person 1 | C6: Josh | D6: 5 | J6: 2026 | K6: ฺB2B | L6: Aun
B7: Origin Plug&Play Nonthaburi Station | C7: Josh | D7: 2
A8: 2024 | B8: Origin Plug&Play E22 Station | C8: Pang | D8: 2
B9: Park Origin Phayathai | C9: Hack | D9: 2
B10: Park origin Chula Samyan | C10: Hack | D10: 10
A11: 2024 | B11: The Origin Campus Khonkaen | C11: Josh | D11: 1 | F11: 0.26
A12: 2024 | B12: Knighsbridge Space Raman4 | C12: Ying | D12: 1 | F12: 0.7
A13: 2025 | B13: So Origin Kaset Interchange | C13: Ying | D13: 5
A14: 2025 | B14: Origin Plug&Play Srinakarin | C14: Ying | D14: 10
A15: 2025 | B15: So Phahol 69 Station | C15: Josh | D15: 10
A16: 2025 | B16: The Origin Sukhumvit Praksa | C16: Pang | D16: =10+4.5 -> 14.5 | E16: 1.45 | F16: 1.97 | G16: 1.68
A17: 2025 | B17: Origin Place Bangna | C17: Ying | D17: =21+1 -> 22 | E17: 0.42 | F17: 0.5 | G17: 0.3
A18: 2025 | B18: Origin Play Bangsaen | C18: Pang | D18: =21+3 -> 24 | E18: 0.27 | F18: 1.62 | G18: 1.38
A19: 2025 | B19: The Origin Bangkae | C19: Hack | D19: =28+2.6 -> 30.6 | E19: =Sumifs('ลค. Event'!$K:$K,'ลค. Event'!$I:$I,B19,'ลค. Event'!$U:$U,"ส่งมอบแล้ว") -> 0 | F19: 0.11 | G19: 2.52
A20: 2025 | B20: Origin Play Bangkhunnon | C20: Hack | D20: =21+7.2 -> 28.2 | E20: 0.47 | F20: 0.83 | G20: 7.24
A21: 2025 | B21: The Origin Phahol 57 | C21: Josh | D21: =21+1.2 -> 22.2 | E21: 1.06 | F21: 0.03 | G21: 0.29
A22: 202ุ6 | B22: Origin Place Khon Kaen-Kanlapaphruek | C22: Josh | D22: =10.1+2.4 -> 12.5 | G22: 2.73
A23: 202ุ6 | B23: SO Origin Siriraj | C23: Ying | D23: =45+6 -> 51 | G23: 6.36
A24: 2026 | B24: The Origin Setthabut | C24: Josh | D24: 10
A25: 2026 | B25: Origin Place Petchkasem | C25: Pang | D25: 20
A26: 2026 | B26: Thonglor World-IP | C26: Ying
A27: 2026 | B27: โครงการนอกเครือ Origin | C27: Hack | D27: 2
A28: 2026 | B28: โครงการนอกเครือ Origin | C28: Josh | D28: 10
C29: Sum (MB.) | D29: =Sum(D3:D28) -> 350 | E29: =Sum(E3:E28) -> 3.67 | F29: =Sum(F3:F28) -> 11.02 | G29: =Sum(G3:G28) -> 22.5 | H29: =Sum(H3:H28) -> 0 | L29: Sum (MB.) | M29: =Sum(M3:M28) -> 200 | O29: =Sum(O3:O28) -> 13 | P29: =Sum(P3:P28) -> 0.8 | Q29: =Sum(Q3:Q28) -> 8
C31: Manager | D31: Target | E31: Actual | F31: Backlog | G31: Book | H31: New Case | L31: Manager | M31: Target | N31: Actual | O31: Backlog | P31: Book | Q31: New Case
B32: Target 350 MB | C32: Jeab | D32: =Sum(D34:D37) -> 350 | E32: =Sum(E34:E37) -> 3.67 | F32: =Sum(F34:F37) -> 11.02 | G32: =Sum(G34:G37) -> 22.5 | H32: =Sum(H34:H37) -> 0 | L32: Aom | M32: =Sum(M34:M37) -> 200 | O32: =Sum(O34:O37) -> 29.2 | P32: =Sum(P34:P37) -> 0.8 | Q32: =Sum(Q34:Q37) -> 10
C33: Sales | D33: Target | E33: Actual | F33: Backlog | G33: Book | H33: New Case | L33: Sales | M33: Target | N33: Actual | O33: Backlog | P33: Book | Q33: New Case
B34: Target 110 MB | C34: Ying | D34: =Sumifs(D3:D28,C3:C28,"Ying") -> 124 | E34: =Sumifs(E3:E28,C3:C28,"Ying") -> 0.42 | F34: =Sumifs(F3:F28,C3:C28,"Ying") -> 2.2 | G34: =Sumifs(G3:G28,C3:C28,"Ying") -> 6.66 | L34: Pon | M34: 100 | O34: 13 | P34: 0.8 | Q34: 8
B35: Target 80 MB | C35: Pang | D35: =Sumifs(D3:D28,C3:C28,"Pang") -> 80.5 | E35: =Sumifs(E3:E28,C3:C28,C35) -> 1.72 | F35: =Sumifs(F3:F28,C3:C28,"Pang") -> 7.59 | G35: =Sumifs(G3:G28,C3:C28,"Pang") -> 3.06 | L35: Aun | M35: 100 | O35: 16.2 | P35: - | Q35: 2
B36: Target 80 MB | C36: Josh | D36: =Sumifs(D3:D28,C3:C28,"Josh") -> 72.7 | E36: =Sumifs(E4:E29,C4:C29,C36) -> 1.06 | F36: =Sumifs(F3:F28,C3:C28,"Josh") -> 0.29 | G36: =Sumifs(G3:G28,C3:C28,"Josh") -> 3.02
B37: Target 80 MB | C37: Hack | D37: =Sumifs(D3:D28,C3:C28,"Hack") -> 72.8 | E37: =Sumifs(E5:E30,C5:C30,C37) -> 0.47 | F37: =Sumifs(F3:F28,C3:C28,"Hack") -> 0.94 | G37: =Sumifs(G3:G28,C3:C28,"Hack") -> 9.76
A41: 2025 | B41: The Origin Sukhumvit Praksa | C41: Pang | D41: =10+4.5 -> 14.5 | E41: =Sumifs('ลค. Event'!$K:$K,'ลค. Event'!$I:$I,B16,'ลค. Event'!$U:$U,"ส่งมอบแล้ว") -> 1459084.1 | F41: =SUMIFS('ลค. Event'!K:K,'ลค. Event'!I:I,B41,'ลค. Event'!R:R,"50%")+SUMIFS('ลค. Event'!K:K,'ลค. Event'!I:I,B41,'ลค. Event'!R:R,"100%") -> 1975400 | G41: =Sumifs('ลค. Event'!$K:$K,'ลค. Event'!$I:$I,B41,'ลค. Event'!$R:$R,"จองสิทธิ์") -> 1688860
A42: 2025 | B42: Origin Place Bangna | C42: Ying | D42: =21+1 -> 22 | E42: =Sumifs('ลค. Event'!$K:$K,'ลค. Event'!$I:$I,B42,'ลค. Event'!$U:$U,"ส่งมอบแล้ว") -> 429943.93 | F42: =SUMIFS('ลค. Event'!K:K,'ลค. Event'!I:I,B42,'ลค. Event'!R:R,"50%")+SUMIFS('ลค. Event'!K:K,'ลค. Event'!I:I,B42,'ลค. Event'!R:R,"100%") -> 501100 | G42: =Sumifs('ลค. Event'!$K:$K,'ลค. Event'!$I:$I,B42,'ลค. Event'!$R:$R,"จองสิทธิ์") -> 319400
A43: 2025 | B43: Origin Play Bangsaen | C43: Pang | D43: =21+3 -> 24 | E43: =Sumifs('ลค. Event'!$K:$K,'ลค. Event'!$I:$I,B43,'ลค. Event'!$U:$U,"ส่งมอบแล้ว") -> 277289.72 | F43: =SUMIFS('ลค. Event'!K:K,'ลค. Event'!I:I,B43,'ลค. Event'!R:R,"50%")+SUMIFS('ลค. Event'!K:K,'ลค. Event'!I:I,B43,'ลค. Event'!R:R,"100%") -> 1621300 | G43: =Sumifs('ลค. Event'!$K:$K,'ลค. Event'!$I:$I,B43,'ลค. Event'!$R:$R,"จองสิทธิ์") -> 1380210
A44: 2025 | B44: The Origin Bangkae | C44: Hack | D44: =28+2.6 -> 30.6 | E44: =Sumifs('ลค. Event'!$K:$K,'ลค. Event'!$I:$I,B44,'ลค. Event'!$U:$U,"ส่งมอบแล้ว") -> 0 | F44: =SUMIFS('ลค. Event'!K:K,'ลค. Event'!I:I,B44,'ลค. Event'!R:R,"50%")+SUMIFS('ลค. Event'!K:K,'ลค. Event'!I:I,B44,'ลค. Event'!R:R,"100%") -> 115200 | G44: =Sumifs('ลค. Event'!$K:$K,'ลค. Event'!$I:$I,B44,'ลค. Event'!$R:$R,"จองสิทธิ์") -> 2526940
A45: 2025 | B45: Origin Play Bangkhunnon | C45: Hack | D45: =21+7.2 -> 28.2 | E45: =Sumifs('ลค. Event'!$K:$K,'ลค. Event'!$I:$I,B45,'ลค. Event'!$U:$U,"ส่งมอบแล้ว") -> 472306.55 | F45: =SUMIFS('ลค. Event'!K:K,'ลค. Event'!I:I,B45,'ลค. Event'!R:R,"50%")+SUMIFS('ลค. Event'!K:K,'ลค. Event'!I:I,B45,'ลค. Event'!R:R,"100%") -> 837340 | G45: =Sumifs('ลค. Event'!$K:$K,'ลค. Event'!$I:$I,B45,'ลค. Event'!$R:$R,"จองสิทธิ์") -> 7244840
A46: 2025 | B46: The Origin Phahol 57 | C46: Josh | D46: =21+1.2 -> 22.2 | E46: =Sumifs('ลค. Event'!$K:$K,'ลค. Event'!$I:$I,B46,'ลค. Event'!$U:$U,"ส่งมอบแล้ว") -> 1068365.4 | F46: =SUMIFS('ลค. Event'!K:K,'ลค. Event'!I:I,B46,'ลค. Event'!R:R,"50%")+SUMIFS('ลค. Event'!K:K,'ลค. Event'!I:I,B46,'ลค. Event'!R:R,"100%") -> 21800 | G46: =Sumifs('ลค. Event'!$K:$K,'ลค. Event'!$I:$I,B46,'ลค. Event'!$R:$R,"จองสิทธิ์") -> 294210
A47: 202ุ6 | B47: Origin Place Khon Kaen-Kanlapaphruek | C47: Josh | D47: =10+2.4 -> 12.4 | E47: =Sumifs('ลค. Event'!$K:$K,'ลค. Event'!$I:$I,B47,'ลค. Event'!$U:$U,"ส่งมอบแล้ว") -> 0 | F47: =SUMIFS('ลค. Event'!K:K,'ลค. Event'!I:I,B47,'ลค. Event'!R:R,"50%")+SUMIFS('ลค. Event'!K:K,'ลค. Event'!I:I,B47,'ลค. Event'!R:R,"100%") -> 0 | G47: =Sumifs('ลค. Event'!$K:$K,'ลค. Event'!$I:$I,B47,'ลค. Event'!$R:$R,"จองสิทธิ์") -> 0
A48: 202ุ6 | B48: SO Origin Siriraj | C48: Ying | D48: =45+6 -> 51 | E48: =Sumifs('ลค. Event'!$K:$K,'ลค. Event'!$I:$I,B48,'ลค. Event'!$U:$U,"ส่งมอบแล้ว") -> 0 | F48: =SUMIFS('ลค. Event'!K:K,'ลค. Event'!I:I,B48,'ลค. Event'!R:R,"50%")+SUMIFS('ลค. Event'!K:K,'ลค. Event'!I:I,B48,'ลค. Event'!R:R,"100%") -> 0 | G48: =Sumifs('ลค. Event'!$K:$K,'ลค. Event'!$I:$I,B48,'ลค. Event'!$R:$R,"จองสิทธิ์") -> 6361280

Sheet Action plan 30MBMonth
B2: Sales / Target | C2: Year | D2: Quarter | E2: Month | F2: Week | G2: day
B3: Jeab | C3: =SUM(C4:C7) -> 350 | D3: =C3/4 -> 87.5 | E3: =D3/3 -> 29.166667 | F3: =E3/4 -> 7.2916667 | G3: =F3/6 -> 1.2152778
B4: Ying | C4: 120 | D4: =C4/4 -> 30 | E4: =D4/3 -> 10 | F4: =E4/4 -> 2.5 | G4: =F4/6 -> 0.41666667
B5: Pang | C5: 80 | D5: =C5/4 -> 20 | E5: =D5/3 -> 6.6666667 | F5: =E5/4 -> 1.6666667 | G5: =F5/6 -> 0.27777778
B6: Josh | C6: 75 | D6: =C6/4 -> 18.75 | E6: =D6/3 -> 6.25 | F6: =E6/4 -> 1.5625 | G6: =F6/6 -> 0.26041667
B7: Hack | C7: 75 | D7: =C7/4 -> 18.75 | E7: =D7/3 -> 6.25 | F7: =E7/4 -> 1.5625 | G7: =F7/6 -> 0.26041667
B9: Action plan / Day (Daily Report)
B10: Sales : Name
B11: Target : 0.42 MB
B12: Activity | C12: ที่มา | D12: Action | E12: เป้าหมาย | F12: ทำแล้ว | G12: ขาด | H12: ผล | I12: ยอดขาย | J12: Retio | K12: Remark
B13: Online Lead | C13: Facebook/IG | D13: Chat&Call | E13: 5 | F13: 0 | G13: =E13-F13 -> 5
B14: Offline Lead | C14: Wyde Data | D14: Call | E14: 10 | F14: 0 | G14: =E14-F14 -> 10
C15: Line OA | D15: Chat&Call | E15: 5 | F15: 0 | G15: =E15-F15 -> 5
F16: 0 | G16: =E16-F16 -> 0
F17: 0 | G17: =E17-F17 -> 0
F18: 0 | G18: =E18-F18 -> 0
B20: Sales / Target | C20: Year | D20: Quarter | E20: Month | F20: Week | G20: day
B21: Aom | C21: =SUM(C22:C23) -> 200 | D21: =C21/4 -> 50 | E21: =D21/3 -> 16.666667 | F21: =E21/4 -> 4.1666667 | G21: =F21/6 -> 0.69444444
B22: Pon | C22: 100 | D22: =C22/4 -> 25 | E22: =D22/3 -> 8.3333333 | F22: =E22/4 -> 2.0833333 | G22: =F22/6 -> 0.34722222
B23: Aun | C23: 100 | D23: =C23/4 -> 25 | E23: =D23/3 -> 8.3333333 | F23: =E23/4 -> 2.0833333 | G23: =F23/6 -> 0.34722222

Sheet KPI ทีมพี่เจี๊ยบ
A1: Month | B1: Week | C1: Salesperson | D1: Target_Amount | E1: Actual_Sales | F1: Achievement_Rate | G1: Notes
A2: May | B2: Week 1 | C2: YING | D2: 1600000 | E2: 0 | F2: 0
A3: May | B3: Week 1 | C3: PANG | D3: 1600000 | E3: 0 | F3: 0
A4: May | B4: Week 1 | C4: JOSH | D4: 1600000 | E4: 0 | F4: 0
A5: May | B5: Week 1 | C5: HACK | D5: 1600000 | E5: 0 | F5: 0
A6: May | B6: Week 2 | C6: YING | D6: 2000000 | E6: 0 | F6: 0
A7: May | B7: Week 2 | C7: PANG | D7: 2000000 | E7: 0 | F7: 0
A8: May | B8: Week 2 | C8: JOSH | D8: 2000000 | E8: 0 | F8: 0
A9: May | B9: Week 2 | C9: HACK | D9: 2000000 | E9: 0 | F9: 0
A10: May | B10: Week 3 | C10: YING | D10: 2400000 | E10: 0 | F10: 0
A11: May | B11: Week 3 | C11: PANG | D11: 2400000 | E11: 0 | F11: 0
A12: May | B12: Week 3 | C12: JOSH | D12: 2400000 | E12: 0 | F12: 0
A13: May | B13: Week 3 | C13: HACK | D13: 2400000 | E13: 0 | F13: 0
... A129: December | B129: Week 4 | C129: HACK | D129: 2750000 | E129: 0 | F129: 0

Sheet Area Assignment
A1: Area-Project | B1: Head | C1: Sales name | D1: Position | E1: Assign
A2: Phuket
A3: The Origin Kathu-Patong | B3: Aom | C3: pon | D3: Senior Project Interior Designer | E3: งานขาย(ลูกค้า Thai +Online ต่างชาติ) + เอกสาร (ลูกค้าไทย +ต่างชาติ) +Designer Brief
A4: SO Origin Bangtao Beach | B4: Aom | C4: pon | D4: Senior Project Interior Designer | E4: งานขาย(ลูกค้า Thai +Online ต่างชาติ) + เอกสาร (ลูกค้าไทย +ต่างชาติ) +Designer Brief
A5: The Origin Center-Phuket | B5: Aom | C5: pon | D5: Senior Project Interior Designer | E5: งานขาย(ลูกค้า Thai +Online ต่างชาติ) + เอกสาร (ลูกค้าไทย +ต่างชาติ) +Designer Brief
A6: Khonkaen
A7: Origin Place Khonkaen | B7: Jeab | C7: Josh | D7: Sales & Marketing Executive | E7: งานขาย(ลูกค้าไทย +Online + เอกสาร +Designer Brief
A8: The Origin Campus Khonkaen | B8: Jeab | C8: Josh | D8: Sales & Marketing Executive | E8: งานขาย(ลูกค้าไทย +Online + เอกสาร +Designer Brief
A9: Nonthaburi
A10: Origin Plug&Play Nonthaburi Station | B10: Jeab | C10: Josh | D10: Sales & Marketing Executive | E10: งานขาย(ลูกค้าไทย +Visit site + เอกสาร +Designer Brief
A11: Samutprakarn
A12: The Origin Praksa | B12: Jeab | C12: Pang | D12: Sales & Marketing Executive | E12: งานขาย(ลูกค้าไทย +Visit site) + เอกสาร +Designer Brief
A13: Origin Plug&Play Srinakarin | B13: Jeab | C13: Ying | D13: Senior Sales & Marketing Executive | E13: งานขาย( (ลูกค้าไทย+ต่างชาติ+Visit site) + เอกสาร +Designer Brief
A14: Origin Plug&Play E22 Station | B14: Jeab | C14: Pang | D14: Sales & Marketing Executive | E14: งานขาย(ลูกค้าไทย +Visit site) + เอกสาร +Designer Brief
A15: The Origin E22 Station | B15: Jeab | C15: Pang | D15: Sales & Marketing Executive | E15: งานขาย(ลูกค้าไทย +Visit site) + เอกสาร +Designer Brief
A16: Rayong
A17: Hampton Suite Rayong | B17: Jeab
A18: Chonburi
A19: Origin Play Bangsaen | B19: Jeab | C19: Pang | D19: Sales & Marketing Executive | E19: งานขาย(ลูกค้าไทย +Visit site) + เอกสาร +Designer Brief
A20: Brixton Campus Sriracha | B20: Jeab
A21: ฺBangkok - BKK
A22: Bangna
A23: Origin Place Bangna | B23: Jeab | C23: Ying | D23: Senior Sales & Marketing Executive | E23: งานขาย( (ลูกค้าไทย+ต่างชาติ+Visit site) + เอกสาร +Designer Brief
A24: Thonglor
A25: Thonglor World | B25: Aom | C25: Pon | D25: Senior Sales & Marketing Executive | E25: งานขาย(ลูกค้าOnline) + เอกสาร (ลูกค้าไทย +ต่างชาติ) +Designer Brief
A26: Park Origin Thonglor | B26: Jeab | C26: Ying | D26: Senior Sales & Marketing Executive | E26: งานขาย(Visit site) + เอกสาร (ลูกค้าไทย +ต่างชาติ) +Designer Brief
A27: Phaholyothin
A28: The Origin Phahol 57 | B28: Jeab | C28: Josh | D28: Sales & Marketing Executive | E28: งานขาย(ลูกค้าไทย +Visit site) + เอกสาร +Designer Brief
A29: SO Origin Phahol 69 | B29: Jeab | C29: Josh | D29: Sales & Marketing Executive | E29: งานขาย(ลูกค้าไทย +Visit site) + เอกสาร +Designer Brief
A30: Brixton Phahol 50 | B30: Jeab | C30: Josh | D30: Sales & Marketing Executive | E30: งานขาย(ลูกค้าไทย +Visit site) + เอกสาร +Designer Brief
A31: SO Origin Kaset-Interchange
A32: Pinklao
A33: SO Origin Siriraj | B33: Jeab | C33: Ying | D33: Senior Sales & Marketing Executive | E33: งานขาย(Visit site) + เอกสาร (ลูกค้าไทย +ต่างชาติ) +Designer Brief
A34: Origin Play Bangkhunnon | B34: Jeab | C34: Hack | D34: Sales & Marketing Executive | E34: งานขาย(ลูกค้าไทย +Visit site) + เอกสาร +Designer Brief
A35: Origin Plug&Play Sirinthorn | B35: Jeab | C35: Ying | D35: Senior Sales & Marketing Executive | E35: งานขาย(Visit site) + เอกสาร (ลูกค้าไทย +ต่างชาติ) +Designer Brief
A36: Ramkamheng
A37: Origin Plug&Play Ram103 | B37: Jeab | C37: Pang | D37: Sales & Marketing Executive | E37: งานขาย(ลูกค้าไทย +Visit site) + เอกสาร +Designer Brief
A38: Ramintra
A39: The Origin Setthabut | B39: Aom | C39: Pon | D39: Sales & Marketing Executive | E39: งานขาย(ลูกค้าไทย +Visit site) + เอกสาร +Designer Brief
A40: Origin Plug&play Ramintra | B40: Jeab | C40: Hack | D40: Sales & Marketing Executive | E40: งานขาย(ลูกค้าไทย +Visit site) + เอกสาร +Designer Brief
A41: Petkasem-Bangkae
A42: Origin Place Petchkasem | B42: Aom | C42: Pon | D42: Sales & Marketing Executive | E42: งานขาย(ลูกค้าไทย +Visit site) + เอกสาร +Designer Brief
A43: The Origin Bangkae | B43: Jeab | C43: Hack | D43: Sales & Marketing Executive | E43: งานขาย(ลูกค้าไทย +Visit site) + เอกสาร +Designer Brief
A44: Rama 4
A45: Knightsbridge Space Rama4 | B45: Jeab | C45: Ying | D45: Senior Sales & Marketing Executive | E45: งานขาย(Visit site) + เอกสาร (ลูกค้าไทย +ต่างชาติ) +Designer Brief
A46: Park Origin Chula-Samyan | B46: Jeab | C46: Hack | D46: Sales & Marketing Executive | E46: งานขาย(ลูกค้าไทย +Visit site) + เอกสาร +Designer Brief
A47: Sathorn
A48: Knightsbridge Prime Sathorn | B48: Jeab | C48: Ying | D48: Senior Sales & Marketing Executive | E48: งานขาย(Visit site) + เอกสาร (ลูกค้าไทย +ต่างชาติ) +Designer Brief

Sheet Booking
A1: ID | B1: วันที่บันทึก | C1: ประเภทลูกค้า | D1: ชื่อลูกค้า | E1: เบอร์ติดต่อ | F1: โครงการ | G1: หมายเลขห้อง | H1: Package ที่เลือก | I1: ราคาแพ็กเกจ | J1: ส่วนลด / Voucher | K1: ยอดสุทธิ | L1: เงินจองสิทธิ์ | M1: ช่องทางการชำระ | N1: หลักฐานการโอน | O1: พนักงานขาย | P1: สถานะการจอง

Sheet Daily Cash
A1: หัวตาราง (Column Header) | B1: ประเภทข้อมูล (Type ใน AppSheet) | C1: หมายเหตุ
A2: Cash ID | B2: Key
A3: วันที่ | B3: Date
A4: ประเภทรายการ | B4: Enum | C4: ตัวเลือก: รายรับ (จอง), รายรับ (อื่นๆ), รายจ่าย
A5: รายการ | B5: Text | C5: เช่น "รับเงินจอง คุณ..." หรือ "ค่าอุปกรณ์สำนักงาน"
A6: จำนวนเงิน | B6: Price
A7: ช่องทางเงิน | B7: Enum | C7: ตัวเลือก: บัญชีบริษัท, บัญชีต่างประเทศ, เงินสดหน้าร้าน
A8: Ref ID (ถ้ามี) | B8: Text | C8: สำหรับใส่ ID จากตาราง Booking มาโยงกัน

Sheet ลค. Event
A1: ปี-เดือน | B1: ปี | C1: เดือน | D1: PO Origin NO. | E1: SO | F1: ประเภทงาน | G1: วันที่รับยอด/PO | H1: ชื่อลูกค้า | I1: Project Name | J1: ห้อง | K1: Revenue(Ex.Vat) | L1: Revenue(Inc.Vat) | M1: ยอดโอน | N1: Voucher | O1: Cost | P1: Profit | Q1: GP% | R1: Working status | S1: Sale | T1: QC | U1: สถานะห้อง | V1: Finish Month | W1: วันที่ส่งมอบงาน | X1: หมายเหตุ | Y1: เดือนเบิกค่าคอมมิชชั่น | Z1: 0.012 | AA1: 0.0135 | AB1: 0.015 | AC1: 0.017 | AD1: 0.0185 | AE1: 0.022 | AF1: 0.025 | AG1: 0.0275 | AH1: 0.03 | AI1: 0.01 | AJ1: 0.015 | AK1: 0.02 | AL1: 500 | AM1: ปี-เดือน | AN1: ปี | AO1: เดือน | AP1: PO Origin NO. | AQ1: SO | AR1: ประเภทงาน | AS1: วันที่รับยอด/PO | AT1: ชื่อลูกค้า | AU1: Project Name | AV1: ห้อง | AW1: Revenue(Ex.Vat) | AX1: Revenue(Inc.Vat) | AY1: ยอดโอน | AZ1: Voucher | BA1: Cost | BB1: Profit | BC1: GP% | BD1: Working status | BE1: Sale | BF1: QC | BG1: สถานะห้อง | BH1: Finish Month | BI1: วันที่ส่งมอบงาน | BJ1: หมายเหตุ | BK1: เดือนเบิกค่าคอมมิชชั่น | BL1: 0.012 | BM1: 0.0135 | BN1: 0.015 | BO1: 0.017 | BP1: 0.0185 | BQ1: 0.022 | BR1: 0.025 | BS1: 0.0275 | BT1: 0.03 | BU1: 0.01 | BV1: 0.015 | BW1: 0.02 | BX1: 500
A2: 46023 | B2: 2026 | C2: 1 | F2: N-RPT/Event | G2: 46047 | H2: ศุภชัย ศรีกาญจนา | I2: Origin Campus khonkaen | J2: B408 | K2: 70000 | S2: อั๋น | U2: ดำเนินการ
A3: 46023 | B3: 2026 | C3: 1 | F3: N-RPT/Event | G3: 46047 | H3: กนกวรรณ ละม้าย | I3: Origin Campus khonkaen | J3: B427 | K3: 100000 | S3: อั๋น | U3: ดำเนินการ
A4: 46054 | B4: 2026 | C4: 2 | F4: N-RPT/Event | G4: 46068 | H4: ณภัสนันท์ ทองคำนุช | I4: Origin Campus khonkaen | J4: B304 | S4: อั๋น | U4: ดำเนินการ
A5: 46054 | B5: 2026 | C5: 2 | F5: N-RPT/Event | G5: 46068 | H5: ภัณฑิรา สิทธิการค้า | I5: Origin Campus khonkaen | J5: B321 | K5: 90000 | S5: อั๋น | U5: ดำเนินการ
A6: 45931 | B6: 2025 | C6: 36 | E6: WAG-SONO25-000698 | F6: N-RPT/Event | G6: 45949 | H6: คุณอานนท์ สมหล่อ | I6: Origin Place Bangna | J6: 510 | K6: 11401.87 | L6: 12200 | P6: 11401.87 | Q6: 1 | S6: หญิง | T6: อาม | U6: ส่งมอบแล้ว
A7: 45839 | B7: 2025 | C7: 46 | E7: WAG-SONO25-000925 | F7: N-RPT/Event | G7: 45850 | H7: บริษัท โปรเกรส แมคคานิค จำกัด | I7: Origin Place Bangna | J7: 540 | K7: 16261.68 | L7: 17400 | P7: 16261.68 | Q7: 1 | S7: หญิง | T7: นุ๊ก | U7: ส่งมอบแล้ว
A8: 45658 | B8: 2025 | C8: 37 | E8: WAG-SONO25-000729 | F8: N-RPT/Event | G8: 45668 | H8: คุณวริษฐา บรรพพงศ์ | I8: Origin Place Bangna | J8: 621 | K8: 79439.25 | L8: 85000 | P8: 79439.25 | Q8: 1 | S8: หญิง | T8: นุ๊ก | U8: ส่งมอบแล้ว
A9: 45870 | B9: 2025 | C9: 8 | F9: N-RPT/Event | G9: 45893 | H9: คุณศรายุทธ ศิวสิริการุณย์ | I9: Origin Place Bangna | J9: 640 | K9: 51100 | M9: 51100 | R9: 1 | S9: หญิง | T9: อาม | U9: ดำเนินการ
A10: 45962 | B10: 2025 | C10: 45 | E10: WAG-SONO25-000773 | F10: N-RPT/Event | H10: คุณสรัญญา วาณิชยโชค | I10: Origin Place Bangna | J10: 646 | K10: 69158.88 | L10: 74000 | P10: 69158.88 | Q10: 1 | S10: หญิง | T10: นุ๊ก | U10: ส่งมอบแล้ว
A11: 45931 | B11: 2025 | C11: 50 | E11: WAG-SONO25-000654 | F11: N-RPT/Event | H11: คุณจินห์จุฑา พงศ์เศรษฐไพศาล | I11: Origin Place Bangna | J11: 704 | K11: 54672.9 | L11: 58500 | P11: 54672.9 | Q11: 1 | S11: หญิง | T11: นุ๊ก | U11: ส่งมอบแล้ว
A12: 45931 | B12: 2025 | C12: 49 | E12: WAG-SONO25-000649 | F12: N-RPT/Event | H12: คุณคณินทร์ สิทธิการ | I12: Origin Place Bangna | J12: 808 | K12: 20560.75 | L12: 22000 | P12: 20560.75 | Q12: 1 | S12: หญิง | T12: นุ๊ก | U12: ส่งมอบแล้ว
A13: 45931 | B13: 2025 | C13: 35 | E13: WAG-SONO25-000647 | F13: N-RPT/Event | G13: 45948 | H13: คุณธนวัฒน์ วาณิชย์สิริกุล | I13: Origin Place Bangna | J13: 832 | K13: 104897.2 | L13: 112240 | P13: 104897.2 | Q13: 1 | S13: หญิง | T13: นุ๊ก | U13: ส่งมอบแล้ว
A14: 45992 | B14: 2025 | C14: 51 | E14: WAG-SONO25-000926 | F14: N-RPT/Event | H14: คุณพิมพ์ลดา มีเฟีย | I14: Origin Place Bangna | J14: 940 | K14: 59532.71 | L14: 63700 | P14: 59532.71 | Q14: 1 | S14: หญิง | T14: นุ๊ก | U14: ส่งมอบแล้ว
A15: 46054 | B15: 2026 | C15: 38 | E15: WAG-SONO26-000144 | F15: N-RPT/Event | G15: 46074 | H15: คุณเหม่ จู เฉิน | I15: Origin Place Bangna | J15: 1138 | K15: 14018.69 | L15: 15000 | P15: 14018.69 | Q15: 1 | S15: หญิง | T15: นุ๊ก | U15: ส่งมอบแล้ว
A16: 45931 | B16: 2025 | C16: 10 | F16: N-RPT/Event | G16: 45949 | H16: คุณนภาพร แย้มวาที | I16: Origin Place Bangna | J16: 1204 | K16: 21500 | M16: 5000 | R16: จองสิทธิ์ | S16: จอส | U16: ดำเนินการ
A17: 45931 | B17: 2025 | C17: 10 | F17: N-RPT/Event | G17: 45949 | H17: คุณธิติวุฒิ หู | I17: Origin Place Bangna | J17: 1239 | K17: 450000 | M17: 230000 | R17: 0.5 | S17: หญิง | T17: นุ๊ก | U17: ดำเนินการ
A18: 45931 | B18: 2025 | C18: 10 | F18: N-RPT/Event | G18: 45949 | H18: คุณวีริสา กิจบุญชัย | I18: Origin Place Bangna | J18: 1241 | K18: 43000 | M18: 5000 | R18: จองสิทธิ์ | S18: หญิง | U18: ดำเนินการ
A19: 45931 | B19: 2025 | C19: 10 | F19: N-RPT/Event | G19: 45949 | H19: คุณวีริสา กิจบุญชัย | I19: Origin Place Bangna | J19: 1241 | K19: 106300 | M19: 5000 | R19: จองสิทธิ์ | S19: หญิง | U19: ดำเนินการ
A20: 45931 | B20: 2025 | C20: 10 | F20: N-RPT/Event | G20: 45949 | H20: คุณวีริสา กิจบุญชัย | I20: Origin Place Bangna | J20: 1241 | K20: 148600 | M20: 3000 | R20: จองสิทธิ์ | S20: หญิง | U20: ดำเนินการ
A21: 46054 | B21: 2026 | C21: 2 | F21: N-RPT/Event | G21: 46071 | H21: คุณณัฐญา วุ้นประสิทธิ์ศักดิ์ | I21: Origin Place Khonkaen | J21: B833 | K21: 36030 | M21: 8015 | R21: 0.5 | S21: จอส | T21: PM | U21: ดำเนินการ
A22: 46023 | B22: 2026 | C22: 1 | F22: N-RPT/Event | G22: 46047 | H22: คุณพิลาวรรณ สาราษฏร์ | I22: Origin Place Khonkaen | J22: B526 | K22: 108360 | M22: 5000 | R22: จองสิทธิ์ | S22: จอส | U22: ดำเนินการ
A23: 46054 | B23: 2026 | C23: 2 | F23: N-RPT/Event | G23: 46054 | H23: คุณพีรพล จ่าเคน | I23: Origin Place Khonkaen | J23: A414 | K23: 300000 | M23: 5000 | R23: จองสิทธิ์ | S23: จอส | U23: ดำเนินการ
A24: 46023 | B24: 2026 | C24: 1 | F24: N-RPT/Event | H24: คุณพิลาวรรณ สาราษฏร์ | I24: Origin Place Khonkaen | J24: B526 | K24: 108360 | M24: 5000 | R24: จองสิทธิ์ | S24: จอส | U24: ดำเนินการ
A25: 46054 | B25: 2026 | C25: 2 | F25: N-RPT/Event | G25: 46054 | H25: คุณพีรพล จ่าเคน | I25: Origin Place Khonkaen | J25: A414 | K25: 300000 | M25: 5000 | R25: จองสิทธิ์ | S25: จอส | U25: ดำเนินการ
A26: 46023 | B26: 2026 | C26: 1 | F26: N-RPT/Event | G26: 46047 | H26: พีรพัฒน์ พัฒนเจริญ | I26: Origin Place Khonkaen | J26: A716 | K26: 30000 | S26: อั๋น | U26: ดำเนินการ
A27: 46023 | B27: 2026 | C27: 1 | F27: N-RPT/Event | G27: 46047 | H27: ณัฐชา จิราวัฒนพงษ์ | I27: Origin Place Khonkaen | J27: A533 | K27: 200000 | S27: อั๋น | U27: ดำเนินการ
A28: 46023 | B28: 2026 | C28: 1 | F28: N-RPT/Event | G28: 46047 | H28: วราพร เทพบรรหาร | I28: Origin Place Khonkaen | J28: A802 | K28: 200000 | S28: อั๋น | U28: ดำเนินการ
A29: 46023 | B29: 2026 | C29: 1 | F29: N-RPT/Event | G29: 46047 | H29: พัชรี เผื่อนงูเหลือม | I29: Origin Place Khonkaen | J29: B527 | K29: 300000 | S29: อั๋น | U29: ดำเนินการ
A30: 46023 | B30: 2026 | C30: 1 | F30: N-RPT/Event | G30: 46047 | H30: ปิยธิดา เมาะราษี | I30: Origin Place Khonkaen | J30: A527 | K30: 27560 | S30: อั๋น | U30: ดำเนินการ
A31: 46023 | B31: 2026 | C31: 1 | F31: N-RPT/Event | G31: 46047 | H31: ศรีจันทร์ ฉินวรรณเลิศ | I31: Origin Place Khonkaen | J31: B531 | K31: 79000 | S31: อั๋น | U31: ดำเนินการ
A32: 46023 | B32: 2026 | C32: 1 | F32: N-RPT/Event | G32: 46047 | H32: ศรีจันทร์ ฉินวรรณเลิศ | I32: Origin Place Khonkaen | J32: B402 | K32: 66000 | S32: อั๋น | U32: ดำเนินการ
A33: 46023 | B33: 2026 | C33: 1 | F33: N-RPT/Event | G33: 46047 | H33: ณััฐพงษ์ รักแก้ว | I33: Origin Place Khonkaen | J33: B713 | K33: 30560 | S33: อั๋น | U33: ดำเนินการ
A34: 46023 | B34: 2026 | C34: 1 | F34: N-RPT/Event | G34: 46047 | H34: ณััฐพงษ์ รักแก้ว | I34: Origin Place Khonkaen | J34: B710 | K34: 31840 | S34: อั๋น | U34: ดำเนินการ
A35: 46023 | B35: 2026 | C35: 1 | F35: N-RPT/Event | G35: 46047 | H35: วราลักษณ์ พรพิพัฒนวงษ์ | I35: Origin Place Khonkaen | J35: A630 | K35: 150000 | S35: อั๋น | U35: ดำเนินการ
A36: 46054 | B36: 2026 | C36: 2 | F36: N-RPT/Event | G36: 46068 | H36: สุกัญญา เด่นกองพล | I36: Origin Place Khonkaen | J36: B201 | S36: อั๋น | U36: ดำเนินการ
A37: 46054 | B37: 2026 | C37: 2 | F37: N-RPT/Event | G37: 46068 | H37: ปวีณา ชัณณกุล | I37: Origin Place Khonkaen | J37: B211 | K37: 377000 | S37: อั๋น | U37: ดำเนินการ
A38: 45870 | B38: 2025 | C38: 8 | F38: N-RPT/Event | G38: 45880 | H38: คุณศิริพร จันทร์ปิง | I38: Origin Play Bangkhunnon | J38: 1012 | K38: 179000 | M38: 94500 | R38: 0.5 | S38: แป้ง | U38: ดำเนินการ
A39: 45870 | B39: 2025 | C39: 8 | F39: N-RPT/Event | G39: 45880 | H39: คุณธนวัฒน์ เคารพาพงศ์ | I39: Origin Play Bangkhunnon | J39: 1512 | K39: 13000 | M39: 11500 | R39: 0.5 | S39: แป้ง | U39: ดำเนินการ
A40: 45870 | B40: 2025 | C40: 8 | E40: WAG-SONO25-000830 | F40: N-RPT/Event | G40: 45880 | H40: คุณพิมพลอย แก่นแก้ว | I40: Origin Play Bangkhunnon | J40: 1908 | K40: 27690 | M40: 16345 | R40: 0.5 | S40: แฮ็ค | T40: แบงค์ | U40: ดำเนินการ
A41: 45870 | B41: 2025 | C41: 8 | F41: N-RPT/Event | G41: 45880 | H41: คุณนวชน สื่อรุ่งเรือง | I41: Origin Play Bangkhunnon | J41: 12A03 | K41: 310930 | M41: 160465 | R41: 0.5 | S41: หญิง | T41: อาม | U41: ดำเนินการ
A42: 45870 | B42: 2025 | C42: 8 | F42: N-RPT/Event | G42: 45880 | H42: คุณชนาชลภ์ เงินประเสริฐศรี | I42: Origin Play Bangkhunnon | J42: 1113 | K42: 80000 | M42: 42500 | R42: 0.5 | S42: แฮ็ค | U42: ดำเนินการ
A43: 45962 | B43: 2025 | C43: 11 | E43: WAG-SONO25-000875 | F43: N-RPT/Event | G43: 45990 | H43: คุณกรรณิกา หาญเวช | I43: Origin Play Bangkhunnon | J43: 12A23 | K43: 12300 | M43: 12300 | R43: 0.5 | S43: แป้ง | T43: แบงค์ | U43: ดำเนินการ
A44: 45809 | B44: 2025 | C44: 6 | E44: WAG-SONO25-000912 | F44: N-RPT/Event | G44: 45820 | H44: คุณบัณฑิตา ทิพย์จักษุ | I44: Origin Play Bangkhunnon | J44: 812 | K44: 167620 | M44: 88810 | R44: 1 | S44: หญิง | T44: อาม | U44: ดำเนินการ
A45: 45839 | B45: 2025 | C45: 7 | F45: N-RPT/Event | G45: 45850 | H45: คุณกนกพัชร์ จงจิตต์ธาดา | I45: Origin Play Bangkhunnon | J45: 1520 | K45: 31000 | M45: 31000 | R45: 1 | S45: หญิง | T45: อาม | U45: ดำเนินการ
A46: 46082 | B46: 2026 | C46: 3 | E46: WAG-SONO26-000184 | F46: N-RPT/Event | G46: 46088 | H46: คุณชาติสยาม นาสูง | I46: Origin Play Bangkhunnon | J46: 1611 | K46: 15800 | M46: 15800 | R46: 1 | S46: แฮ็ค | T46: แบงค์ | U46: ดำเนินการ
A47: 45870 | B47: 2025 | C47: 8 | F47: N-RPT/Event | G47: 45880 | H47: คุณศุภรัตน์ ศรีรัตนะ | I47: Origin Play Bangkhunnon | J47: 922 | K47: 36760 | M47: 5000 | R47: จองสิทธิ์ | S47: แป้ง | U47: ดำเนินการ
A48: 45870 | B48: 2025 | C48: 8 | F48: N-RPT/Event | G48: 45880 | H48: คุณกรญา อุณาโลม | I48: Origin Play Bangkhunnon | J48: 1205 | K48: 12000 | M48: 5000 | R48: จองสิทธิ์ | S48: แป้ง | U48: ดำเนินการ
A49: 45870 | B49: 2025 | C49: 8 | F49: N-RPT/Event | G49: 45880 | H49: คุณโอภาส ลิ้มเกียรติเชิดชู | I49: Origin Play Bangkhunnon | J49: 1507 | K49: 350000 | M49: 5000 | R49: จองสิทธิ์ | S49: แป้ง | U49: ดำเนินการ
A50: 45870 | B50: 2025 | C50: 8 | F50: N-RPT/Event | G50: 45880 | H50: คุณวรรณนภา คชรักษ์ | I50: Origin Play Bangkhunnon | J50: 804 | K50: 200000 | M50: 5000 | R50: จองสิทธิ์ | S50: แฮ็ค | U50: ดำเนินการ
A51: 45870 | B51: 2025 | C51: 8 | F51: N-RPT/Event | G51: 45880 | H51: คุณอริสา ผลบุญ | I51: Origin Play Bangkhunnon | J51: 1421 | K51: 300000 | M51: 5000 | R51: จองสิทธิ์ | S51: แป้ง | U51: ดำเนินการ
A52: 45870 | B52: 2025 | C52: 8 | F52: N-RPT/Event | G52: 45880 | H52: คุณอรุณ งามวิชัยกิจ | I52: Origin Play Bangkhunnon | J52: 1525 | K52: 150000 | M52: 5000 | R52: จองสิทธิ์ | S52: แฮ็ค | U52: ดำเนินการ
A53: 45870 | B53: 2025 | C53: 8 | F53: N-RPT/Event | G53: 45880 | H53: คุณชวนพร เวชนุเคราะห์ | I53: Origin Play Bangkhunnon | J53: 901 | K53: 46900 | M53: 5000 | R53: จองสิทธิ์ | S53: แฮ็ค | U53: ดำเนินการ
A54: 45870 | B54: 2025 | C54: 8 | F54: N-RPT/Event | G54: 45880 | H54: คุณธมลพรรณ์ เพื่อนสงคราม | I54: Origin Play Bangkhunnon | J54: 2008 | K54: 156000 | M54: 5000 | R54: จองสิทธิ์ | S54: แฮ็ค | U54: ดำเนินการ
A55: 45870 | B55: 2025 | C55: 8 | F55: N-RPT/Event | G55: 45880 | H55: คุณอรุษา รัตนะพิสิฐ | I55: Origin Play Bangkhunnon | J55: 1902 | K55: 39000 | M55: 5000 | R55: จองสิทธิ์ | S55: แป้ง | U55: ดำเนินการ
A56: 45870 | B56: 2025 | C56: 8 | F56: N-RPT/Event | G56: 45880 | H56: คุณกนกพร ศักดิ์ตนไท | I56: Origin Play Bangkhunnon | J56: 1401 | K56: 200000 | M56: 3000 | R56: จองสิทธิ์ | S56: หญิง | U56: ดำเนินการ
A57: 45870 | B57: 2025 | C57: 8 | F57: N-RPT/Event | G57: 45880 | H57: คุณธนินี ภักดีพันธุ์ | I57: Origin Play Bangkhunnon | J57: 1601 | K57: 200000 | M57: 3000 | R57: จองสิทธิ์ | S57: หญิง | U57: ดำเนินการ
A58: 45870 | B58: 2025 | C58: 8 | F58: N-RPT/Event | G58: 45880 | H58: คุณธวัลรัตน์ เลิศวนิชกิจกุล | I58: Origin Play Bangkhunnon | J58: 1402 | K58: 136000 | M58: 5000 | R58: จองสิทธิ์ | S58: หญิง | U58: ดำเนินการ
... A82: 45992 | B82: 2025 | C82: 12 | F82: N-RPT/Event | G82: 46004 | H82: คุณชัญญนัษฐ์ อภิรักษ์ขจรเดช | I82: Origin Play Bangkhunnon | J82: 2018 | K82: 412000 | M82: 10000 | R82: จองสิทธิ์ | S82: หญิง | U82: ดำเนินการ
A83: 46082 | B83: 2026 | C83: 3 | E83: WAG-SONO26-000184 | F83: N-RPT/Event | G83: 46088 | H83: คุณพริมรตา อินทร์ถมยา | I83: Origin Play Bangkhunnon | J83: 2803 | K83: 350000 | M83: 20000 | R83: จองสิทธิ์ | S83: หญิง | U83: ดำเนินการ
A84: 46082 | B84: 2026 | C84: 3 | E84: WAG-SONO26-000213 | F84: N-RPT/Event | G84: 46096 | H84: คุณอาทิตย์ ภูเกียรติก้อง | I84: Origin Play Bangkhunnon | J84: 2707 | K84: 350000 | M84: 20000 | R84: จองสิทธิ์ | S84: หญิง | U84: ดำเนินการ
A85: 45962 | B85: 2025 | C85: 55 | E85: WAG-SONO25-000799 | F85: N-RPT/Event | H85: คุณอริสรา เมืองคุ้ม | I85: Origin Play Bangkhunnon | J85: 146-U-Z0905 | K85: 11214.95 | L85: 12000 | P85: 11214.95 | Q85: 1 | S85: หญิง | T85: อาม | U85: ส่งมอบแล้ว
A86: 45870 | B86: 2025 | C86: 21 | E86: WAG-SONO26-000102 | F86: N-RPT/Event | G86: 45880 | H86: คุณจุธาทิพย์ บางศรี | I86: Origin Play Bangkhunnon | J86: 146-U-Z0804 | K86: 101308.41 | L86: 108400 | O86: 62153.28 | P86: 39155.13 | Q86: 0.3865 | S86: แฮ็ค | T86: อาม | U86: ส่งมอบแล้ว
A87: 45809 | B87: 2025 | C87: 39 | E87: WAG-SONO25-000917 | F87: N-RPT/Event | G87: 45820 | H87: คุณวิภารัตน์ มีเมือง | I87: Origin Play Bangkhunnon | J87: 146-U-Z0820 | K87: 56560.75 | L87: 60520 | P87: 56560.75 | Q87: 1 | S87: หญิง | T87: อาม | U87: ส่งมอบแล้ว
A88: 45839 | B88: 2025 | C88: 40 | E88: WAG-SONO25-000916 | F88: N-RPT/Event | G88: 45850 | H88: คุณทัศนีย์ ศิริวรรณ | I88: Origin Play Bangkhunnon | J88: 146-U-Z1517 | K88: 19719.63 | L88: 21100 | P88: 19719.63 | Q88: 1 | S88: หญิง | T88: อาม | U88: ส่งมอบแล้ว
A89: 45839 | B89: 2025 | C89: 41 | E89: WAG-SONO25-000918 | F89: N-RPT/Event | G89: 45850 | H89: คุณอาทิมา สอนไทย | I89: Origin Play Bangkhunnon | J89: 146-U-Z1911 | K89: 39710.28 | L89: 42490 | P89: 39710.28 | Q89: 1 | S89: หญิง | T89: อาม | U89: ส่งมอบแล้ว
A90: 45870 | B90: 2025 | C90: 48 | E90: WAG-SONO25-000835 | F90: N-RPT/Event | G90: 45880 | H90: คุณวิศิษฎ์ ตันติสังวรากูร | I90: Origin Play Bangkhunnon | J90: 146-U-Z1404 | K90: 155962.62 | L90: 166880 | O90: 105366.5 | P90: 50596.12 | Q90: 0.3244 | S90: แฮ็ค | T90: แบงค์ | U90: ส่งมอบแล้ว
A91: 45962 | B91: 2025 | C91: 49 | E91: WAG-SONO25-000870 | F91: N-RPT/Event | G91: 45991 | H91: คุณรวิสรา สุวรรณนิมิตร | I91: Origin Play Bangkhunnon | J91: 146-U-Z0817 | K91: 87829.91 | L91: 93978 | O91: 69004 | P91: 18825.91 | Q91: 0.2143 | S91: แฮ็ค | T91: แบงค์ | U91: ส่งมอบแล้ว
A92: 45962 | B92: 2025 | C92: 11 | F92: N-RPT/Event | G92: 45983 | H92: คุณศักดิ์ หลูอารีย์สุวรรณ | I92: Origin Play Bangsaen | J92: 1408 | K92: 74670 | M92: 42335 | R92: 0.5 | S92: แป้ง | T92: เวฟ | U92: ดำเนินการ
A93: 45962 | B93: 2025 | C93: 11 | F93: N-RPT/Event | G93: 45983 | H93: คุณสิริกัญญา นิลโพธิ์ทอง | I93: Origin Play Bangsaen | J93: 1606 | K93: 185000 | M93: 102500 | R93: 0.5 | S93: แป้ง | T93: เวฟ | U93: ดำเนินการ
A94: 45962 | B94: 2025 | C94: 11 | E94: WAG-SONO25-000852 | F94: N-RPT/Event | G94: 45983 | H94: คุณอระวรรณ แดงโสภา | I94: Origin Play Bangsaen | J94: 1018 | K94: 275550 | M94: 147775 | R94: 0.5 | S94: แป้ง | T94: เวฟ | U94: ดำเนินการ
A95: 45962 | B95: 2025 | C95: 11 | E95: WAG-SONO25-000854 | F95: N-RPT/Event | G95: 45983 | H95: คุณนันทวรรณ นามวงษ์ | I95: Origin Play Bangsaen | J95: 911 | K95: 99900 | M95: 54950 | R95: 0.5 | S95: แป้ง | T95: เวฟ | U95: ดำเนินการ
A96: 45962 | B96: 2025 | C96: 11 | F96: N-RPT/Event | G96: 45984 | H96: คุณชมภูนุช สุภาพล | I96: Origin Play Bangsaen | J96: 1615 | K96: 184120 | M96: 97060 | R96: 0.5 | S96: แป้ง | U96: ดำเนินการ
A97: 45962 | B97: 2025 | C97: 11 | E97: WAG-SONO25-000862 | F97: N-RPT/Event | G97: 45991 | H97: คุณรชากุญช์ ชาติชนก | I97: Origin Play Bangsaen | J97: 1720 | K97: 51540 | M97: 30770 | R97: 0.5 | S97: แป้ง | T97: เวฟ | U97: ดำเนินการ
A98: 45962 | B98: 2025 | C98: 11 | F98: N-RPT/Event | G98: 45990 | H98: คุณพนมศักดิ์ ศิริยา | I98: Origin Play Bangsaen | J98: 2119 | K98: 147700 | M98: 78860 | R98: 0.5 | S98: แป้ง | T98: เวฟ | U98: ดำเนินการ
A99: 45839 | B99: 2025 | C99: 7 | F99: N-RPT/Event | G99: 45850 | H99: คุณพิมผกา สุนทร | I99: Origin Play Bangsaen | J99: 2006 | K99: 17280 | M99: 13640 | R99: 0.5 | S99: แป้ง | T99: เวฟ | U99: ดำเนินการ
A100: 45839 | B100: 2025 | C100: 7 | E100: WAG-SONO26-000027 | F100: N-RPT/Event | G100: 45850 | H100: คุณอริย์ธัช ปลอดขาว | I100: Origin Play Bangsaen | J100: 1901 | K100: 125610 | M100: 67805 | R100: 0.5 | S100: แป้ง | T100: เวฟ | U100: ดำเนินการ
A101: 45992 | B101: 2025 | C101: 12 | E101: WAG-SONO26-000029 | F101: N-RPT/Event | G101: 46004 | H101: คุณจิตรา สุขเจริญ | I101: Origin Play Bangsaen | J101: 2308 | K101: 207000 | M101: 108500 | R101: 0.5 | S101: แป้ง | T101: เวฟ | U101: ดำเนินการ
A102: 46023 | B102: 2026 | C102: 1 | F102: N-RPT/Event | G102: 46031 | H102: คุณณัฐปราย์ ธนโชติจิรันธนิน | I102: Origin Play Bangsaen | J102: 1515 | K102: 19200 | M102: 9600 | R102: 0.5 | S102: แป้ง | T102: เวฟ | U102: ดำเนินการ
A103: 46023 | B103: 2026 | C103: 1 | F103: N-RPT/Event | G103: 46039 | H103: บริษัท พีคอน อินดัสเทรียล จำกัด | I103: Origin Play Bangsaen | J103: 803 | K103: 166230 | M103: 83115 | R103: 0.5 | S103: แป้ง | T103: เวฟ | U103: ดำเนินการ
A104: 45962 | B104: 2025 | C104: 11 | E104: WAG-SONO25-000843 | F104: N-RPT/Event | G104: 45983 | H104: คุณอนงค์รักษ์ ศาลากิจ | I104: Origin Play Bangsaen | J104: 802 | K104: 5000 | M104: 5000 | R104: 1 | S104: แป้ง | T104: เวฟ | U104: ดำเนินการ
A105: 45962 | B105: 2025 | C105: 11 | E105: WAG-SONO25-000850 | F105: N-RPT/Event | G105: 45984 | H105: คุณพิชญ์ ปริญญาจารย์ | I105: Origin Play Bangsaen | J105: 1713 | K105: 5000 | M105: 5000 | R105: 1 | S105: แป้ง | T105: เวฟ | U105: ดำเนินการ
A106: 45839 | B106: 2025 | C106: 7 | F106: N-RPT/Event | G106: 45850 | H106: คุณสุณี เลิศสุรศักดา | I106: Origin Play Bangsaen | J106: 2107 | K106: 5000 | M106: 5000 | R106: 1 | S106: แป้ง | T106: เวฟ | U106: ดำเนินการ
A107: 45992 | B107: 2025 | C107: 12 | E107: WAG-SONO25-000907 | F107: N-RPT/Event | G107: 46011 | H107: คุณกนกวรรณ ฉัตรเพชรรัชต์ | I107: Origin Play Bangsaen | J107: 1709 | K107: 5000 | M107: 5000 | R107: 1 | S107: แป้ง | T107: เวฟ | U107: ดำเนินการ
A108: 46023 | B108: 2026 | C108: 1 | F108: N-RPT/Event | G108: 46051 | H108: คุณตันติมา ซื่อตรงกิจ | I108: Origin Play Bangsaen | J108: 1210 | K108: 18500 | M108: 18500 | R108: 1 | S108: แป้ง | T108: เวฟ | U108: ดำเนินการ
A109: 46054 | B109: 2026 | C109: 2 | E109: WAG-SONO26-000104 | F109: N-RPT/Event | G109: 46061 | I109: Origin Play Bangsaen | J109: 2116 | K109: 3000 | M109: 3000 | R109: 1 | S109: แป้ง | T109: เวฟ | U109: ดำเนินการ
A110: 46082 | B110: 2026 | C110: 3 | E110: WAG-SONO26-000174 | F110: N-RPT/Event | G110: 46083 | H110: คุณสุนทรานี ตรรกสิริทรัพย์ | I110: Origin Play Bangsaen | J110: 2202 | K110: 11000 | M110: 11000 | N110: 10000 | R110: 1 | S110: แป้ง | T110: เวฟ | U110: ดำเนินการ
A111: 46082 | B111: 2026 | C111: 3 | E111: WAG-SONO26-000183 | F111: N-RPT/Event | G111: 46090 | H111: คุณยศวดี ตันสิน | I111: Origin Play Bangsaen | J111: 2220 | K111: 13000 | M111: 13000 | N111: 10000 | R111: 1 | S111: แป้ง | T111: เวฟ | U111: ดำเนินการ
A112: 45931 | B112: 2025 | C112: 10 | F112: N-RPT/Event | G112: 45954 | H112: คุณนพดล ใจเจริญ | I112: Origin Play Bangsaen | J112: 2215 | K112: 11000 | M112: 5000 | R112: จองสิทธิ์ | S112: แป้ง | U112: ดำเนินการ
A113: 45931 | B113: 2025 | C113: 10 | F113: N-RPT/Event | G113: 45954 | H113: คุณสุทัตตา เท่งเจียว | I113: Origin Play Bangsaen | J113: 1501 | K113: 134320 | M113: 5000 | R113: จองสิทธิ์ | S113: แป้ง | U113: ดำเนินการ
A114: 45931 | B114: 2025 | C114: 10 | F114: N-RPT/Event | G114: 45954 | H114: คุณธัญชนก สุวรรณปัญญา | I114: Origin Play Bangsaen | J114: 1204 | K114: 232720 | M114: 5000 | R114: จองสิทธิ์ | S114: แป้ง | U114: ดำเนินการ
A115: 45962 | B115: 2025 | C115: 11 | F115: N-RPT/Event | G115: 45984 | H115: คุณอรรถนัย เปรมศรี | I115: Origin Play Bangsaen | J115: 1708 | K115: 91000 | M115: 5000 | R115: จองสิทธิ์ | S115: แป้ง | U115: ดำเนินการ
A116: 45962 | B116: 2025 | C116: 11 | F116: N-RPT/Event | G116: 45987 | H116: คุณยุทธนา บรรพต | I116: Origin Play Bangsaen | J116: 2212 | K116: 200000 | M116: 10000 | R116: จองสิทธิ์ | S116: แป้ง | U116: ดำเนินการ
A117: 45962 | B117: 2025 | C117: 11 | F117: N-RPT/Event | G117: 45984 | H117: คุณสุรีย์ลักษณ์ จงอยู๋สุข | I117: Origin Play Bangsaen | J117: 1215 | K117: 140000 | M117: 5000 | R117: จองสิทธิ์ | S117: แป้ง | U117: ดำเนินการ
A118: 45962 | B118: 2025 | C118: 11 | F118: N-RPT/Event | G118: 45990 | H118: คุณดารณี อุทัยศรี | I118: Origin Play Bangsaen | J118: 1121 | K118: 88110 | M118: 5000 | R118: จองสิทธิ์ | S118: แป้ง | U118: ดำเนินการ
A119: 45962 | B119: 2025 | C119: 11 | F119: N-RPT/Event | G119: 45990 | H119: คุณพุฒิชัย อินทรักษาทรัพย์ | I119: Origin Play Bangsaen | J119: 1216 | K119: 6500 | M119: 6500 | R119: จองสิทธิ์ | S119: แป้ง | U119: ดำเนินการ
A120: 45839 | B120: 2025 | C120: 7 | F120: N-RPT/Event | G120: 45850 | H120: คุณหทัยทิพย์ นามนัย | I120: Origin Play Bangsaen | J120: 2108 | K120: 185180 | M120: 5000 | R120: จองสิทธิ์ | S120: แป้ง | U120: ดำเนินการ
A121: 45839 | B121: 2025 | C121: 7 | F121: N-RPT/Event | G121: 45850 | H121: คุณสุภัทรา วงษ์รัตนะ | I121: Origin Play Bangsaen | J121: 2016 | K121: 135180 | M121: 5000 | R121: จองสิทธิ์ | S121: แป้ง | U121: ดำเนินการ
A122: 45992 | B122: 2025 | C122: 12 | F122: N-RPT/Event | G122: 46010 | H122: คุณมลิวัลย์ เทพสุภรณ์กุล | I122: Origin Play Bangsaen | J122: 2021 | K122: 156200 | M122: 5000 | R122: จองสิทธิ์ | S122: แป้ง | U122: ดำเนินการ
A123: 46082 | B123: 2026 | C123: 3 | E123: WAG-SONO26-000208 | F123: N-RPT/Event | G123: 46093 | I123: Origin Play Bangsaen | J123: 12A11 | K123: 2000 | M123: 2000 | R123: 1 | S123: แป้ง | T123: เวฟ | U123: ส่งมอบแล้ว
...

Sheet Event Report
A1: No | B1: Project | C1: Event | D1: Event name | E1: Event Date | F1: Year-Month | G1: ลูกค้าที่มา | H1: ลูกค้าแอดไลน์ | I1: จำนวนรับลูกค้า | J1: จำนวนที่ปิดได้ | K1: Conversion rate | L1: rev. | M1: จำนวนตามต่อ
B2: Origin Play Bangkhunnon | C2: Financial day | D2: FND #1 | E2: 45969 | F2: =year(E2)&"-"&MONTH(E2) -> 2025-11 | K2: =J2/I2 -> #DIV/0! | L2: 5406620 | M2: =H2-J2 -> 0 | N2: =IFERROR(__xludf.DUMMYFUNCTION("AI("""")"),"5,406,620.00") -> 5,406,620.00
B3: Origin Play Bangkhunnon | C3: Room Transfer | D3: Transfer #1 | E3: 45990 | F3: =year(E3)&"-"&MONTH(E3) -> 2025-11 | K3: =J3/I3 -> #DIV/0! | L3: 906925 | M3: =H3-J3 -> 0
B4: Origin Play Bangkhunnon | C4: Room Transfer | D4: Transfer #2 | E4: 45991 | F4: =year(E4)&"-"&MONTH(E4) -> 2025-11 | K4: =J4/I4 -> #DIV/0! | L4: 609500 | M4: =H4-J4 -> 0
B5: Origin Play Bangkhunnon | C5: Room Transfer | D5: Transfer #3 | E5: 45998 | F5: =year(E5)&"-"&MONTH(E5) -> 2025-12 | K5: =J5/I5 -> #DIV/0! | L5: 719540 | M5: =H5-J5 -> 0
B6: Origin Play Bangkhunnon | C6: Room Transfer | D6: Transfer #4 | E6: 46004 | F6: =year(E6)&"-"&MONTH(E6) -> 2025-12 | K6: =J6/I6 -> #DIV/0! | L6: 522000 | M6: =H6-J6 -> 0
B7: Origin Place Bangna | C7: Financial day | F7: =year(E7)&"-"&MONTH(E7) -> 1899-12 | K7: =J7/I7 -> #DIV/0! | M7: =H7-J7 -> 0
B8: Origin Place Bangna | C8: Room Transfer | D8: Transfer #1 | E8: 45949 | F8: =year(E8)&"-"&MONTH(E8) -> 2025-10 | K8: =J8/I8 -> #DIV/0! | L8: 1361000 | M8: =H8-J8 -> 0
B9: Origin Place Bangna | C9: Room Transfer | D9: Transfer #2 | E9: 45955 | F9: =year(E9)&"-"&MONTH(E9) -> 2025-10 | I9: 10 | J9: 5 | K9: =J9/I9 -> 0.5 | L9: 716760 | M9: =H9-J9 -> -5
B10: The Origin Bangkae | C10: Financial day | F10: =year(E10)&"-"&MONTH(E10) -> 1899-12 | K10: =J10/I10 -> #DIV/0! | M10: =H10-J10 -> 0
B11: The Origin Bangkae | C11: Room Transfer | D11: Transfer #1 | E11: 45962 | F11: =year(E11)&"-"&MONTH(E11) -> 2025-11 | G11: 95 | H11: 49 | J11: 7 | K11: =J11/I11 -> #DIV/0! | L11: 638040 | M11: =H11-J11 -> 42
B12: The Origin Bangkae | C12: Room Transfer | D12: Transfer #2 | E12: 46011 | F12: =year(E12)&"-"&MONTH(E12) -> 2025-12 | H12: 35 | I12: 35 | J12: 4 | K12: =J12/I12 -> 0.11428571 | L12: 343500 | M12: =H12-J12 -> 31
B13: The Origin Praksa | D13: Transfer #1 | F13: =year(E13)&"-"&MONTH(E13) -> 1899-12 | K13: =J13/I13 -> #DIV/0! | M13: =H13-J13 -> 0
B14: The Origin Praksa | C14: Room Transfer | D14: Transfer #2 | E14: 45949 | F14: =year(E14)&"-"&MONTH(E14) -> 2025-10 | K14: =J14/I14 -> #DIV/0! | L14: 1032600 | M14: =H14-J14 -> 0
B15: The Origin Praksa | C15: Room Transfer | D15: Transfer #3 | E15: 45962 | F15: =year(E15)&"-"&MONTH(E15) -> 2025-11 | G15: 33 | H15: 8 | J15: 5 | K15: =J15/I15 -> #DIV/0! | L15: 305110 | M15: =H15-J15 -> 3
B16: The Origin Praksa | C16: Room Transfer | D16: Transfer #4 | E16: 45969 | F16: =year(E16)&"-"&MONTH(E16) -> 2025-11 | K16: =J16/I16 -> #DIV/0! | L16: 98000 | M16: =H16-J16 -> 0
B17: The Origin Phahol 57 | C17: Financial day | F17: =year(E17)&"-"&MONTH(E17) -> 1899-12 | K17: =J17/I17 -> #DIV/0! | M17: =H17-J17 -> 0
B18: The Origin Phahol 57 | C18: Room Transfer | D18: Transfer #1 | E18: 45969 | F18: =year(E18)&"-"&MONTH(E18) -> 2025-11 | K18: =J18/I18 -> #DIV/0! | L18: 612050 | M18: =H18-J18 -> 0
B19: The Origin Phahol 57 | C19: Room Transfer | D19: Transfer #2 | E19: 45970 | F19: =year(E19)&"-"&MONTH(E19) -> 2025-11 | K19: =J19/I19 -> #DIV/0! | L19: 1331760 | M19: =H19-J19 -> 0
B20: The Origin Phahol 57 | C20: Room Transfer | D20: Transfer #3 | E20: 45984 | F20: =year(E20)&"-"&MONTH(E20) -> 2025-11 | K20: =J20/I20 -> #DIV/0! | L20: 202800 | M20: =H20-J20 -> 0
B21: Origin Play Bangsaen | C21: Financial day | D21: FND #1 | E21: 45955 | F21: =year(E21)&"-"&MONTH(E21) -> 2025-10 | I21: 5 | J21: 4 | K21: =J21/I21 -> 0.8 | M21: =H21-J21 -> -4
B22: Origin Play Bangsaen | C22: Room Transfer | D22: Transfer #1 | E22: 45983 | F22: =year(E22)&"-"&MONTH(E22) -> 2025-11 | G22: 51 | J22: 14 | K22: =J22/I22 -> #DIV/0! | L22: 2270600 | M22: =H22-J22 -> -14
B23: Origin Play Bangsaen | C23: Room Transfer | D23: Transfer #2 | E23: 45991 | F23: =year(E23)&"-"&MONTH(E23) -> 2025-11 | G23: 14 | H23: 11 | I23: 11 | J23: 5 | K23: =J23/I23 -> 0.45454545 | L23: 652610 | M23: =H23-J23 -> 6
B24: Origin Play Bangsaen | C24: Room Transfer | D24: Transfer #3 | E24: 45997 | F24: =year(E24)&"-"&MONTH(E24) -> 2025-12 | H24: 21 | I24: 21 | J24: 6 | K24: =J24/I24 -> 0.28571429 | L24: 868470 | M24: =H24-J24 -> 15
B25: Origin Play Bangsaen | C25: Room Transfer | D25: Transfer #4 | E25: 46004 | F25: =year(E25)&"-"&MONTH(E25) -> 2025-12 | H25: 17 | I25: 17 | J25: 2 | K25: =J25/I25 -> 0.11764706 | L25: 221340 | M25: =H25-J25 -> 15
C26: Room Transfer | D26: Transfer #5 | E26: 46011 | F26: =year(E26)&"-"&MONTH(E26) -> 2025-12 | G26: 21 | H26: 9 | I26: 9 | J26: 1 | K26: =J26/I26 -> 0.11111111 | L26: 95710 | M26: =H26-J26 -> 8
B27: The Origin Kathu-Patong | C27: Financial day | D27: FND #1 | E27: 45949 | F27: =year(E27)&"-"&MONTH(E27) -> 2025-10 | K27: =J27/I27 -> #DIV/0! | L27: 3404520 | M27: =H27-J27 -> 0
B28: The Origin Kathu-Patong | C28: Financial day | D28: FND #2 | E28: 45970 | F28: =year(E28)&"-"&MONTH(E28) -> 2025-11 | K28: =J28/I28 -> #DIV/0! | L28: 970000 | M28: =H28-J28 -> 0
B29: The Origin Kathu-Patong | C29: Wyde | D29: Wyde Creative Talk | E29: 46011 | F29: =year(E29)&"-"&MONTH(E29) -> 2025-12 | K29: =J29/I29 -> #DIV/0! | L29: 639310 | M29: =H29-J29 -> 0
B30: The Origin Kathu-Patong | C30: Room Transfer | D30: Transfer #1 | E30: 46061 | F30: =year(E30)&"-"&MONTH(E30) -> 2026-2 | K30: =J30/I30 -> #DIV/0! | L30: 2600000 | M30: =H30-J30 -> 0
B31: Origin Place Khonkaen | C31: Financial day | D31: FND #1 | E31: 46047 | F31: =year(E31)&"-"&MONTH(E31) -> 2026-1 | J31: 14 | K31: =J31/I31 -> #DIV/0! | L31: 1364480 | M31: =H31-J31 -> -14
B32: Origin Place Khonkaen | C32: Room Transfer | D32: Transfer #1 | E32: 46067 | F32: =year(E32)&"-"&MONTH(E32) -> 2026-2 | G32: 39 | H32: 21 | J32: 8 | K32: =J32/I32 -> #DIV/0! | L32: 909375 | M32: =H32-J32 -> 13
B33: Origin Place Khonkaen | C33: Room Transfer | D33: Transfer #4 | E33: 46102 | F33: =year(E33)&"-"&MONTH(E33) -> 2026-3 | J33: 9 | K33: =J33/I33 -> #DIV/0! | L33: 693187 | M33: =H33-J33 -> -9
B34: SO Origin Siriraj | C34: Financial day | D34: FND #1 | E34: 46096 | F34: =year(E34)&"-"&MONTH(E34) -> 2026-3 | K34: =J34/I34 -> #DIV/0! | L34: 6141280 | M34: =H34-J34 -> 0
B35: SO Origin Siriraj | C35: Condo Sale | D35: มหกรรมบ้านและคอนโด | F35: =year(E35)&"-"&MONTH(E35) -> 1899-12 | K35: =J35/I35 -> #DIV/0! | M35: =H35-J35 -> 0
A36: 1 | B36: Origin Thonglor world - IP | C36: Financial day | E36: 46120 | F36: 46113 | G36: 50 | H36: 25 | I36: 10 | J36: 10 | K36: =IFERROR(J36/I36, 0) -> 1 | L36: 1000000 | M36: 0

Sheet Monthly 
A1: Department | B1: > | C1: WYDE SALES
A2: Choose month | B2: > | C2: MAR 26 | D2: 😀 | E2: 😀 | F2: 😀 | G2: 😀 | H2: 😀 | I2: 😀 | J2: 😀 | N2: > | P2: > | T2: >
C3: =VLOOKUP(C2,'Back up sheet'!$C$15:$D$26,2,0) -> #REF!
C4: MONTHLY PERFORMANCE | D4: YING | E4: PANG | F4: JOSH | G4: HACK | H4: MINT(EDH) | I4: PHON | J4: AUN | K4: B2B | M4: TOTAL | Q4: TEAM JEAB | R4: TEAM AOM | S4: TEAM B2B
C5: เป้าขาย | D5: 3000000 | E5: 3000000 | F5: 3000000 | G5: 2000000 | H5: 0 | I5: 3000000 | J5: 3000000 | K5: 0 | M5: =Sum(D5:K5) -> 17000000 | Q5: =sum(D5:H5) -> 11000000 | R5: =sum(I5:J5) -> 6000000 | S5: =K5 -> 0
C6: ยอด | D6: =SUM(D7) -> #N/A | E6: =SUM(E7) -> #N/A | F6: =SUM(F7) -> #N/A | G6: =SUM(G7) -> #N/A | H6: =SUM(H7) -> #N/A | I6: =SUM(I7) -> #N/A | J6: =SUM(J7) -> #N/A | K6: =SUM(K7) -> #N/A | M6: =SUM(M7) -> #N/A | Q6: =SUM(Q7) -> #N/A | R6: =SUM(R7) -> #N/A | S6: =SUM(S7) -> #N/A
C7: ยอดขาย "2026 ขายใหม่" | D7: =SUMIFS('Sales Ying'!$P:$P,'Sales Ying'!$A:$A,"2026ขายใหม่",'Sales Ying'!$N:$N,C3) -> #N/A | E7: =SUMIFS('Sales Pang'!$P:$P,'Sales Pang'!$A:$A,"2026ขายใหม่",'Sales Pang'!$N:$N,C3) -> #N/A | F7: =SUMIFS('Sales Josh'!$P:$P,'Sales Josh'!$A:$A,"2026ขายใหม่",'Sales Josh'!$N:$N,C3) -> #N/A | G7: =SUMIFS('Sales Hack'!$P:$P,'Sales Hack'!$A:$A,"2026ขายใหม่",'Sales Hack'!$N:$N,C3) -> #N/A | H7: =SUMIFS('Sales Mint'!$P:$P,'Sales Mint'!$A:$A,"2026ขายใหม่",'Sales Mint'!$N:$N,C3) -> #N/A | I7: =SUMIFS('Sales Phon'!$P:$P,'Sales Phon'!$A:$A,"2026ขายใหม่",'Sales Phon'!$N:$N,C3) -> #N/A | J7: =SUMIFS('Sales Aun'!$P:$P,'Sales Aun'!$A:$A,"2026ขายใหม่",'Sales Aun'!$N:$N,C3) -> #N/A | K7: =SUMIFS('Sales B2B'!$P:$P,'Sales B2B'!$A:$A,"2026ขายใหม่",'Sales B2B'!$N:$N,C3) -> #N/A | M7: =Sum(D7:K7) -> #N/A | Q7: =sum(D7:H7) -> #N/A | R7: =sum(I7:J7) -> #N/A | S7: =K7 -> #N/A
C9: Tracking By Lead From
C10: Facebook
C11: Instagram
C12: LINE OA
C13: OPA
C14: หาเอง
C15: Tracking By Contact
C18: Tracking By Status
C19: จอง
C20: ลงทะเบียน
C21: ส่งใบเสนอราคา
C22: ฺBacklog
... C27: งานอื่นๆ
A29: >

Sheet ชีต30

Sheet ชีต31

Sheet DashBoard

Sheet Team PAom
A1: No. | B1: Assign date | C1: Sales Activity | D1: Project /Client | E1: Sales | F1: Deadline | G1: มูลค่าคาดากาณ์ | H1: สถานะ | I1: Design Package | J1: Remark | K1: Next Action
A2: 1 | B2: 25281 | C2: หาเอง | D2: Customers | E2: kathu-patong | F2: คุณกุลชญา คีรีรักษ์ | G2: C828 | I2: Premium(L)
A3: 2 | B3: 25281 | C3: หาเอง | D3: Customers | E3: kathu-patong | F3: คุณกุลชญา คีรีรักษ์ | G3: C428 | I3: Premium(L)
A4: 3 | B4: 25281 | C4: LINE OA | D4: Customers | E4: kathu-patong | F4: Mr.Thi Thanh Tam HOANG | G4: C605 | I4: Medium(M)
A5: 4 | B5: 25281 | C5: LINE OA | D5: Customers | E5: kathu-patong | F5: Oleg Foltyn | G5: B405 | I5: Combo(S)
A6: 5 | B6: 25281 | C6: LINE OA | D6: Customers | E6: kathu-patong | F6: สุวคนธ์ พิทยานันทกิจ | I6: Combo(S)
A7: 6 | B7: 25281 | C7: LINE OA | D7: Customers | E7: kathu-patong | F7: นงลักษณ์ ตั้งขันติกุล | G7: C422 | I7: Premium(L)
A8: 7 | B8: 25281 | C8: LINE OA | D8: Customers | E8: kathu-patong | F8: ชณิตา ปาริเวสัง | G8: B305 | I8: Medium(M)
A9: 8 | B9: 25281 | C9: LINE OA | D9: Customers | E9: kathu-patong | F9: สุวคนธ์ พิทยานันทกิจ | G9: B310 | I9: Medium(M)
A10: 9 | B10: 25281 | C10: LINE OA | E10: kathu-patong | F10: ฐิติวัลคุ์ ลักษณะวิมล | G10: B432 | I10: Premium(L)
A11: 10 | B11: 25281 | C11: LINE OA | E11: kathu-patong | F11: Slimane, Moustapha DAGHMANI | G11: C631 | I11: Medium(M)
A12: 11 | B12: 25281 | E12: kathu-patong | F12: Anthony Fred William BOULANGER | G12: C817 | I12: Premium(L)
A13: 12 | B13: 25281 | E13: tonglor world | F13: pattie | I13: Premium(L)
A14: 13 | B14: 25281 | E14: kathu-patong | F14: บอร์ดแคช ไลน์ออฟฟิเซียล | H14: บอร์ดแคช ไลน์ออฟฟิเซียล
A15: 14 | B15: 25281 | E15: kathu-patong | F15: โทรตามลูกค้าร่วมกิจกรรม GTK | H15: โทรตามลูกค้าร่วมกิจกรรม GTK
A16: 15 | B16: 25282 | E16: kathu-patong | F16: จัดบูธ กระทู้-ภูเก็ต | H16: จัดบูธ กระทู้-ภูเก็ต
A17: 16 | B17: 25282 | E17: kathu-patong | F17: ดูหน้างานบางเทา-ภูเก็ต | H17: ดูหน้างานบางเทา-ภูเก็ต
A18: 17 | B18: 25282 | E18: kathu-patong | F18: พัชร์กันต์ อนันต์นฤนาถ | G18: A419 | I18: Premium(L)
A19: 18 | B19: 25282 | E19: kathu-patong | F19: กุลธิดา ดินแดง | G19: B512 | I19: Medium(M)
A20: 19 | B20: 25282 | E20: kathu-patong | F20: ชาลิสา มัลลัม | G20: C531 | I20: Medium(M)
A21: 20 | B21: 25282 | E21: kathu-patong | F21: อรวรรณ ใจกล้า | G21: B416 | I21: Medium(M)
A22: 21 | B22: 25282 | E22: kathu-patong | F22: ดาริสา กรดสุริกาญจน์ | G22: A325 | I22: Medium(M)
A23: 22 | B23: 25282 | E23: kathu-patong | F23: ศิริลักษณ์ แก้วมณี | G23: C308 | I23: Combo(S)
A24: 23 | B24: 25283 | E24: kathu-patong | F24: Mr.Ghanim Sirelkhatim Ataia | G24: B703 | I24: Premium(L)
A25: 24 | B25: 25283 | E25: kathu-patong | F25: Mr.Ghanim Sirelkhatim Ataia | G25: B704 | I25: Premium(L)
A26: 25 | B26: 25283 | E26: kathu-patong | F26: Mr.Ghanim Sirelkhatim Ataia | G26: B705 | I26: Premium(L)
A27: 26 | B27: 25283 | E27: kathu-patong | F27: Mr.Ghanim Sirelkhatim Ataia | G27: B706 | I27: Premium(L)
A28: 27 | B28: 25283 | E28: kathu-patong | F28: Mr.Ghanim Sirelkhatim Ataia | G28: B707 | I28: Premium(L)
A29: 28 | B29: 25283 | E29: kathu-patong | F29: นส.ลลิตภัทร สุวรรณทิพย์ | G29: A723 | I29: Combo(S)
... A38: 37 | B38: 25284 | E38: kathu-patong | F38: คุณอาไรด้า ชินพงศ์ | G38: C208 | I38: Combo(S)
A39: 38 | B39: 25285 | E39: kathu-patong | F39: สไลด์weekly Update Phuket-Wyde interior | H39: สไลด์weekly Update Phuket-Wyde interior
A40: 39 | B40: 25285 | E40: kathu-patong | F40: โพสต์รายได้+ตามเอกสาร | H40: โพสต์รายได้+ตามเอกสาร
A41: 40 | B41: 25285 | E41: kathu-patong | F41: Slimane, Moustapha DAGHMANI | G41: C631 | H41: Slimane, Moustapha DAGHMANI | I41: Medium(M)
A42: 41 | B42: 25285 | E42: kathu-patong | F42: Mr.Anh Pha Le | G42: C611 | I42: Medium(M)
A43: 42 | B43: 25285 | E43: kathu-patong | F43: คุณชาลิสา มัลลัม | G43: C531 | I43: Combo(S)
A44: 43 | B44: 25285 | E44: kathu-patong | F44: ธนเทพ อนันพิพัฒพงศ์ | G44: B431 | I44: Combo(S)
A45: 44 | B45: 25285 | E45: kathu-patong | F45: คุณชณิตา ปาริเวสัง | G45: B305 | I45: Medium(M)
B46: 25285 | E46: kathu-patong
A47: 45 | B47: 25285 | E47: kathu-patong | F47: โพสต์รายได้+ตามเอกสาร
A48: 46 | B48: 25285 | E48: kathu-patong | F48: เปิด PO-PR lotแรก บ้างส่วน
A49: 47 | B49: 25285 | E49: kathu-patong | F49: ทำ back boq | G49: B601
A50: 48 | B50: 25284 | C50: หาเอง | D50: Retail | E50: After you Pattaya | F50: After you | H50: ปรับแบบรอส่งประเมินราคา | J50: 46120 | K50: รอส่งราคาประเมิน พร้อมเข้าทำงาน
B51: 25284 | C51: หาเอง | D51: Hotel | E51: The sky vile rooftop. Sukumvit 24 | F51: คุณสมศักดิ์ cm | H51: รอปรับ BOQ จาก CM | J51: 46129 | K51: รอ comment BOQ
A52: 49 | B52: 25284 | C52: หาเอง | D52: Retail | E52: R&B karaoke. Donnie | F52: คุณสมพงษ์ cm | H52: รอส่ง BOQ ประชุมกับลูกค้าเกี่ยวกับขอบเขตการเสนอราคา | J52: 46129 | K52: ระหว่างประเมินราคา
A53: 50 | B53: 25284 | C53: หาเอง | D53: Customers | E53: Park Burlington rama3 | F53: สยามมาสเตอร์พีช แอสเสท | G53: Type twin | H53: รอประเมินราคา | J53: 46132
A54: 51 | B54: 25284 | C54: หาเอง | D54: Customers | E54: Park Burlington rama3 | F54: สยามมาสเตอร์พีช แอสเสท | G54: Type C | H54: รอประเมินราคา | J54: 46132
A55: 52 | B55: 25284 | C55: หาเอง | D55: Customers | E55: Sale gallery the bliss Pattaya | F55: Royal prime development | H55: ประชุมลูกค้า 18/04 | J55: 46132
A56: 53 | B56: 25287 | E56: kathu-patong | F56: Mr.Slimane | G56: C631 | I56: Premium(L)
A57: 54 | B57: 25287 | E57: kathu-patong | F57: Mr.DOMINIK POPELAR | G57: B631 | I57: Premium(L)
A58: 55 | B58: 25287 | E58: kathu-patong | F58: Mr.NATHAN KUO WEI | G58: B310 | I58: Combo(S)
A59: 56 | B59: 25287 | E59: kathu-patong | F59: Bryan Fouad Dandan | G59: C601 | I59: Combo(S)
A60: 57 | B60: 25287 | E60: kathu-patong | F60: Mr.Marco Menini | G60: C728 | I60: Combo(S)
A61: 58 | B61: 25287 | E61: kathu-patong | F61: คุณทวีรัฐ สกุมโอม | G61: B418 | I61: Combo(S)
A62: 59 | B62: 25287 | E62: kathu-patong | F62: Thi Thanh Tam HOANG | G62: C605 | I62: Medium(M)
A63: 60 | B63: 25287 | E63: kathu-patong | F63: Ka Ming Lou | G63: C726 | I63: Combo(S)
A64: 61 | B64: 25287 | E64: kathu-patong | F64: Mr.Vincent Alex | G64: A517 | I64: Premium(L)
A65: 62 | B65: 25287 | E65: kathu-patong | F65: Oleg Foltyn | G65: B405 | I65: Combo(S)
A66: 63 | B66: 25292 | E66: kathu-patong | F66: ฐิติวัลคุ์ ลักษณะวิมล | G66: B432 | I66: Premium(L)
A67: 64 | B67: 25292 | E67: kathu-patong | F67: ธนเทพ อนันพิพัฒพงศ์ | G67: B431 | I67: Medium(M)
... A69: 66 | B69: 25292 | E69: kathu-patong | F69: คุณธนายุทธ พูลมา | G69: B314 | I69: Medium(M)
A70: 67 | B70: 25292 | E70: kathu-patong | F70: เปิด PO-PR lot2
A71: 68 | B71: 25292 | E71: kathu-patong | F71: รอชื่อลูกค้า | G71: A607 | I71: Combo(S)
A72: 69 | B72: 25294 | E72: kathu-patong | F72: จันทรา แฮงกี้ | G72: A802
A73: 70 | B73: 25294 | E73: kathu-patong | F73: โพสค่าแนะนำ
A74: 71 | B74: 25295 | E74: kathu-patong | F74: สรุปแมททิเรีย ทั้ง14 ห้องลอตแรก
A75: 72 | B75: 25295 | E75: kathu-patong | F75: ออก memo ฺB405
A76: 73 | B76: 25295 | C76: Call | E76: kathu-patong | F76: ติดต่อลูกค้า 14 คนก่อนเข้างาน
A77: 74 | B77: 25295 | C77: หาเอง | E77: kathu-patong | F77: revise และราคาใหม่ตามที่ลูกค้าปรับ | G77: C631
A78: 75 | B78: 25296 | E78: kathu-patong | F78: ติดต่่อเรื่อง ขอเข้าหน้างานกับนิติกระทู้ | H78: ไม่ได้คำตอบ/ตามพี่ตี๋
A79: 76 | B79: 25303 | C79: หาเอง | E79: kathu-patong | F79: ชัชนันท์ เจริญใจ | G79: A606
A80: 77 | B80: 25303 | E80: kathu-patong | F80: ริช่า/ | G80: C402
A81: 78 | B81: 25303 | E81: kathu-patong | F81: คุณพัชรา/ดีไซน์ 3D | G81: ศุภาลัย
A82: 79 | B82: 25303 | E82: kathu-patong | F82: บางเทา/แพคเกจ
A83: 80 | B83: 25303 | E83: kathu-patong | F83: คุณเรยา /ราคา | G83: B601
A84: 81 | B84: 25303 | E84: kathu-patong | F84: คุณน้อย/ราคา | G84: C428,C828
A85: 82 | B85: 25303 | E85: kathu-patong | F85: Jay huan lee | G85: C504
A86: 83 | B86: 25303 | E86: kathu-patong | F86: Bartosz Zielinski | G86: C606
A87: 84 | B87: 25303 | E87: kathu-patong | F87: Estera Stegintka | G87: c608
A88: 85 | B88: 25303 | E88: kathu-patong | F88: รื่มรม Home diffuser | G88: B2B | H88: รื่มรม Home diffuser ( Packaged )
A89: 86 | B89: 25303 | E89: kathu-patong | F89: VC-LOT3 29 ห้อง Ori | H89: VC-LOT3 29 ห้อง Ori
A90: 87 | B90: 25303 | E90: kathu-patong | F90: คุณนิรา | G90: B333
A91: 88 | B91: 25303 | E91: kathu-patong | F91: คุณเอมมี่ | G91: C414 | H91: เปลี่ยนสีแมททิเรีย
A92: 89 | B92: 25303 | E92: kathu-patong | F92: คุณเมฒวรรณ | G92: ฺB404 | H92: revise ใบเสนอราคา
A93: 90 | B93: 25303 | E93: kathu-patong | F93: คุณแบ | G93: B401
A94: 91 | B94: 25303 | E94: kathu-patong | F94: เทเท สกุลบัตไร | G94: B417
A95: 92 | B95: 25303 | E95: kathu-patong | F95: ฤทัยรัตน์ สกุลบาสิต้า | G95: B617
A96: 93 | B96: 25303 | E96: kathu-patong | F96: วรรณี ทาบาเรียน | G96: C404
A97: 94 | B97: 25303 | E97: kathu-patong | F97: โพสค่่าแนะนำ
A98: 95 | B98: 25303 | E98: kathu-patong | F98: เคลี่ยร์สเปคกับ ผรม | G98: 14 ห้อง
A99: 96 | B99: 25303 | E99: kathu-patong | F99: revise ราคาเคลี่ยร์ดีไซน์คุณแบ | G99: B401
A100: 97 | B100: 25303 | E100: kathu-patong | F100: revise ราคาคุณเมตวรรณ | G100: B404
A101: 98 | B101: 25303 | C101: หาเอง | E101: After you | F101: final ราคา boot Emquartier | H101: รอ PO
A102: 99 | B102: 46122 | C102: หาเอง | E102: Khonkaen | F102: รอเข้างาน | H102: จ่าย 50%
A103: 100 | B103: 46122 | C103: OPA | E103: Khonkaen | F103: รอปรับแบบ-ประเมินราคา | H103: ขอแก้แบบ ครั้งที่ 2 กำหนดการเข้าอยู่ 30/5
A104: 101 | B104: 46128 | E104: kathu-patong | F104: A607/Ms.Rafa
A105: 102 | B105: 46128 | E105: kathu-patong | F105: B417/คุณเทเท สกุลบัตไร
A106: 103 | B106: 46128 | E106: kathu-patong | F106: B806/คุณโมชิน ราซา
A107: 104 | B107: 46128 | E107: kathu-patong | F107: C422/คุณนงลักษณ์ ตั้งขันติกุล
A108: 105 | B108: 46128 | E108: kathu-patong | F108: C606/ Mr.Bartosz Zielinski
A109: 106 | B109: 46128 | E109: kathu-patong | F109: C608/Mr. Pawel
...

Sheet Aun
B2: TEAM P' AOM | C2: ( B2B & B2C)
B5: Daily sales report
B6: Sales : Supakron Potisorn (Aun)
A9: No. | B9: Contact date | C9: Project | D9: Room | E9: Name (Customer) | F9: รายละเอียดการทำงาน | G9: Design Package | H9: คาดยอดขาย | I9: โอกาสปิด (%) | J9: Next Update /Action Plan | K9: Remark
A10: 1 | B10: 25332 | C10: Origin Place Petkasem | D10: 2006 | E10: ไพจิตร ดิสสานนท์ | F10: ✅ จอง | H10: 200000 | I10: มัดจำสิทธิ์ | J10: ส่งบรีฟ designer ทำแบบ | K10: รอคุยรายละเอียด Event Transfer
A11: 2 | B11: 25332 | C11: Origin Place Petkasem | D11: 805 | E11: ศราพร ศราภัยวานิช | F11: ✅ จอง | H11: 39000 | I11: มัดจำสิทธิ์ | J11: ส่งบรีฟ designer ทำแบบ | K11: รอคุยรายละเอียด Event Transfer
A12: 3 | B12: 25332 | C12: Origin Place Petkasem | D12: 508 | E12: จิตราภรณ์ ควรประดิษฐ์ | F12: ✅ จอง | H12: 55000 | I12: มัดจำสิทธิ์ | J12: ส่งบรีฟ designer ทำแบบ | K12: รอคุยรายละเอียด Event Transfer
A13: 4 | B13: 25332 | C13: Origin Place Petkasem | D13: 1003 | E13: อนิวัช ทั้งวงศ์สกุล | F13: ✅ จอง | H13: 300000 | I13: มัดจำสิทธิ์ | J13: ส่งบรีฟ designer ทำแบบ | K13: รอคุยรายละเอียด Event Transfer
A14: 5 | B14: 25332 | C14: Origin Place Petkasem | D14: 1220 | E14: กิตตินันท์ สุขนันที | F14: ✅ จอง | H14: 200000 | I14: มัดจำสิทธิ์ | J14: ส่งบรีฟ designer ทำแบบ | K14: รอคุยรายละเอียด Event Transfer
A15: 6 | B15: 25332 | C15: Origin Place Petkasem | D15: 506 | E15: นารดา แซ่จัง | F15: ยกเลิก | H15: 150000 | I15: มัดจำสิทธิ์ | J15: ส่งบรีฟ designer ทำแบบ | K15: รอคุยรายละเอียด Event Transfer
A16: 7 | B16: 25332 | C16: Origin Place Petkasem | D16: 1615 | E16: อารีย์ เจริญมี | F16: ✅ จอง | H16: 300000 | I16: มัดจำสิทธิ์ | J16: ส่งบรีฟ designer ทำแบบ | K16: รอคุยรายละเอียด Event Transfer
A17: 8 | B17: 25336 | C17: The Klever Residence | E17: บริษัท เอส พาร์ค ทรี จำกัด | F17: ✅ จอง | H17: 220616.88 | I17: มัดจำสิทธิ์ | J17: ส่งบรีฟ designer ทำแบบ | K17: ทำเอกสารส่งมอบ วางบิล
A18: 9 | B18: 25335 | C18: R&B KARAOKE DONGKI THONGLOR | E18: คุณพงษ์ CM | F18: 🔄ส่งใบเสนอราคา | H18: 17401006 | I18: 0.5 | J18: ติดตามใบเสนอราคา 3 Day 15/05/2026
A19: 10 | B19: 25336 | C19: Add work power outlet / Park Burlington type B | E19: คุุณอ้อ Siam masterpice asset | F19: 🔄ส่งใบเสนอราคา | H19: 21186 | I19: 0.9 | J19: ติดตามใบเสนอราคา 3 Day 15/05/2027
A20: 11 | B20: 25336 | C20: Add work power outlet / Park Burlington type D | E20: คุุณอ้อ Siam masterpice asset | F20: 🔄ส่งใบเสนอราคา | H20: 50494 | I20: มัดจำสิทธิ์ | J20: ติดตามใบเสนอราคา 3 Day 15/05/2028
A21: 12 | B21: 25342 | C21: ฺDesign Baan Khun Pang-Luddawan House | E21: K .pang | F21: ติดตามครั้งที่ 2 | H21: 279299 | I21: 0.2 | J21: ติดตามใบเสนอราคา 14 Day 05/06/2028 | K21: ยังไม่ตัดสินใจ/ยังไม่ตัดสินใจ
A22: 13 | B22: 25352 | C22: Build -in GBB-BN plot 16 S type S | E22: บริษัท เอสซแอสเสท คอร์ปอเรช่ัน จำกัด (มหาชน) | F22: ลูกค้าได้ผู้เราหมาแล้ว Close lead | H22: 8778141.1 | I22: 0.5 | J22: E-Bidding 10/06/2026
A23: 14 | B23: 25352 | C23: Build -in GBB-BN plot 16 S type M | E23: บริษัท เอสซแอสเสท คอร์ปอเรช่ัน จำกัด (มหาชน) | F23: ลูกค้าได้ผู้เราหมาแล้ว Close lead | H23: 10077009 | I23: 0.5 | J23: E-Bidding 10/06/2027
A24: 15 | B24: 25352 | C24: Build -in GBB-BN plot 16 S type L | E24: บริษัท เอสซแอสเสท คอร์ปอเรช่ัน จำกัด (มหาชน) | F24: ลูกค้าได้ผู้เราหมาแล้ว Close lead | H24: 16209502 | I24: 0.5 | J24: E-Bidding 10/06/2028
A25: 16 | B25: 25353 | C25: Build -in GBB-PKN plot 16 S type S | E25: บริษัท เอสซแอสเสท คอร์ปอเรช่ัน จำกัด (มหาชน) | F25: ลูกค้าได้ผู้เราหมาแล้ว Close lead | H25: 8778141.1 | I25: 0.5 | J25: E-Bidding 10/06/2029
A26: 17 | B26: 25353 | C26: Build -in GBB-PKN plot 16 S type M | E26: บริษัท เอสซแอสเสท คอร์ปอเรช่ัน จำกัด (มหาชน) | F26: ลูกค้าได้ผู้เราหมาแล้ว Close lead | H26: 10077009 | I26: 0.5 | J26: E-Bidding 10/06/2030
A27: 18 | B27: 25358 | C27: Sky ville Hotel Sukumvit 24 Lounge 37 Floor | E27: K . somsak CM | F27: 🔄ส่งใบเสนอราคา | H27: 5675954.7 | I27: 0.5 | J27: พิจารณาราคา ร่วมกับ 35-36 floor 11/06/2026
A28: 19 | B28: 25358 | C28: Sky ville Hotel Sukumvit 24 Lounge 36 Floor | E28: K . somsak CM | F28: 🔄ส่งใบเสนอราคา | I28: 0.5 | J28: รอใบเสนอราคา ส่ง 11/06/2026 | K28: ส่งใบเสนอราคา
A29: 20 | B29: 25358 | C29: Sky ville Hotel Sukumvit 24 Lounge 35 Floor | E29: K . somsak CM | F29: 🔄ส่งใบเสนอราคา | I29: 0.5 | J29: รอใบเสนอราคา ส่ง 11/06/2027
A30: 21 | B30: 25359 | C30: งาน wallpaper Bedroom 2-3 BAM HOUSE | E30: BAM DAIMOND | F30: 📝 ลงทะเบียน | I30: 0.5 | J30: รอเลื่อก spec และใบเสนอราคา
A31: 22 | B31: 25359 | C31: งานต่อเติมห้องนอน 6 BAM HOUSE | E31: BAM DAIMOND | F31: 📝 ลงทะเบียน | H31: 300000 | I31: 0.5 | J31: รอเลื่อก spec และใบเสนอราคา
A32: 23 | B32: 25360 | C32: Design office k.pae chonburi 80 sq.m | E32: k.pae | F32: 📝 ลงทะเบียน | H32: 200000 | I32: 0.2 | J32: ออกใบเสนอราคา
A33: 24 | B33: 25361 | C33: Renovate painhouse Pattaya | E33: Major Development public company | F33: ยกเลิก | H33: 800000 | I33: 0.2 | J33: ออกใบเสนอราคา
A34: 25 | B34: 25369 | C34: Renovate Mock up room CRAFT CONDO | E34: บริษัท สยามราชดำริ จำกัด | F34: 🔄ส่งใบเสนอราคา | H34: 212421.22 | I34: 0.5 | J34: ติดตามใบเสนอราคา 16/06/2026
A35: 26 | B35: 25371 | C35: Build-in showhouse grand burlington rama 3 type twin | E35: คุุณอ้อ Siam masterpice asset | F35: 📝 ลงทะเบียน | I35: 0.5 | J35: ออกใบเสนอราคา
A36: 27 | B36: 25371 | C36: Build-in showhouse grand burlington rama 3 town Home | E36: คุุณอ้อ Siam masterpice asset | F36: 📝 ลงทะเบียน | I36: 0.5 | J36: ออกใบเสนอราคา
A37: 28
A38: 29
A39: 30
A40: 31
A41: 32
A42: 33
A43: 34
A44: 35
A45: 36
A46: 37
A47: 38
A48: 39
... A57: 47
A58: 48 | K58: รอส่งราคาประเมิน พร้อมเข้าทำงาน
K59: รอ comment BOQ
A60: 49 | K60: ระหว่างประเมินราคา
A61: 50
A62: 51
A63: 52
A64: 53
A65: 54
A66: 55
A67: 56
A68: 57
A69: 58
A70: 59
A71: 60
A72: 61
... A139: 128

Sheet Pon
B2: TEAM P' AOM | C2: ( B2B & B2C)
B5: Daily sales report
B6: Sales : Pornsiri Tistongkum (PON)
A9: No. | B9: Contact date | C9: Project | D9: Room | E9: Name (Customer) | F9: รายละเอียดการทำงาน | G9: Design Package | H9: คาดยอดขาย | I9: โอกาสปิด (%) | J9: Next Update /Action Plan | K9: Remark
A10: 1 | B10: 25334 | C10: The Origin Kathu-Pathong | D10: B507 | E10: Alexander Teplyakov | F10: ✅ จอง | H10: 21500 | I10: มัดจำสิทธิ์ | J10: จ่ายแล้ว
A11: 2 | B11: 25335 | C11: The Origin Kathu-Pathong | D11: C602 | E11: K.Bo Peng | F11: 🔄ส่งใบเสนอราคา | H11: 19500 | I11: 0.9 | J11: ส่งใบราคาใหม่อีกครั้ง
A12: 3 | B12: 25335 | C12: The Origin Kathu-Pathong | D12: C802 | E12: K.Bo Peng | F12: 🔄ส่งใบเสนอราคา | H12: 19500 | I12: 0.9 | J12: ส่งใบราคาใหม่อีกครั้ง
A13: 4 | B13: 25336 | C13: เบลกราเวีย-บางนาพระราม9 | D13: 98/33 | E13: K.เพ็ญ | F13: ✅ จอง | H13: 330000 | I13: 0.5 | J13: ผ่านพี่หมู-พี่เอ กฤษ
A14: 5 | B14: 25336 | C14: The Origin Kathu-Pathong | D14: C330 | E14: K.จริยวัฒน์ ศรียาภัย | F14: ต้องติดตามต่อ | H14: 16900 | I14: 0.2 | J14: 085-4854016
A15: 6 | B15: 25336 | C15: The Origin Kathu-Pathong | D15: C331 | E15: K.จริยวัฒน์ ศรียาภัย | F15: ต้องติดตามต่อ | H15: 16900 | I15: 0.2 | J15: 085-4854016
A16: 7 | B16: 25337 | C16: The Origin Kathu-Pathong | D16: B230 | E16: มณีรัตน์ บุญลาภ | F16: ต้องติดตามต่อ | H16: 50000 | I16: 0.5 | J16: 095-2648935
A17: 8 | B17: 25337 | C17: The Origin Kathu-Pathong | D17: A603 | E17: Mr.Andrea Donalisio | F17: ✅ จอง | H17: 152513 | I17: 0.9
A18: 9 | B18: 25338 | C18: The Origin Kathu-Pathong | D18: A717 | E18: คุณโชติกา รัตนวิริยะพิทักษ | F18: 🔄ส่งใบเสนอราคา | H18: 360000 | I18: 0.5
A19: 10 | B19: 25341 | C19: The Origin Kathu-Pathong | D19: A812 | E19: Mr.Andrea Donalisio | F19: ✅ จอง | H19: 69950 | I19: 0.9
A20: 11 | B20: 25341 | C20: The Origin Kathu-Pathong | D20: A816 | E20: AHTON CHUBCHENKO | F20: ✅ จอง | H20: 69000 | I20: 0.9
A21: 12 | B21: 25342 | C21: The Origin Kathu-Pathong | D21: B310 | E21: คุณชัญญา พิทยานันทกิจ | F21: ✅ จอง | H21: 34080 | I21: 0.9
A22: 13 | B22: 25343 | C22: The Origin Kathu-Pathong | D22: B401 | E22: คุณภณัชกรณ์ สหสันติวรกุล | F22: ✅ จอง | H22: 200000 | I22: 0.9
A23: 14 | B23: 25344 | C23: The Origin Kathu-Pathong | D23: B502 | E23: คุณนัทธพงศ์ แก้วหัวเมือง | F23: ✅ จอง | H23: 21500 | I23: 0.9
A24: 15 | B24: 25345 | C24: The Origin Kathu-Pathong | D24: B507 | E24: Alexander Teplyakov | F24: 🔄ส่งใบเสนอราคา | H24: 21500 | I24: 0.5
A25: 16 | B25: 25346 | C25: The Origin Kathu-Pathong | D25: B711 | E25: อัจฉรา พิเศษเมธา | F25: 🔄ส่งใบเสนอราคา | H25: 160000 | I25: 0.5
A26: 17 | B26: 25351 | C26: The Origin Kathu-Pathong | D26: B806 | E26: คุณโมชิน ราซา | F26: ✅ จอง | H26: 20800 | I26: 0.9
A27: 18 | B27: 25351 | C27: The Origin Kathu-Pathong | D27: C130 | E27: Pramjit Margaret Kaur | F27: ✅ จอง | H27: 31500 | I27: 0.9
A28: 19 | B28: 25351 | C28: The Origin Kathu-Pathong | D28: C131 | E28: Mrs .Johaneke Nicole Van | F28: ✅ จอง | H28: 470000 | I28: 0.5
... A38: 29 | B38: 25355 | C38: The Origin Kathu-Pathong | D38: C730 | E38: Fiona Anne Yung | F38: 🔄ส่งใบเสนอราคา | H38: 42900 | I38: 0.5
A39: 30 | B39: 25358 | C39: The Origin Kathu-Pathong | D39: - | E39: เลือกพรอพ คุณพัชรา | F39: งานอื่นๆ
A40: 31 | B40: 25358 | C40: The Origin Kathu-Pathong | D40: - | E40: เปิดอนุมัติ po-pr lot3 รอบแรก | F40: งานอื่นๆ
A41: 32 | B41: 25358 | C41: So origin Bangtao Beach | D41: B703 | E41: ประชุม บางเทา อัพเดทห้องลูกค้า Mr.Myron Ivan Haluk | F41: ✅ จอง | H41: 1500000 | I41: 0.5
A42: 33 | B42: 25358 | C42: The Origin Kathu-Pathong | D42: - | E42: เสนอราคา voucher lot4 /origin 6ห้อง | F42: งานอื่นๆ | H42: 150000 | I42: 0.9
A43: 34 | B43: 25358 | C43: The Origin Kathu-Pathong | D43: B422 | E43: คุณจันจิรา มณะโสต์ | F43: งานอื่นๆ | H43: 150000 | I43: 0.9
A44: 35 | B44: 25359 | C44: The Origin Kathu-Pathong | D44: C630 | E44: คุณจารุวรรณ พุทธเมฆ | F44: 🔄ส่งใบเสนอราคา | H44: 58200 | I44: 0.5
A45: 36 | B45: 25359 | C45: The Origin Kathu-Pathong | D45: C131 | E45: บรีบแบบสรุปให้เพื่อแก้ไขทำราคาอีกครั้ง | F45: งานอื่นๆ
A46: 37 | B46: 25359 | C46: The Origin Kathu-Pathong | D46: B512 | E46: คุณกุลธิดา ดินแดง | F46: ✅ จอง | H46: 83202 | I46: 0.9
A47: 38 | B47: 25359 | C47: The Origin Kathu-Pathong | D47: B331 | E47: คุณชัยรัตน์ ไฝสุข | F47: ✅ จอง | H47: 224000 | I47: 0.9
A48: 39 | B48: 25359 | C48: The Origin Kathu-Pathong | D48: B622 | E48: กนกณัฏ ทองช่วย | F48: ต้องติดตามต่อ
A49: 40 | B49: 25359 | C49: The Origin Kathu-Pathong | D49: - | E49: เปิดอนุมัติ po-pr lot3 เพิ่มเติม | F49: งานอื่นๆ
A50: 41 | B50: 25359 | C50: The Origin Kathu-Pathong | D50: - | E50: ตามลูกค้าเซ็นส่งมอบ lotแรก (คนไทย) | F50: งานอื่นๆ
A51: 42
A52: 43
A53: 44
A54: 45
A55: 46
A56: 47
A57: 48
A58: 49 | K58: รอส่งราคาประเมิน พร้อมเข้าทำงาน
A59: 50 | K59: รอ comment BOQ
A60: 51 | K60: ระหว่างประเมินราคา
A61: 52
A62: 53
A63: 54
A64: 55
A65: 56
A66: 55
A67: 56
A68: 57
A69: 58
A70: 59
A71: 60
A72: 61
... A139: 128

Sheet Team PJeab
A1: No. | B1: Contact date | C1: Close date | D1: Where | E1: 0 | F1: Project | G1: Name (Customer) | H1: Room no. | I1: Phone | J1: Product Type | K1: Design Package | L1: คาดยอดขาย | M1: โอกาสปิด (%) | N1: SALES | O1: Status | P1: Next Update /Action Plan | Q1: Remark
F2: Origin Place Khonkaen | G2: โศจิรัตน์ เลิศวรวงศ์ | H2: B203 | I2: 0632696253
F3: Origin Place Khonkaen | G3: ฐิติมาศ ทับสกุล | H3: B206 | I3: 0849926654
F4: Origin Place Khonkaen | G4: เนาวรัตน์ บุญช่วย | H4: B214 | I4: 0829469915
F5: Origin Place Khonkaen | G5: อมิตรา อับดุลเลาะห์ | H5: B232 | I5: 0649804570
F6: Origin Place Khonkaen | G6: จันทร์จิรา เชษฐา | H6: B234 | I6: 0928387525
F7: Origin Place Khonkaen | G7: งามตา แพรงาม | H7: B236 | I7: 0956577481
F8: Origin Place Khonkaen | G8: สุรีย์ณา ปลายนา | H8: B301 | I8: 0642466644
F9: Origin Place Khonkaen | G9: เขมรา จีนหวาด | H9: B303 | I9: 0830565882
F10: Origin Place Khonkaen | G10: จงจิตร พิเศษฤทธิ์ | H10: B306 | I10: 0812550608
F11: Origin Place Khonkaen | G11: ลิขิตพงษ์ สามล | H11: B309 | I11: 0960401505
F12: Origin Place Khonkaen | G12: วนิดา สอนวงษ์ | H12: B311 | I12: "0839700988
F13: Origin Place Khonkaen | G13: อนาวินท์ อิงอนุรักษ์สกุล | H13: B312 | I13: 0919155263
G14: นฤมล ยำพะวา | H14: B313 | I14: 0924716999
G15: แพรชมภู วังศกาญจน์ | H15: B314 | I15: 0941936496
G16: ชนนิกานต์ ศรีคำรุณ | H16: B315 | I16: 0942299669
G17: เนตรนภา เนตรภักดี | H17: B319 | I17: 0896055578
G18: กิตติยา ทองสวัสดิ์ | H18: B327 | I18: 0858290533
G19: วีรภัทร นามสวน | H19: B328 | I19: 0909907782
G20: วราพร แผลงฤทธิ์ | H20: B329 | I20: 0955572800
G21: สุรางคนางค์ บำเพ็ญผล | H21: B330 | I21: 0879857271
G22: อานนท์ โมหะหมัดบาราเฮม | H22: B331 | I22: 0909726575
G23: สุวิทย์ วรสิทธิ์ | H23: B332 | I23: 0819171703
G24: มนัฌยา ดอกดวง | H24: B334 | I24: 0614540988
G25: วศิน ภัทรภาณุ | H25: B336 | I25: 0816981919
... G27: มลทิพย์ สีมันตะ | H27: B403 | I27: 0954369194
G28: ธัญชนก สันทนาประสิทธิ์ | H28: B406
G29: สลักจิต คงแสงทอง | H29: B409
G30: กรรณิการ์ หู้เต็ม | H30: B411
G31: กรรณิการ์ หู้เต็ม | H31: B412
G32: กษิดิศ ลีละสกุลมีเกียรติ | H32: B420
G33: ชนนิกานต์ ศรีคำรุณ | H33: B422
G34: วนิดา สอนวงษ์ | H34: B428
G35: ศรีสุดา สกุลเชื้อ | H35: B429
G36: วชิระ เจริญรื่น | H36: B430
G37: รังสิมา เอมสาน | H37: B431
G38: SEOK JUN MOON
G39: ฐิติกา พลางกูร
A50: 48 | B50: 25284 | D50: หาเอง | E50: Retail | F50: After you Pattaya | G50: After you | I50: - | L50: 500000 | N50: AUN | O50: ต้องติดตามต่อ | P50: 46120 | Q50: ปรับแบบรอส่งประเมินราคา
B51: 25284 | D51: หาเอง | E51: Hotel | F51: The sky vile rooftop. Sukumvit 24 | G51: คุณสมศักดิ์ cm | L51: 3000000 | N51: AUN | O51: ต้องติดตามต่อ | P51: 46120 | Q51: รอปรับ BOQ จาก CM
A52: 49 | B52: 25284 | D52: หาเอง | E52: Retail | F52: R&B karaoke. Donnie | G52: คุณสมพงษ์ cm | L52: 7000000 | N52: AUN | O52: ต้องติดตามต่อ | P52: 46122 | Q52: รอส่ง BOQ ประชุมกับลูกค้าเกี่ยวกับขอบเขตการเสนอราคา
A53: 50 | B53: 25284 | D53: หาเอง | E53: Customers | F53: Park Burlington rama3 | G53: สยามมาสเตอร์พีช แอสเสท | H53: Type twin | L53: 1500000 | N53: AUN | O53: ต้องติดตามต่อ | P53: 46122 | Q53: รอประเมินราคา
A54: 51 | B54: 25284 | D54: หาเอง | E54: Customers | F54: Park Burlington rama3 | G54: สยามมาสเตอร์พีช แอสเสท | H54: Type C | L54: 1500000 | N54: AUN | O54: ต้องติดตามต่อ | P54: 46122 | Q54: รอประเมินราคา
A55: 52 | B55: 25284 | D55: หาเอง | E55: Customers | F55: Sale gallery the bliss Pattaya | G55: Royal prime development | L55: 5000000 | N55: AUN | O55: ต้องติดตามต่อ | P55: 46130 | Q55: ประชุมลูกค้า 18/04
A99: 96 | F99: kathu-patong | G99: revise ราคาเคลี่ยร์ดีไซน์คุณแบ | H99: B401 | L99: 200000 | O99: ✅ จอง
A100: 97 | F100: kathu-patong | G100: revise ราคาคุณเมตวรรณ | H100: B404 | L100: 100000 | O100: ต้องติดตามต่อ
A101: 98 | O101: งานอื่นๆ
A102: 99 | O102: งานอื่นๆ
A103: 100 | O103: งานอื่นๆ
O104: งานอื่นๆ
O105: งานอื่นๆ
O106: งานอื่นๆ

Sheet Ying
B1: SALES : YING
B2: **** WEEKLY REPORT : รายงานการทำงานรายสัปดาห์ ระบุการทำงานเกี่ยวกับ ลูกค้าใหม่ที่ยังไม่จอง และ ลูกค้าใน Backlog + งานอื่นๆที่ทำอยู่ ****
I4: สรุปรายวัน
B5: วันที่ | C5: โครงการ | D5: เลขห้อง | E5: ประเภทลูกค้า | F5: สถานะงาน | G5: เสนอราคา/คาดการ(บาท) | H5: รายละเอียด | I5: LEAD ใหม่ วันนี้ (ราย) | J5: ยอดขายใหม่วันนี้ (ราย) | K5: มูลค่าแพ็คเกจที่จองวันนี้ (บาท) | L5: จำนวนเงินจองมัดจำ วันนี้ (บาท) | M5: ยอดชำระ 50/100% ก่อนตกแต่ง วันนี้ (ราย) | N5: ยอดชำระ 50/100% ก่อนตกแต่ง วันนี้ (บาท)
B6: APR
B7: 46116 | C7: Origin Play Bangkunnon | D7: 2301 | E7: คุยลูกค้าใหม่ | F7: ไม่ซื้อแล้ว | G7: 1052000 | H7: เสนอราคาแล้ว ไม่สนใจ | I7: 9 | J7: 1 | K7: =G14 -> 350000 | L7: 20000 | M7: - | N7: -
C8: Knights Bridge Space Sukhumvit-Rama4 | D8: 1812 | E8: คุยลูกค้าใหม่ | F8: ไม่ซื้อแล้ว | G8: 100000 | H8: เสนอราคาแล้ว ไม่สนใจ จะแต่งห้องเอง
C9: Aspire Onnuch station | D9: 335 | E9: คุยลูกค้าใหม่ | F9: ไม่ซื้อแล้ว | G9: 100000 | H9: เสนอราคาแล้ว ไม่สนใจ จะแต่งห้องเอง
C10: Park Origin Thonglor | D10: B2513 | E10: คุยลูกค้าใหม่ | F10: ไม่ซื้อแล้ว | G10: 300000 | H10: ส่งใบเสนอราคาแล้ว / ไม่สนใจ
C11: Origin Plug&Play Sirindhorn Station | D11: B2402 | E11: คุยลูกค้าใหม่ | F11: ไม่ซื้อแล้ว | G11: 200000 | H11: ส่งใบเสนอราคาแล้ว / ไม่สนใจ
C12: Park Origin Thonglor | D12: B4008 | E12: คุยลูกค้าใหม่ | F12: ไม่ซื้อแล้ว | G12: 200000 | H12: หา ผรมเอง
C13: Origin Play Bangkunnon | D13: 919 | E13: คุยลูกค้าใหม่ | F13: ไม่ซื้อแล้ว | G13: 15000 | H13: เสนอราคาฟิลมเพิ่ม / ไม่สนใจ
C14: Origin Place Bangna | D14: 532 | E14: คุยลูกค้าใหม่ | F14: จองสิทธิ์ | G14: 350000 | H14: เสนอ ราคา ลูกค้าจองออกแบบ
C15: Plug ang Play Srinakarin | D15: 1615 | E15: คุยลูกค้าใหม่ | F15: กำลังคุย | G15: 22100 | H15: ส่งใบเสนอราคาแล้ว / รอตัดสินใจ
C16: Origin Play Bangkhunnon | D16: 12A03 | E16: ลูกค้าในBacklog | F16: จ่าย 50% | G16: 310930 | H16: นัดลูกค้าตรวจรับงาน รับชำระงวดสุดท้าย
C17: Origin Play Bangkhunnon | D17: 812 | E17: ลูกค้าในBacklog | F17: จ่าย 50% | G17: 167620 | H17: นัดลูกค้าตรวจรับงาน รับชำระงวดสุดท้าย
B18: 46117 | C18: Origin Play Bangkhunnon | D18: 1909 | E18: ลูกค้าในBacklog | F18: จ่าย 50% | G18: 383710 | H18: รับชำระ ก่อนตกแต่ง 50% | I18: 2 | J18: - | K18: - | L18: - | M18: 1 | N18: =G18 -> 383710
C19: Origin Play Bangkhunnon | D19: 1418 | E19: ลูกค้าในBacklog | F19: จองสิทธิ์ | G19: 26300 | H19: นัดคุุยรีควายเม้นต์
C20: Origin Play Bangkhunnon | D20: 802 | E20: คุยลูกค้าใหม่ | F20: กำลังคุย | G20: 19610 | H20: นัดเลือกม่าน
C21: Origin Play Bangkhunnon | D21: 2707 | E21: ลูกค้าในBacklog | F21: จองสิทธิ์ | G21: 350000 | H21: นัด คุยบรีฟออกแบบ เพื่อปรับแบบ
C22: Origin Place Bangna | D22: 532 | E22: ลูกค้าในBacklog | F22: จองสิทธิ์ | G22: 350000 | H22: คุยบรีฟออกแบบ / เสนอแบบเฟอร์นิเจอร์เพิ่มเติม
C23: Origin Play Bangkhunnon | D23: 2207 | E23: ลูกค้าในBacklog | F23: จองสิทธิ์ | G23: 220000 | H23: นัด คุยแบบครั้งสุดท้าย และ สรุปรายการตกแต่ง เลือกม่าน
C24: Origin Place Bangna | D24: 710 | E24: คุยลูกค้าใหม่ | F24: กำลังคุย | G24: 24400 | H24: เสนอราคาม่าน / รอตัดสินใจ
B25: 46120 | C25: Origin Place Bangna | D25: 810 | E25: คุยลูกค้าใหม่ | F25: กำลังคุย | G25: 24400 | H25: เสนอราคาม่าน / รอตัดสินใจ | I25: 1 | J25: - | K25: - | L25: - | M25: - | N25: -
C26: Origin Play Bangkhunnon | D26: 1703 | E26: ลูกค้าในBacklog | F26: จ่าย 100%ก่อนตกแต่ง | G26: 28000 | H26: นัดส่งมอบงาน
C27: Origin Play Bangkhunnon | D27: 919 | E27: ลูกค้าในBacklog | F27: จ่าย 100%ก่อนตกแต่ง | G27: 16600 | H27: นัดส่งมอบงาน
C28: Prodigy | D28: 642 | E28: ลูกค้าในBacklog | F28: จองสิทธิ์ | G28: 450000 | H28: นัดวัดที่หน้างาน
B29: 46122 | C29: Park Origin Thonglor | D29: C4207 | E29: ลูกค้าในBacklog | F29: จ่าย 100%ก่อนตกแต่ง | G29: 172000 | H29: ลค นัดดูความคืบหน้า | I29: 1 | J29: - | K29: - | L29: - | M29: - | N29: -
C30: KNB space SK- rama 4 | D30: 2008 | E30: ลูกค้าในBacklog | F30: จ่าย 50% | G30: 735440 | H30: เลือกม่าน ที่โครงการ
C31: Origin Place Bangna | D31: 708 | E31: คุยลูกค้าใหม่ | F31: กำลังคุย | G31: 88250 | H31: นัดคุยบรีฟงานตกแต่ง วัดพื้นที่
B32: 46123 | C32: Origin Play Bangkhunnon | D32: 1418 | E32: ลูกค้าในBacklog | F32: จองสิทธิ์ | G32: 26300 | H32: คุุยลคปรับใบเสนอราคา | I32: - | J32: - | K32: - | L32: - | M32: - | N32: -
C33: ออริจิ้น บางแค | D33: A228 | E33: ลูกค้าในBacklog | F33: จองสิทธิ์ | G33: 108000 | H33: คุุยลคปรับใบเสนอราคา
C34: Place bangna | D34: 532 | E34: ลูกค้าในBacklog | F34: จองสิทธิ์ | G34: 350000 | H34: ทำบรีฟออกแบบให้ทีมออกแบบ
B35: 46124 | C35: Origin Play Bangkhunnon | D35: 2513 | E35: ลูกค้าในBacklog | F35: จองสิทธิ์ | G35: 26000 | H35: ตามลูกค้ามาเลือกม่าน / เสนอแพ็คเพิ่ม | I35: - | J35: - | K35: - | L35: - | M35: - | N35: -
C36: Origin Play Bangkhunnon | D36: 2707 | E36: ลูกค้าในBacklog | F36: จองสิทธิ์ | G36: 350000 | H36: ตามคุยรับบรีฟเพิ่มเติม
C37: Origin Place Bangna | D37: 1239 | E37: ลูกค้าในBacklog | F37: จองสิทธิ์ | G37: 450000 | H37: ตามอัพเดต ความคืบหน้า การเข้างาน
B38: 46132 | C38: Origin Place Bangna | D38: 708 | E38: ลูกค้าใหม่ตามต่อ | F38: กำลังคุย | G38: 88250 | H38: ทำใบเสนอราคา | I38: - | J38: - | K38: - | L38: - | M38: 1 | N38: 26300
C39: Place bangna | D39: 532 | E39: ลูกค้าในBacklog | F39: จองสิทธิ์ | G39: 350000 | H39: ตามคุุยบรีฟเพิ่มเติม
C40: Origin Place Bangna | D40: 1239 | E40: ลูกค้าในBacklog | F40: จ่าย 50% | G40: 450000 | H40: ตามอัพเดต ความคืบหน้า
C41: Origin Play Bangkhunnon | D41: 1418 | E41: ลูกค้าในBacklog | F41: จ่าย 100%ก่อนตกแต่ง | G41: 26300 | H41: ทำใบเสนอราคา / ตามนัดเก็บเงิน
C42: KNB rama 4 | D42: 2008 | E42: ลูกค้าในBacklog | F42: จ่าย 50% | G42: 735440 | H42: ตามอัพเดต ความคืบหน้า ตามผรม เข้างาน
B43: 46133 | C43: so kaset | D43: 1406 | E43: คุยลูกค้าใหม่ | F43: กำลังคุย | G43: 254000 | H43: คุยลูกค้าใหม่ เสนอแพ็คเกจ | I43: 1 | J43: - | K43: - | L43: - | M43: - | N43: -
C44: Origin Play Bangkhunnon | D44: 2513 | E44: ลูกค้าในBacklog | F44: จองสิทธิ์ | G44: 26000 | H44: นัดเลือกม่านวอลล์
B45: 46134 | C45: prodigy โครงนอก | D45: 642 | E45: ลูกค้าในBacklog | F45: จองสิทธิ์ | G45: 450000 | H45: นัดคุยเสนอแบบครั้งที่ 1 | I45: 1 | J45: - | K45: - | L45: - | M45: - | N45: -
C46: Origin Play Bangkhunnon | D46: 2111 | E46: คุยลูกค้าใหม่ | F46: กำลังคุย | G46: 120000 | H46: เสนอแพ็คให้ลูกค้า / รอตัดสินใจ
C47: Origin Play Bangkhunnon | D47: 2707 | E47: ลูกค้าในBacklog | F47: จองสิทธิ์ | G47: 350000 | H47: ทำบรีฟออกแบบเพิ่มเติมให้ทีมออกแบบ
B48: 46135 | C48: สิรินธร | D48: A1415 | E48: ลูกค้าในBacklog | F48: จ่าย 50% | G48: 189300 | H48: นัดส่งมอบงาน/ นัดรับชำระ | I48: 23 | J48: - | K48: - | L48: - | M48: 2 | N48: =G50+G49 -> 22610
C49: Origin Play Bangkunnon | D49: 1804 | E49: ลูกค้าในBacklog | F49: จ่าย 100%ก่อนตกแต่ง | G49: 3000 | H49: ทำใบเสนอราคา / สรุปแ็คเกจ
C50: Origin Play Bangkunnon | D50: 802 | E50: ลูกค้าในBacklog | F50: จ่าย 100%ก่อนตกแต่ง | G50: 19610 | H50: ทำใบเสนอราคา / ตามนัดเก็บเงิน
C51: Origin Play Bangkunnon | D51: 1412 | E51: คุยลูกค้าใหม่ | F51: กำลังคุย | G51: 98000 | H51: ตามลค = รอนัดคุยหน้างาน
C52: Origin Play Bangkhunnon | D52: 2804 | E52: คุยลูกค้าใหม่ | F52: กำลังคุย | G52: 150000 | H52: ตามลค = รอนัดคุยหน้างาน
C53: Origin Play Bangkunnon | D53: 1822 | E53: คุยลูกค้าใหม่ | F53: กำลังคุย | G53: 150000 | H53: ตามลค = รอนัดคุยหน้างาน
C54: soho bangkok ratchada | D54: 2021 | E54: คุยลูกค้าใหม่ | F54: ไม่ซื้อแล้ว | G54: 250000 | H54: ตามลค = ซื้อเองแล้ว
C55: Plug ang Play Nonthaburi Station | D55: 2437 | E55: คุยลูกค้าใหม่ | F55: กำลังคุย | G55: 120000 | H55: ตามลค = กำลังพิจารณา เดี๋ยวแจ้งกลับ
C56: Park Origin Chula Samyan | D56: 3707 | E56: คุยลูกค้าใหม่ | F56: กำลังคุย | G56: 600000 | H56: ตามลค = ตามนัดลูกค้าคุยหน้างาน 18/04/26
C57: Nonthaburi station | D57: 2139 | E57: CALL | F57: ไม่ซื้อแล้ว | G57: - | H57: หาซื้อเอง
C58: Knights Bridge Space Sukhumvit-Rama4 | D58: 1905 | E58: CALL | F58: ไม่ซื้อแล้ว | G58: - | H58: ไม่อยากทำแล้ว
C59: Park Origin Thonglor | D59: B2610 | E59: CALL | F59: ไม่ซื้อแล้ว | G59: - | H59: ตามลค = หาผรมเองแล้ว
C60: Origin Plug&Play Sirindhorn Station | D60: B2402 | E60: CALL | F60: ไม่ซื้อแล้ว | G60: - | H60: ตกแต่งแล้ว
C61: Origin Plug&Play Sirindhorn Station | D61: A712 | E61: CALL | F61: ไม่ซื้อแล้ว | G61: - | H61: ไม่่สนใจ อยู่ไปแล้ว
C62: Origin Plug&Play Sirindhorn Station | D62: C1905 | E62: CALL | F62: ไม่ซื้อแล้ว | G62: - | H62: ไม่่สนใจ อยู่ไปแล้ว
C63: Origin Plug&Play Sirindhorn Station | D63: A1106 | E63: CALL | F63: ไม่ซื้อแล้ว | G63: - | H63: ยังไม่สนใจ
C64: Origin Plug&Play Sirindhorn Station | D64: B1016 | E64: CALL | F64: ไม่ซื้อแล้ว | G64: - | H64: ซื้อของแต่งเองแล้ว
C65: Origin Plug&Play Sirindhorn Station | D65: B905 | E65: CALL | F65: ไม่ซื้อแล้ว | G65: - | H65: ลคเก่า / ตามซื้อเพิ่ม = ยังไม่สนใจ
C66: Origin Plug&Play Sirindhorn Station | D66: C2001 | E66: CALL | F66: ไม่ซื้อแล้ว | G66: - | H66: ไม่ตอบ
C67: Origin Plug&Play Sirindhorn Station | D67: C12A17 | E67: CALL | F67: ไม่ซื้อแล้ว | G67: - | H67: ไม่่สนใจ อยู่ไปแล้ว
C68: Origin Plug&Play Sirindhorn Station | D68: B701 | E68: CALL | F68: ไม่ซื้อแล้ว | G68: - | H68: ไม่ตอบ
C69: Origin Plug&Play Sirindhorn Station | D69: C1612 | E69: CALL | F69: ไม่ซื้อแล้ว | G69: - | H69: ไม่ตอบ
C70: Origin Plug&Play Sirindhorn Station | D70: C2003 | E70: CALL | F70: ไม่ซื้อแล้ว | G70: - | H70: ลคเก่า / ตามซื้อเพิ่ม = ยังไม่สนใจ
... C72: Origin Plug&Play Sirindhorn Station | D72: A714 | E72: CALL | F72: ไม่ซื้อแล้ว | G72: - | H72: ติดต่อไม่ได้
C73: Origin Plug&Play Sirindhorn Station | D73: 1005 | E73: CALL | F73: ไม่ซื้อแล้ว | G73: - | H73: ขอคิดดูก่อน / สนใจเมื่อไร จะติดต่อ
B74: 46136 | C74: so kaset | D74: 1406 | E74: ลูกค้าใหม่ตามต่อ | F74: กำลังคุย | G74: 254000 | H74: ทำใบเสนอราคา | I74: 12 | J74: - | K74: - | L74: - | M74: - | N74: -
C75: ทองหล่อ | D75: B2511 | E75: ประเภทงาน | F75: สถานะงาน | G75: - | H75: ลูกค้า VVIP/ส่งมอบไปแล้ว / ตามเคลมงานโคมไฟ
C76: เพลส บางนา | D76: 532 | E76: ลูกค้าในBacklog | F76: จองสิทธิ์ | G76: 350000 | H76: เสนอแบบครั้งที่ 1
C77: Origin Plug&Play Sirindhorn Station | D77: A1016 | E77: CALL | F77: ไม่ซื้อแล้ว | G77: - | H77: ตามลค = ทำไปแล้ว ไม่สนใจทำเพิ่ม
C78: Origin Plug&Play Sirindhorn Station | D78: A1701 | E78: CALL | F78: ไม่ซื้อแล้ว | G78: - | H78: ตามลค = ไม่ตกแต่ง ซื้อของเอง
C79: Origin Plug&Play Sirindhorn Station | D79: A2114 | E79: CALL | F79: ไม่ซื้อแล้ว | G79: - | H79: ตามลค = ปล่อยเช่าไปแล้ว
C80: Srinakarin | D80: 1912 | E80: CALL | F80: ไม่ซื้อแล้ว | G80: - | H80: ตามลค = ยังไม่สนใจ ถ้าสนใจจะติดต่อ
C81: Srinakarin | D81: 2303 | E81: CALL | F81: ไม่ซื้อแล้ว | G81: - | H81: ตามลค = ต่างชาติ ตแต่งห้องเอง
C82: Srinakarin | D82: 2707 | E82: CALL | F82: ไม่ซื้อแล้ว | G82: - | H82: ตามลค = ติดต่อไม่ได้
C83: Srinakarin | D83: 2716 | E83: CALL | F83: ไม่ซื้อแล้ว | G83: - | H83: ตามลค = ไม่ตกแต่ง งบน้อย
C84: Srinakarin | D84: 2012 | E84: CALL | F84: ไม่ซื้อแล้ว | G84: - | H84: ตามลค = ไม่่ตกแต่ง
C85: Srinakarin | D85: 1423 | E85: CALL | F85: ไม่ซื้อแล้ว | G85: - | H85: ตามลค = ตามซื้อเพิ่ม ยังไม่สนใจ
C86: Srinakarin | D86: 1919 | E86: CALL | F86: ไม่ซื้อแล้ว | G86: - | H86: ตามลค = ตามซื้อเพิ่ม ยังไม่สนใจ
C87: Srinakarin | D87: 2215 | E87: CALL | F87: ไม่ซื้อแล้ว | G87: - | H87: ตามลค = ไม่ตกแต่่ง เคยติดม่านไปแล้ว
C88: Srinakarin | D88: 2802 | E88: CALL | F88: ไม่ซื้อแล้ว | G88: - | H88: ตามลค = ไม่ตกแต่งอะไร หาซื้อเฟอร์เอง
B89: 46137 | C89: KNB rama 4 | D89: 2106 | E89: ลูกค้าในBacklog | F89: จ่าย 100%ก่อนตกแต่ง | G89: 24500 | H89: คุยลค เสนอ งานตกแต่งเพิ่มเติม | I89: 5 | J89: - | K89: - | L89: - | M89: 1 | N89: 10000
C90: Origin Play Bangkunnon | D90: 802 | E90: ลูกค้าในBacklog | F90: จ่าย 100%ก่อนตกแต่ง | G90: 19610 | H90: นัดคุยที่โครงการ / เลือกวอลล์เพิ่ม
C91: Origin Play Bangkunnon | D91: 1909 | E91: ลูกค้าในBacklog | F91: จ่าย 50% | G91: 383710 | H91: นัดคุย ผรม / วัดที่หน้างาน
C92: Origin Play Bangkunnon | D92: 2224 | E92: ลูกค้าในBacklog | F92: จ่าย 100%ก่อนตกแต่ง | G92: 10000 | H92: นัดรับชำระ งานกรุกระจกเงา
C93: Origin Play Bangkunnon | D93: 1418 | E93: ลูกค้าในBacklog | F93: จ่าย 100%ก่อนตกแต่ง | G93: 21300 | H93: นัดคุย ผรม / วัดที่หน้างาน
C94: KNB rama 4 | D94: 1403 | E94: CALL | F94: ไม่ซื้อแล้ว | G94: 28000 | H94: ตามลค = เสนอราคากระจกเงาติดผนัง
C95: KNB rama 4 | D95: 1908 | E95: CALL | F95: ไม่ซื้อแล้ว | G95: - | H95: ตามลค = ไม่สนใจ
C96: so kaset | D96: 1404 | E96: CALL | F96: ไม่ซื้อแล้ว | G96: - | H96: ตามลค = ติดต่อไม่ได้
C97: KNB rama 4 | D97: 2509 | E97: CALL | F97: ไม่ซื้อแล้ว | G97: - | H97: ตามลค = ไม่อยู่ห้อง ยังไม่มีแพลนจะอยู่
C98: KNB rama 4 | D98: 1408 | E98: CALL | F98: ไม่ซื้อแล้ว | G98: - | H98: ตามลค = สนใจแต่เดี๋ยวสะดวกจะติดต่อกลับ
C99: ทำใบส่งมอบ | D99: - | E99: ทำเอกสาร | F99: - | G99: - | H99: ทำใบส่งมอบงาน APR26
B100: 46138 | C100: สาทร | D100: 3124 | E100: ลูกค้าในBacklog | F100: จ่าย 50% | G100: 256400 | H100: นัดส่งมอบงาน= ตรวจงานแล้ว / จะชำระ วันที่ 28 | I100: 3 | J100: - | K100: - | L100: - | M100: - | N100: -
C101: so kaset | D101: 807 | E101: ลูกค้าในBacklog | F101: จ่าย 50% | G101: 271850 | H101: นัดรับชำระส่งมอบงาน
C102: so kaset | D102: 1014 | E102: CALL | F102: ไม่ซื้อแล้ว | G102: - | H102: ตามลค = ติดต่อไม่ได้
...

Sheet ชีต32

Sheet Pang
A1: No. | B1: Contact date | C1: Close date | D1: Where | E1: Clients type | F1: Project | G1: Name (Customer) | H1: ประเภทลูกค้า | I1: Room no | J1: สถานะงาน | K1: Product Type | L1: คาดยอดขาย | M1: โอกาสปิด (%) | N1: Next Update | O1: SALES | P1: สถานะปัจจุบัน | Q1: Close/Inprogress | R1: Follow up | S1: Status | T1: Remark | V1: LEAD ใหม่ วันนี้ (ราย) | W1: ยอดขายใหม่วันนี้ (ราย) | X1: มูลค่าแพ็คเกจที่จองวันนี้ (บาท) | Y1: จำนวนเงินจองมัดจำ วันนี้ (บาท) | Z1: ยอดชำระ 50/100% ก่อนตกแต่ง วันนี้ (ราย) | AA1: ยอดชำระ 50/100% ก่อนตกแต่ง วันนี้ (บาท)
A2: 1 | B2: 46106 | D2: หาเอง | F2: Park Origin Ratchathewi | G2: คุณพสุชกร พงษ์เสวลักษณ์ | H2: ลูกค้าในBacklog | I2: 2310 | J2: ✅ จอง | K2: EQ ซ่อมแผ่นดินไหว | L2: 285396 | M2: 1 | O2: Pang | P2: Closed | Q2: =iferror(vlookup(S2,'Back up'!$B$2:$C$18,2,0),"") -> Close Lead | R2: Line | S2: ลูกค้าชำระเงินเรียบร้อย
A3: 2 | B3: 46107 | D3: OPA | F3: The Origin Sukhumvit Praksa | G3: คุณสิทธิกร กฤตยานำสิน | I3: 3316 | J3: ✅ จอง | K3: Built-in | L3: 53000 | M3: 1 | O3: Pang | P3: Closed | Q3: =iferror(vlookup(S3,'Back up'!$B$2:$C$18,2,0),"") -> Close Lead | R3: Line | S3: ลูกค้าชำระเงินเรียบร้อย
A4: 3 | B4: 46107 | D4: OPA | F4: บางแสน | I4: 1507 | J4: ✅ จอง | K4: Curtain | L4: 12000 | N4: รอ ลค ตัดสินใจ | O4: Pang | P4: Quotation | Q4: =iferror(vlookup(S4,'Back up'!$B$2:$C$18,2,0),"") -> Inprogress | R4: Line | S4: ส่งใบราคาหรือ ข้อมูลแพ็คเกจให้กับลูกค้าแล้ว
A5: 4 | B5: 46108 | D5: LINE OA | F5: E22 | G5: คุณ เค | I5: 1737 | J5: ✅ จอง | K5: Design&turnkey | L5: 200000 | M5: มัดจำ | N5: 05.04.26 ลูกค้าเลือกสีวัสดุ | O5: Pang | P5: Lead | Q5: =iferror(vlookup(S5,'Back up'!$B$2:$C$18,2,0),"") | R5: Line
A6: 5 | B6: 46108 | D6: OPA | F6: Origin Play Bangsaen | G6: บางแสน | I6: 1716 | J6: ✅ จอง | K6: Curtain | O6: Pang | Q6: =iferror(vlookup(S6,'Back up'!$B$2:$C$18,2,0),"")
A7: 6 | B7: 46116 | D7: OPA | F7: The Origin Sukhumvit Praksa | I7: 3113 | J7: ✅ จอง | N7: คุยรายละเอียดงานบิ้วที่อยาก เพื่อทำราคาส่ง | O7: Pang | Q7: =iferror(vlookup(S7,'Back up'!$B$2:$C$18,2,0),"")
A8: 7 | D8: OPA | F8: The Origin Sukhumvit Praksa | I8: 1401 | J8: ✅ จอง | K8: wallcovering | O8: Pang
A9: 8 | D9: หาเอง | F9: บางขุน นน | I9: 1210 | J9: ✅ จอง | N9: ทำเอกสาร ยื่น นิติ เรื่องอนุมัติ ขอเข้างาน | O9: Pang
A10: 9 | B10: 46117 | F10: The Origin Sukhumvit Praksa | I10: 1218 | J10: ✅ จอง | N10: ลค สรุปรายการเพื่อทำราคา | O10: Pang
A11: 10 | D11: OPA | F11: The Origin Sukhumvit Praksa | I11: 1711 | J11: ✅ จอง | K11: Built-in | L11: 50000 | N11: 05.04.26 คุยรายละเอียดสินค้าเพื่อทำราคา 07.04.26 ทำราคาส่งให้ลูกค้าตามรายการ | O11: Pang | Q11: =iferror(vlookup(S11,'Back up'!$B$2:$C$18,2,0),"")
A12: 11 | B12: 46119 | D12: OPA | F12: The Origin Sukhumvit Praksa | I12: 2103 | J12: ✅ จอง | K12: Built-in | L12: 104100 | M12: 1 | N12: ส่งมอบงาน | O12: Pang | P12: Closed | Q12: =iferror(vlookup(S12,'Back up'!$B$2:$C$18,2,0),"") -> Close Lead | R12: Line | S12: ลูกค้าชำระเงินเรียบร้อย
A13: 12 | D13: OPA | F13: The Origin Sukhumvit Praksa | I13: 2110 | J13: ✅ จอง | K13: Built-in | L13: 11130 | M13: 1 | N13: 07.04.26 ทำเอกสารใบเสร็จ | O13: Pang | P13: Closed | Q13: =iferror(vlookup(S13,'Back up'!$B$2:$C$18,2,0),"") -> Close Lead | R13: Line | S13: ลูกค้าชำระเงินเรียบร้อย
A14: 13 | D14: LINE OA | F14: Origin Play Bangsaen | G14: คุณจินตนา วงศ์มหาพร | I14: 12A21 | J14: ✅ จอง | K14: wallcovering | L14: 17500 | M14: 1 | N14: 07.04.26 ทำใบเสนอราคาพร้อมเก็บชำระ | O14: Pang | Q14: =iferror(vlookup(S14,'Back up'!$B$2:$C$18,2,0),"")
A15: 14 | B15: 46120 | F15: The Origin Sukhumvit Praksa | I15: 2026 | J15: ✅ จอง | L15: 52000 | N15: 08.04.26 ทำใบเสนอราคา อัพเดตดูส่วนลดใหม่อีกที่วันศุกร์ | O15: Pang | Q15: =iferror(vlookup(S15,'Back up'!$B$2:$C$18,2,0),"")
A16: 15 | D16: OPA | F16: บางแสน | G16: คุณอระวรรณ แดงโสภา | I16: 1018 | J16: ✅ จอง | K16: Built-in | M16: 1 | N16: 08.04.26 เก็บเงินงวดสุดท้ายพร้อมเอกสารส่งมอบงาน | O16: Pang | P16: Closed | Q16: =iferror(vlookup(S16,'Back up'!$B$2:$C$18,2,0),"") -> Close Lead | R16: Line | S16: ลูกค้าชำระเงินเรียบร้อย
A17: 16 | B17: 46132 | D17: หาเอง | F17: PP E22 | I17: 1439 | J17: ✅ จอง | K17: Loose furniture | L17: 20000 | N17: ติดต่อกลับ | O17: Pang | Q17: =iferror(vlookup(S17,'Back up'!$B$2:$C$18,2,0),"")
A18: 17 | D18: หาเอง | F18: แพรกษา | I18: 2026 | J18: ✅ จอง | K18: Built-in | L18: 50000 | N18: ทำราคา | O18: Pang | Q18: =iferror(vlookup(S18,'Back up'!$B$2:$C$18,2,0),"")
A19: 18 | D19: หาเอง | F19: แพรกษา | G19: คุณธนพนธ์ ไพเราะห์ | I19: 1621 | J19: ✅ จอง | K19: Built-in | L19: 40000 | N19: สรุปแพค | O19: Pang | Q19: =iferror(vlookup(S19,'Back up'!$B$2:$C$18,2,0),"")
A20: 19 | D20: หาเอง | F20: แพรกษา | I20: 3113 | J20: ✅ จอง | K20: Built-in | N20: คุยรายละเอียดงานเฟอร์ ดูห้องตัวอย่าง ห้องลูกค้า เพื่ออธิบายรายละเอียดขนาดและงานติดตั้งเพื่อทำราคาตามรายการที่ต้องการอีกครั้ง | O20: Pang
A21: 20 | D21: OPA | F21: แพรกษา | G21: คุณสุชาดา ไทยแท้ | I21: 1203 | J21: ✅ จอง | K21: Built-in | L21: 88100 | M21: 0.5 | N21: เครียปัญหาหน้างานเรื่องงานแอร์พร้อมสรุปวันเข้าแก้ไข | O21: Pang
A22: 21 | D22: OPA | F22: แพรกษา | G22: คุณจิตรา สุขเจริญ | I22: 2308 | J22: ✅ จอง | K22: Built-in | L22: 100000 | M22: 1 | N22: คุุยรายละเอียดตารางงานจัดคิวเข้างานกับลูกค้าเนื่องจากลูกค้ามีงานบิ้วอื่นๆจากด้านนอก | O22: Pang
A23: 22 | D23: OPA | F23: แพรกษา | G23: คุณอนันท์ธิดา อาจบำรุง | I23: 12A05 | J23: ✅ จอง | K23: Built-in | L23: 28000 | M23: 0.5 | N23: อัพเดต งานติดตั้ง และดูเรื่องงานแอร์เข้าได้อีกครั้งวันไหน ขาดแค่รายการเดียว | O23: Pang
A24: 23 | J24: ✅ จอง | O24: Pang
A25: 24 | J25: ✅ จอง | O25: Pang
A26: 25 | J26: ✅ จอง | O26: Pang
A27: 26 | J27: ✅ จอง | O27: Pang
A28: 27 | J28: ✅ จอง | O28: Pang
A29: 28 | D29: หาเอง | F29: แพรกษา | I29: 2510 | J29: ✅ จอง | K29: Built-in | L29: 50000 | N29: คุยรายละเอียดใหม่ | O29: Pang | Q29: =iferror(vlookup(S29,'Back up'!$B$2:$C$18,2,0),"")
A30: 29 | B30: 46133 | D30: หาเอง | F30: แพรกษา | G30: คุณธนพนธ์ ไพเราะห์ | I30: 1621 | K30: Built-in | L30: 100000 | N30: ทำใบราคาใหม่ | O30: Pang | P30: Closed | Q30: =iferror(vlookup(S30,'Back up'!$B$2:$C$18,2,0),"") -> Close Lead | R30: Line | S30: ลูกค้าชำระเงินเรียบร้อย
A31: 30 | D31: หาเอง | F31: แพรกษา | G31: คุณภิรติพร โพธิ์แดง | I31: 2511 | K31: Curtain | L31: 11000 | N31: นัดวันวัดพื้น ที่ และติดตั้ง | O31: Pang | P31: Closed | Q31: =iferror(vlookup(S31,'Back up'!$B$2:$C$18,2),"") -> Close Lead | R31: Line | S31: ลูกค้าชำระเงินเรียบร้อย
A32: 31 | D32: หาเอง | F32: แพรกษา | G32: คุณสุภาพร พัดโสภา | I32: 2110 | K32: Curtain | L32: 11130 | N32: ทำใบส่งมอบ | O32: Pang | P32: Closed | Q32: =iferror(vlookup(S32,'Back up'!$B$2:$C$18,2),"") -> Close Lead | R32: Line | S32: ลูกค้าชำระเงินเรียบร้อย
A33: 32 | D33: หาเอง | F33: แพรกษา | G33: คุณสุชาดา ไทยแท้ | I33: 1203 | K33: Built-in | L33: 88100 | N33: เครียงานติดตั้ง สรุป เก็บเงิน และ ทำส่งมอบงาน | O33: Pang | P33: Closed | Q33: =iferror(vlookup(S33,'Back up'!$B$2:$C$18,2),"") -> Close Lead | R33: Line | S33: ลูกค้าชำระเงินเรียบร้อย
D34: OPA | F34: Origin Play Bangsaen | G34: Origin Play Bangsaen Co., Ltd. | I34: 1910 | K34: Curtain | L34: 16000 | N34: ทำใบส่งมอบ | O34: Pang | P34: Closed | Q34: =iferror(vlookup(S34,'Back up'!$B$2:$C$18,2),"") -> Close Lead | R34: Line | S34: ลูกค้าชำระเงินเรียบร้อย
D35: OPA | F35: Origin Play Bangsaen | G35: Origin Play Bangsaen Co., Ltd. | I35: 1508 | K35: Curtain | L35: 16000 | N35: ทำใบส่งมอบ | O35: Pang | P35: Closed | Q35: =iferror(vlookup(S35,'Back up'!$B$2:$C$18,2),"") -> Close Lead | R35: Line | S35: ลูกค้าชำระเงินเรียบร้อย
D36: OPA | F36: Origin Play Bangsaen | G36: Origin Play Bangsaen Co., Ltd. | I36: 1102 | K36: Curtain | L36: 8000 | N36: ทำใบส่งมอบ | O36: Pang | P36: Closed | Q36: =iferror(vlookup(S36,'Back up'!$B$2:$C$18,2),"") -> Close Lead | R36: Line | S36: ลูกค้าชำระเงินเรียบร้อย
D37: OPA | F37: Origin Play Bangsaen | G37: Origin Play Bangsaen Co., Ltd. | I37: 1103 | K37: Curtain | L37: 8000 | N37: ทำใบส่งมอบ | O37: Pang | P37: Closed | Q37: =iferror(vlookup(S37,'Back up'!$B$2:$C$18,2),"") -> Close Lead | R37: Line | S37: ลูกค้าชำระเงินเรียบร้อย
D38: OPA | F38: Origin Play Bangsaen | G38: Origin Play Bangsaen Co., Ltd. | I38: 1106 | K38: Curtain | L38: 8000 | N38: ทำใบส่งมอบ | O38: Pang | P38: Closed | Q38: =iferror(vlookup(S38,'Back up'!$B$2:$C$18,2),"") -> Close Lead | R38: Line | S38: ลูกค้าชำระเงินเรียบร้อย
D39: OPA | F39: Origin Play Bangsaen | G39: Origin Play Bangsaen Co., Ltd. | I39: 1407 | K39: Curtain | L39: 8000 | N39: ทำใบส่งมอบ | O39: Pang | P39: Closed | Q39: =iferror(vlookup(S39,'Back up'!$B$2:$C$18,2),"") -> Close Lead | R39: Line | S39: ลูกค้าชำระเงินเรียบร้อย
D40: OPA | F40: Origin Play Bangsaen | G40: Origin Play Bangsaen Co., Ltd. | I40: 1417 | K40: Curtain | L40: 8000 | N40: ทำใบส่งมอบ | O40: Pang | P40: Closed | Q40: =iferror(vlookup(S40,'Back up'!$B$2:$C$18,2),"") -> Close Lead | R40: Line | S40: ลูกค้าชำระเงินเรียบร้อย
D41: OPA | F41: Origin Play Bangsaen | G41: Origin Play Bangsaen Co., Ltd. | I41: 12A39 | K41: ready | L41: 140000 | N41: ทำใบเบิก EDH | O41: Pang | P41: Closed | Q41: =iferror(vlookup(S41,'Back up'!$B$2:$C$18,2),"") -> Close Lead | R41: Line | S41: ลูกค้าชำระเงินเรียบร้อย
D42: OPA | F42: Origin Play Bangsaen | G42: Origin Play Bangsaen Co., Ltd. | I42: 1910 | K42: Curtain | O42: Pang | P42: Closed | R42: Line | S42: ลูกค้าชำระเงินเรียบร้อย
D43: OPA | F43: Origin Play Bangsaen | G43: Origin Play Bangsaen Co., Ltd. | I43: 1508 | K43: Curtain | O43: Pang | P43: Closed | R43: Line | S43: ลูกค้าชำระเงินเรียบร้อย
D44: OPA | F44: Origin Play Bangsaen | G44: Origin Play Bangsaen Co., Ltd. | I44: 1102 | K44: Curtain | O44: Pang | P44: Closed | R44: Line | S44: ลูกค้าชำระเงินเรียบร้อย
D45: OPA | F45: Origin Play Bangsaen | G45: Origin Play Bangsaen Co., Ltd. | I45: 1215 | K45: Curtain | O45: Pang | P45: Closed | R45: Line | S45: ลูกค้าชำระเงินเรียบร้อย
D46: OPA | F46: Origin Play Bangsaen | G46: Origin Play Bangsaen Co., Ltd. | I46: 1103 | K46: Curtain | O46: Pang | P46: Closed | R46: Line | S46: ลูกค้าชำระเงินเรียบร้อย
D47: OPA | F47: Origin Play Bangsaen | G47: Origin Play Bangsaen Co., Ltd. | I47: 1106 | K47: Curtain | O47: Pang | P47: Closed | R47: Line | S47: ลูกค้าชำระเงินเรียบร้อย
D48: OPA | F48: Origin Play Bangsaen | G48: Origin Play Bangsaen Co., Ltd. | I48: 1407 | K48: Curtain | O48: Pang | P48: Closed | R48: Line | S48: ลูกค้าชำระเงินเรียบร้อย
D49: OPA | F49: Origin Play Bangsaen | G49: Origin Play Bangsaen Co., Ltd. | I49: 1417 | K49: Curtain | O49: Pang | P49: Closed | R49: Line | S49: ลูกค้าชำระเงินเรียบร้อย
B50: 46134 | D50: OPA | F50: Origin Play Bangsaen | G50: Origin Play Bangsaen Co., Ltd. | I50: 1204 | K50: ready | L50: 5000 | M50: มัดจำ | N50: คุุยรายละเอียดแพคใหม่ | O50: Pang | P50: Lead | Q50: =iferror(vlookup(S50,'Back up'!$B$2:$C$18,2),"") -> Close Lead | R50: Line | S50: ส่งใบราคาหรือ ข้อมูลแพ็คเกจให้กับลูกค้าแล้ว
D51: OPA | F51: Origin Play Bangsaen | G51: Origin Play Bangsaen Co., Ltd. | I51: 1616 | K51: Built-in | M51: 1 | N51: นั้ำแอร์รั่ว ต้องนัดเข้าแก้ไขแอร์ใหม่ | O51: Pang | P51: Closed | Q51: =iferror(vlookup(S51,'Back up'!$B$2:$C$18,2),"") -> Close Lead | R51: Line | S51: ลูกค้าชำระเงินเรียบร้อย
D52: OPA | F52: แพรกษา | G52: คุณจอม เมธศาสตร์ | I52: 2418 | K52: Built-in | L52: 50000 | M52: 1 | N52: อัพเดตหน้างาน ทำใบส่งมอบ / รอ ลค นัดเข้า ตรวจงาน | O52: Pang | P52: Closed | Q52: =iferror(vlookup(S52,'Back up'!$B$2:$C$18,2),"") -> Close Lead | R52: Line | S52: ลูกค้าชำระเงินเรียบร้อย
D53: OPA | F53: แพรกษา | G53: คุณเมกพัฒน์ เยี่ยมประเสริฐ | I53: 2917 | K53: Built-in | L53: 26000 | M53: 1 | N53: ก็อกน้ำไม่ไหว หาช่างเข้าแก้ | O53: Pang | P53: Closed | Q53: =iferror(vlookup(S53,'Back up'!$B$2:$C$18,2),"") -> Close Lead | R53: Line | S53: ลูกค้าชำระเงินเรียบร้อย
D54: OPA | F54: แพรกษา | G54: คุณเมกพัฒน์ เยี่ยมประเสริฐ | I54: 2918 | K54: Built-in | L54: 53000 | M54: 1 | N54: ปลั๊กแตก แต่ทางโครงการทำ เช็คภาพ อัพเดต | O54: Pang | P54: Closed | Q54: =iferror(vlookup(S54,'Back up'!$B$2:$C$18,2),"") -> Close Lead | R54: Line | S54: ลูกค้าชำระเงินเรียบร้อย
D55: OPA | F55: แพรกษา | G55: คุณพายุ สิมบุตร | I55: 1206 | K55: Built-in | L55: 8000 | M55: 1 | N55: เช็ครายละเอียดหน้างาน ช่างขอเลื่อนวันติดวลล์ | O55: Pang | P55: Closed | Q55: =iferror(vlookup(S55,'Back up'!$B$2:$C$18,2),"") -> Close Lead | R55: Line | S55: ลูกค้าชำระเงินเรียบร้อย
D56: OPA | F56: Origin Play Bangsaen | G56: Origin Play Bangsaen Co., Ltd. | I56: 1709 | K56: Curtain | L56: 8000 | M56: 1 | N56: ทำเอกสาร ส่งมอบงาน | O56: Pang | P56: Closed | R56: Line | S56: ลูกค้าชำระเงินเรียบร้อย
D57: OPA | F57: Origin Play Bangsaen | G57: Origin Play Bangsaen Co., Ltd. | I57: 2012 | K57: Curtain | L57: 8000 | M57: 1 | N57: ทำเอกสาร ส่งมอบงาน | O57: Pang | P57: Closed | R57: Line | S57: ลูกค้าชำระเงินเรียบร้อย
D58: OPA | F58: Origin Play Bangsaen | G58: Origin Play Bangsaen Co., Ltd. | I58: 2304 | K58: Curtain | L58: 8000 | M58: 1 | N58: ทำเอกสาร ส่งมอบงาน | O58: Pang | P58: Closed | R58: Line | S58: ลูกค้าชำระเงินเรียบร้อย
D59: OPA | F59: Origin Play Bangsaen | G59: Origin Play Bangsaen Co., Ltd. | I59: 1604 | K59: Curtain | L59: 8000 | M59: 1 | N59: ทำเอกสาร ส่งมอบงาน | O59: Pang | P59: Closed | R59: Line | S59: ลูกค้าชำระเงินเรียบร้อย
D60: OPA | F60: Origin Play Bangsaen | G60: Origin Play Bangsaen Co., Ltd. | I60: 1210 | K60: Curtain | L60: 8000 | M60: 1 | N60: ทำเอกสาร ส่งมอบงาน | O60: Pang | P60: Closed | R60: Line | S60: ลูกค้าชำระเงินเรียบร้อย
D61: OPA | F61: Origin Play Bangsaen | G61: Origin Play Bangsaen Co., Ltd. | I61: 1906 | K61: Curtain | L61: 8000 | M61: 1 | N61: ทำเอกสาร ส่งมอบงาน | O61: Pang | P61: Closed | R61: Line | S61: ลูกค้าชำระเงินเรียบร้อย
D62: OPA | F62: Origin Play Bangsaen | G62: Origin Play Bangsaen Co., Ltd. | I62: 2113 | K62: Curtain | L62: 8000 | M62: 1 | N62: ทำเอกสาร ส่งมอบงาน | O62: Pang | P62: Closed | R62: Line | S62: ลูกค้าชำระเงินเรียบร้อย
D63: OPA | F63: Origin Play Bangsaen | G63: Origin Play Bangsaen Co., Ltd. | I63: 12A11 | K63: Curtain | L63: 8000 | M63: 1 | N63: ทำเอกสาร ส่งมอบงาน | O63: Pang | P63: Closed | R63: Line | S63: ลูกค้าชำระเงินเรียบร้อย
D64: OPA | F64: Origin Play Bangsaen | G64: Origin Play Bangsaen Co., Ltd. | I64: 2116 | K64: Curtain | L64: 8000 | M64: 1 | N64: ทำเอกสาร ส่งมอบงาน | O64: Pang | P64: Closed | R64: Line | S64: ลูกค้าชำระเงินเรียบร้อย
D65: OPA | F65: Origin Play Bangsaen | G65: Origin Play Bangsaen Co., Ltd. | I65: 1504 | K65: Curtain | L65: 8000 | M65: 1 | N65: ทำเอกสาร ส่งมอบงาน | O65: Pang | P65: Closed | R65: Line | S65: ลูกค้าชำระเงินเรียบร้อย
D66: OPA | F66: Origin Play Bangsaen | G66: Origin Play Bangsaen Co., Ltd. | I66: 1520 | K66: Curtain | L66: 8000 | M66: 1 | N66: ทำเอกสาร ส่งมอบงาน | O66: Pang | P66: Closed | R66: Line | S66: ลูกค้าชำระเงินเรียบร้อย
D67: OPA | F67: Origin Play Bangsaen | G67: Origin Play Bangsaen Co., Ltd. | I67: 802 | K67: Curtain | L67: 8000 | M67: 1 | N67: ทำเอกสาร ส่งมอบงาน | O67: Pang | P67: Closed | R67: Line | S67: ลูกค้าชำระเงินเรียบร้อย
D68: OPA | F68: Origin Play Bangsaen | G68: Origin Play Bangsaen Co., Ltd. | I68: 2104 | K68: Curtain | L68: 8000 | M68: 1 | N68: ทำเอกสาร ส่งมอบงาน | O68: Pang | P68: Closed | R68: Line | S68: ลูกค้าชำระเงินเรียบร้อย
D69: OPA | F69: Origin Play Bangsaen | G69: Origin Play Bangsaen Co., Ltd. | I69: 1513 | K69: Curtain | L69: 8000 | M69: 1 | N69: ทำเอกสาร ส่งมอบงาน | O69: Pang | P69: Closed | R69: Line | S69: ลูกค้าชำระเงินเรียบร้อย
D70: OPA | F70: Origin Play Bangsaen | G70: Origin Play Bangsaen Co., Ltd. | I70: 1408 | K70: Curtain | L70: 8000 | M70: 1 | N70: ทำเอกสาร ส่งมอบงาน | O70: Pang | P70: Closed | R70: Line | S70: ลูกค้าชำระเงินเรียบร้อย
D71: OPA | F71: Origin Play Bangsaen | G71: Origin Play Bangsaen Co., Ltd. | I71: 1913 | K71: Curtain | L71: 8000 | M71: 1 | N71: ทำเอกสาร ส่งมอบงาน | O71: Pang | P71: Closed | R71: Line | S71: ลูกค้าชำระเงินเรียบร้อย
D72: OPA | F72: Origin Play Bangsaen | G72: Origin Play Bangsaen Co., Ltd. | I72: 1403 | K72: Curtain | L72: 8000 | M72: 1 | N72: ทำเอกสาร ส่งมอบงาน | O72: Pang | P72: Closed | R72: Line | S72: ลูกค้าชำระเงินเรียบร้อย
D73: OPA | F73: Origin Play Bangsaen | G73: Origin Play Bangsaen Co., Ltd. | I73: 2310 | K73: Curtain | L73: 8000 | M73: 1 | N73: ทำเอกสาร ส่งมอบงาน | O73: Pang | P73: Closed | R73: Line | S73: ลูกค้าชำระเงินเรียบร้อย
D74: หาเอง | F74: Origin Play Bangsaen | G74: คุณอนงค์รักษ์ ศาลากิจ | I74: 802 | K74: Loose furniture | L74: 5000 | M74: 1 | N74: ส่งของ | O74: Pang | P74: Closed | R74: Line | S74: ลูกค้าชำระเงินเรียบร้อย
O75: Pang | P75: Closed | R75: Line | S75: ลูกค้าชำระเงินเรียบร้อย
B76: 46135 | D76: หาเอง | F76: พหล 69 | G76: คุณวีรศักดิ์ สุขจันทร์ | I76: 1446 | K76: Built-in | L76: 400000 | M76: 1 | N76: เอกสารคืนเงินค้ำประกัน | O76: Pang | P76: Closed | Q76: =iferror(vlookup(S76,'Back up'!$B$2:$C$18,2),"") -> Close Lead | R76: Line | S76: ลูกค้าชำระเงินเรียบร้อย
D77: หาเอง | F77: บางแสน | G77: ธัญชนก สุวรรณปัญญา | I77: 1204 | K77: Built-in | L77: 170000 | M77: มัดจำ | N77: อัพเดตใบเสนอราคา | O77: Pang | P77: Lead | Q77: =iferror(vlookup(S77,'Back up'!$B$2:$C$18,2),"") -> Close Lead | R77: Line | S77: ส่งใบราคาหรือ ข้อมูลแพ็คเกจให้กับลูกค้าแล้ว
D78: หาเอง | F78: แพรกษา | G78: คุณกนกวรรณ คงธนาคมธัญกิจ | I78: 1918 | K78: Built-in | L78: 53000 | M78: 1 | N78: ลูกค้าเก่า ซ่อมเฟอร์ แจ้งราคา | O78: Pang | P78: Closed | Q78: =iferror(vlookup(S78,'Back up'!$B$2:$C$18,2),"")
D79: OPA | F79: Origin Play Bangsaen | G79: Origin Play Bangsaen Co., Ltd. | I79: 1407 | K79: Curtain | L79: 8000 | M79: 1 | N79: ทำเอกสาร ส่งมอบงาน | O79: Pang | P79: Closed | Q79: =iferror(vlookup(S79,'Back up'!$B$2:$C$18,2),"")
D80: OPA | F80: Origin Play Bangsaen | G80: Origin Play Bangsaen Co., Ltd. | I80: 1901 | K80: Curtain | L80: 8000 | M80: 1 | N80: ทำเอกสาร ส่งมอบงาน | O80: Pang | P80: Closed | Q80: =iferror(vlookup(S80,'Back up'!$B$2:$C$18,2),"")
D81: OPA | F81: Origin Play Bangsaen | G81: Origin Play Bangsaen Co., Ltd. | I81: 1121 | K81: Curtain | L81: 8000 | M81: 1 | N81: ทำเอกสาร ส่งมอบงาน | O81: Pang | P81: Closed | Q81: =iferror(vlookup(S81,'Back up'!$B$2:$C$18,2),"")
D82: OPA | F82: Origin Play Bangsaen | G82: Origin Play Bangsaen Co., Ltd. | I82: 2308 | K82: Curtain | L82: 8000 | M82: 1 | N82: ทำเอกสาร ส่งมอบงาน | O82: Pang | P82: Closed | Q82: =iferror(vlookup(S82,'Back up'!$B$2:$C$18,2),"")
D83: OPA | F83: Origin Play Bangsaen | G83: Origin Play Bangsaen Co., Ltd. | I83: 2119 | K83: Curtain | L83: 8000 | M83: 1 | N83: ทำเอกสาร ส่งมอบงาน | O83: Pang | P83: Closed | Q83: =iferror(vlookup(S83,'Back up'!$B$2:$C$18,2),"")
D84: OPA | F84: Origin Play Bangsaen | G84: Origin Play Bangsaen Co., Ltd. | I84: 911 | K84: Curtain | L84: 8000 | M84: 1 | N84: ทำเอกสาร ส่งมอบงาน | O84: Pang | P84: Closed | Q84: =iferror(vlookup(S84,'Back up'!$B$2:$C$18,2),"")
D85: OPA | F85: Origin Play Bangsaen | G85: Origin Play Bangsaen Co., Ltd. | I85: 1018 | K85: Curtain | L85: 8000 | M85: 1 | N85: ทำเอกสาร ส่งมอบงาน | O85: Pang | P85: Closed | Q85: =iferror(vlookup(S85,'Back up'!$B$2:$C$18,2),"")
D86: หาเอง | F86: แพรกษา | G86: คุณภิรติพร โพธิ์แดง | I86: 2511 | K86: Curtain | L86: 10000 | M86: 0.5 | N86: นัดวันคอนเฟริมวันวัดพื้นที่ และ วันติดตั้ง | O86: Pang | P86: Lead | Q86: =iferror(vlookup(S86,'Back up'!$B$2:$C$18,2),"") -> Close Lead | R86: Line | S86: ลูกค้าชำระเงินเรียบร้อย
D87: หาเอง | F87: Origin Play Bangsaen | G87: คุณตันติมา ซื่อตรงกิจ | I87: 1210 | K87: Built-in | L87: 18500 | M87: 1 | N87: ทำเอกสาร ส่งมอบงาน | O87: Pang | P87: Closed | Q87: =iferror(vlookup(S87,'Back up'!$B$2:$C$18,2),"") -> Close Lead | R87: Line | S87: ลูกค้าชำระเงินเรียบร้อย
B88: 46137 | D88: หาเอง | F88: Origin Play Bangsaen | I88: 12A08 | K88: Curtain | L88: 5000 | O88: Pang | P88: Lead | Q88: =iferror(vlookup(S88,'Back up'!$B$2:$C$18,2),"") | R88: Call
D89: หาเอง | F89: Origin Play Bangsaen | I89: 1013 | K89: Design&turnkey | L89: 200000 | M89: 1 | O89: Pang | P89: Lead | Q89: =iferror(vlookup(S89,'Back up'!$B$2:$C$18,2),"") | R89: Call
D90: หาเอง | F90: Origin Play Bangsaen | I90: 1715 | K90: Curtain | L90: 5000 | O90: Pang | P90: Lead | Q90: =iferror(vlookup(S90,'Back up'!$B$2:$C$18,2),"") | R90: Call
D91: หาเอง | F91: Origin Play Bangsaen | I91: 2111 | K91: Curtain | L91: 5000 | O91: Pang | P91: Lead | Q91: =iferror(vlookup(S91,'Back up'!$B$2:$C$18,2),"") | R91: Call
D92: หาเอง | F92: Origin Play Bangsaen | I92: 1812 | K92: Curtain | L92: 5000 | O92: Pang | P92: Lead | Q92: =iferror(vlookup(S92,'Back up'!$B$2:$C$18,2),"") | R92: Call
D93: หาเอง | F93: Origin Play Bangsaen | I93: 1003 | K93: Curtain | L93: 5000 | O93: Pang | P93: Lead | Q93: =iferror(vlookup(S93,'Back up'!$B$2:$C$18,2),"") | R93: Call
D94: หาเอง | F94: บางขุน นน | I94: 1012 | K94: Design&turnkey | L94: 170000 | N94: เข้า ตรวจงานเพื่อส่งมอบงานกับ ลค ครั้งที่ 1 | O94: Pang | Q94: =iferror(vlookup(S94,'Back up'!$B$2:$C$18,2),"")
B95: 46139 | D95: OPA | F95: แพรกษา | I95: 2816 | K95: Built-in | L95: 50000 | N95: นำของสมนาคุณ หมอนอิงให้ลูกค้า | O95: Pang | Q95: =iferror(vlookup(S95,'Back up'!$B$2:$C$18,2),"")
D96: OPA | F96: แพรกษา | I96: 1809 | K96: Built-in | L96: 50000 | N96: สรุป แพคเกจ และ เก็บชำระงวดแรก | O96: Pang | Q96: =iferror(vlookup(S96,'Back up'!$B$2:$C$18,2),"")
D97: OPA | F97: แพรกษา | I97: 2026 | K97: Built-in | N97: สรุป แก้ไขแพคและทำราคาใหม่ / ทำส่งเรียบร้อย | O97: Pang | Q97: =iferror(vlookup(S97,'Back up'!$B$2:$C$18,2),"")
D98: OPA | F98: แพรกษา | I98: 2401 | K98: Built-in | L98: 90000 | N98: คุยรายละเอียด รายการสินค้าเพื่อ สรุปแพคเกจ | O98: Pang | Q98: =iferror(vlookup(S98,'Back up'!$B$2:$C$18,2),"")
D99: หาเอง | F99: PP E22 | I99: 12A17 | K99: wallcovering | N99: คุยรายละเอียดสรุปวัสดุ ม่านวลล์ | O99: Pang | Q99: =iferror(vlookup(S99,'Back up'!$B$2:$C$18,2),"")
D100: หาเอง | F100: บางแสน | I100: 1402 | K100: Built-in | L100: 30000 | N100: สรุปแพคเกจ | O100: Pang | Q100: =iferror(vlookup(S100,'Back up'!$B$2:$C$18,2),"")
...

Sheet Josh
A1: 📊Weekly Report📊 ลูกค้าใหม่ที่ยังไม่จอง 📱 ลูกค้าใน Backlog 📱งานอื่นๆที่ทำอยู่ 💻 | O1: สรุปรายวัน
A2: No. | B2: Contact date | C2: Close date | D2: Where | E2: Clients type | F2: Project | G2: Room | H2: Name (Customer) | I2: Product Type | J2: คาดยอดขาย | K2: โอกาสปิด (%) | L2: Close/Inprogress | M2: สถานะปัจจุบัน | N2: Remark | O2: LEAD ใหม่ วันนี้ (ราย) | P2: ยอดขายใหม่วันนี้ (ราย) | Q2: มูลค่าแพ็คเกจที่จองวันนี้ (บาท) | R2: จำนวนเงินจองมัดจำ วันนี้ (บาท) | S2: ยอดชำระ 50/100% ก่อนตกแต่ง วันนี้ (ราย) | T2: ยอดชำระ 50/100% ก่อนตกแต่ง วันนี้ (บาท)
A3: 1 | B3: 46102 | C3: 46102 | D3: LINE OA | F3: Origin Place Khon Kaen-Kanlapaphruek | G3: A329 | H3: คุณพัชชา เชื้อดวงผูย | I3: Curtain, wallcovering | J3: 28000 | K3: 0.5 | L3: In Progress | M3: ลูกค้าใน Backlog | N3: เปิด PR/PO นัด Sup. เข้าติดตั้งต้นเมษายน
A4: 2 | D4: LINE OA | F4: Origin Place Khon Kaen-Kanlapaphruek | G4: A427 | H4: คุณวิทยา จิตรแก้ว | I4: Curtain | J4: 70000 | K4: 0.5 | L4: In Progress | M4: ลูกค้าใน Backlog | N4: รอตรวจรับห้อง
A5: 3 | D5: LINE OA | F5: Origin Place Khon Kaen-Kanlapaphruek | G5: B729 | H5: คุณศศิธร กุลวงศ์ | I5: Curtain | J5: 43840 | K5: 1 | L5: In Progress | M5: ลูกค้าใน Backlog | N5: รอตรวจรับห้อง
A6: 4 | D6: LINE OA | F6: Origin Place Khon Kaen-Kanlapaphruek | G6: A217 | H6: คุณระพีพงศ์ บุ่งศรี | I6: Curtain | J6: 11495 | K6: 1 | L6: In Progress | M6: ลูกค้าใน Backlog | N6: รอตรวจรับห้อง
A7: 5 | B7: 46103 | C7: 46103 | D7: LINE OA | F7: Origin Place Khon Kaen-Kanlapaphruek | G7: B526 | H7: คุณพิลาวรรณ สาราษฎร์ | I7: Design | J7: 69882 | K7: 0.5 | L7: In Progress | M7: ลูกค้าใน Backlog | N7: รอตรวจรับห้อง
A8: 6 | D8: LINE OA | F8: Origin Place Khon Kaen-Kanlapaphruek | G8: A216 | H8: คุณตุลาณี เชาว์ประจักษ์ | I8: Loose furniture | J8: 67000 | K8: 0.5 | L8: In Progress | M8: ลูกค้าใน Backlog | N8: รอตรวจรับห้อง
A9: 7 | D9: หาเอง | F9: Origin Place Khon Kaen-Kanlapaphruek | G9: B611 | H9: คุณดวงพร สมสวย | I9: Curtain | J9: 30000 | K9: 1 | L9: In Progress | M9: ลูกค้าใน Backlog | N9: รอตรวจรับห้อง
A10: 8 | D10: OPA | F10: Origin Place Khon Kaen-Kanlapaphruek | G10: B606 | H10: คุณพิพัธน์ เรืองแสง | I10: Design | J10: 300000 | K10: 0.5 | L10: In Progress | M10: ลูกค้าใน Backlog | N10: รอตรวจรับห้อง
A11: 9 | D11: หาเอง | F11: Origin Place Khon Kaen-Kanlapaphruek | G11: B505 | H11: คุณวิลัยพร ชัยเจริญ | I11: Built-in | J11: 139000 | K11: 1 | L11: In Progress | M11: ลูกค้าใน Backlog | N11: อยู่ในระหว่าง Brief กับ Designer / ส่งเมล 03/04/26
A12: 10 | D12: LINE OA | F12: Origin Place Khon Kaen-Kanlapaphruek | G12: B516 | H12: คุณกัญญาณัฐ โคโตศรี | I12: Loose furniture, Built-in | J12: 87400 | K12: 1 | L12: In Progress | M12: ลูกค้าใน Backlog | N12: ส่ง QR รอชำระ
A13: 12 | D13: OPA | F13: Origin Phahol 57 | G13: B833 | H13: คุณณัฐญา วุ้นประสิทธิ์ศักดิ์ | I13: Curtain | J13: 36030 | K13: 1 | L13: In Progress | M13: ลูกค้าใน Backlog | N13: Completed รอส่งมอบ
A14: 13 | D14: OPA | F14: Origin Phahol 57 | G14: B511 | H14: คุณชิติพัทธ์ จงสถาพรพงศ์ | I14: Curtain | J14: 13200 | K14: 1 | L14: In Progress | M14: ลูกค้าใน Backlog | N14: กำลังดำเนินการเปิด PR/PO
A15: 14 | B15: 46112 | C15: 46113 | D15: OPA | F15: Origin Place Khon Kaen-Kanlapaphruek | G15: B210 | H15: คุณสุกัญญา เด่นกองพล | I15: Curtain | J15: 20340 | K15: 1 | L15: In Progress | M15: ลูกค้าใน Backlog | N15: กำลังดำเนินการเปิด PR/PO
A16: 16 | F16: D Condo Campus Khonkaen | H16: คุณสุธาทิพย์ หรเพลิด | I16: Design&turnkey | J16: 100000 | K16: 0.2 | L16: In Progress | M16: ลูกค้าใน Backlog | N16: งานตกแต่งโครงนอก 989/391 ชั้น 5 อาคาร B
A17: 17 | C17: 46111 | D17: OPA | F17: Origin Phahol 57 | G17: B609 | H17: คุณจตุพงษ์ ศรีพงษ์พันธ์กุล | I17: Built-in | J17: 74056 | K17: 1 | L17: Close | M17: ลูกค้าใน Backlog | N17: ส่งมอบแล้ว
A18: 18 | F18: Origin Phahol 57 | G18: B328 | H18: คุณณัฐธนัน เลิศพูนผล | I18: Built-in | J18: 12100 | K18: 1 | L18: In Progress | M18: ลูกค้าใน Backlog | N18: ช่างเข้าวัดพื้นที่ 04/04/26 ติด Backsplash
A19: 19 | B19: 46314 | C19: 46109 | D19: OPA | F19: Origin Place Bangna | G19: 1204 | H19: คุณนภาพร แย้มวาที | I19: Curtain | J19: 16800 | K19: 1 | L19: In Progress | M19: ลูกค้าใน Backlog | N19: ติดตั้งม่าน 04/04/26
A20: 1 | B20: 46115 | D20: OPA | F20: Origin Place Khon Kaen-Kanlapaphruek | G20: A506 | H20: คุณออ | I20: Curtain | K20: ส่ง QT & Package | L20: In Progress | M20: ลูกค้าใหม่ยังไม่จอง | N20: กำลัังรอสรุปเรื่องวัสดุ
A21: 2 | F21: Origin Place Khon Kaen-Kanlapaphruek | G21: B825 | H21: คุณธีรวัฒน์ | I21: Built-in, Curtain, wallcovering | K21: ส่ง QT & Package | L21: In Progress | M21: ลูกค้าใหม่ยังไม่จอง | N21: อยูู่่ในระหว่างคุย
A22: 3 | B22: 1703/26 | F22: Origin Place Khon Kaen-Kanlapaphruek | G22: A529 | H22: คุณกรุง | I22: Curtain, wallcovering, Built-in | K22: ส่ง QT & Package | L22: In Progress | M22: ลูกค้าใหม่ยังไม่จอง | N22: อยูู่่ในระหว่างคุย
A23: 4 | F23: Origin Place Khon Kaen-Kanlapaphruek | G23: B222 | H23: สุวิมล พรหมชัยนันท์ | I23: Curtain | K23: ส่ง QT & Package | L23: In Progress | M23: ลูกค้าใหม่ยังไม่จอง | N23: ต้องการบานปิดตู้เสื้อผ้า / ไม่รับทำแจ้งแล้ว
A24: 5 | F24: Origin Place Khon Kaen-Kanlapaphruek | G24: A832 | H24: อ้อมทิพย์ ศรีจันทะ | I24: Curtain | K24: ส่ง QT & Package | L24: In Progress | M24: ลูกค้าใหม่ยังไม่จอง | N24: สนใจตกแต่งห้อง ขอคุยรายละเอียดเพิ่มเติม
A25: 6 | I25: Curtain | L25: =iferror(vlookup(#REF!,'Back up'!$B$2:$C$18,2),"")
F26: 46116 | L26: =iferror(vlookup(#REF!,'Back up'!$B$2:$C$18,2),"")
A27: 34 | D27: OPA | F27: Origin Place Khon Kaen-Kanlapaphruek | G27: A329 | H27: คุณพัชชา เชื้อดวงผูย | I27: Curtain, wallcovering | J27: 28000 | K27: 0.5 | L27: In Progress | M27: ลูกค้าใน Backlog | N27: อัพเดทรูปหน้างาน/ติดวอลล์ที่เหลือปลาบสงกรานต์
A28: 35 | D28: หาเอง | F28: Origin Phahol 57 | G28: B328 | H28: คุณณัฐธนัน เลิศพูนผล | I28: Built-in | J28: 12100 | K28: 1 | L28: Close | M28: ลูกค้าใน Backlog | N28: ช่างเข้าวัดพื้นที่ติดตั้ง Backsplash ชาดำ
A29: 36 | D29: OPA | F29: Origin Place Khon Kaen-Kanlapaphruek | G29: A427 | H29: คุณวิทยา จิตรแก้ว | I29: RTM | J29: 70000 | K29: 1 | L29: In Progress | M29: ลูกค้าใน Backlog | N29: กำลังดำเนินการเปิด PR/PO
L30: =iferror(vlookup(#REF!,'Back up'!$B$2:$C$18,2),"")
F31: 46117 | L31: =iferror(vlookup(#REF!,'Back up'!$B$2:$C$18,2),"")
A32: 38 | D32: OPA | F32: Origin Phahol 57 | G32: B511 | H32: คุณชิติพัทธ์ จงสถาพรพงศ์ | I32: Built-in | J32: 13200 | K32: 1 | L32: In Progress | M32: ลูกค้าใน Backlog | N32: แจ้งลูกค้าเข้าวัดหน้างานแล้ว จะนัดติดตั้งอีกที ถ้าเร็วก่อนสงกรานต์หรือหลัง
A33: 39 | D33: OPA | F33: Origin Phahol 57 | G33: B328 | H33: คุณณัฐธนัน เลิศพูนผล | I33: Built-in | J33: 12100 | K33: 1 | L33: In Progress | M33: ลูกค้าใน Backlog | N33: ลูกค้าขอนัดติดตั้งก่อนสงกรานต์ แจ้งทาง QC ประสานงาน
A34: 40 | D34: Call | F34: Origin Place Khon Kaen-Kanlapaphruek | G34: A214 | H34: คุณระพีพงศ์ บุ่งศรี | I34: Built-in | J34: 11495 | K34: 1 | L34: In Progress | M34: ลูกค้าใน Backlog | N34: โทรสอบถามเรื่องการเข้าตกแต่ง / จะรับห้องสัปดาห์หน้า พร้อมตกแต่ง
A35: 41 | D35: LINE OA | F35: Origin Place Khon Kaen-Kanlapaphruek | G35: B611 | H35: คุณดวงพร สมสวย | I35: Built-in | J35: 30000 | K35: 1 | L35: In Progress | M35: ลูกค้าใน Backlog | N35: สอบถามเรื่องจะขึ้นไปขอนแก่นอีกมั้ย / ส่งวัสดุให้เลือก
A36: 1 | D36: Call | F36: Origin Place Khon Kaen-Kanlapaphruek | G36: A506 | H36: คุณออ | I36: Curtain, wallcovering | K36: 1 | L36: In Progress | M36: ลูกค้าใหม่ยังไม่จอง | N36: หา Rev ให้ลูกค้า
L37: =iferror(vlookup(#REF!,'Back up'!$B$2:$C$18,2),"")
F38: 46120 | L38: =iferror(vlookup(#REF!,'Back up'!$B$2:$C$18,2),"")
A39: 45 | D39: OPA | F39: Origin Phahol 57 | G39: B511 | H39: คุณชิติพัทธ์ จงสถาพรพงศ์ | I39: Built-in | J39: 13200 | K39: 1 | L39: In Progress | M39: ลูกค้าใน Backlog | N39: แจ้ง QC ติดตามงานม่านให้เข้าวันเสาร์ 11/04/26
A40: 1 | D40: แนะนำ | F40: Origin Phahol 57 | G40: A507 | H40: คุณพิมลพรรณ สีสิงห์ | I40: Built-in, Curtain, wallcovering | J40: 344240 | K40: ส่ง QT & Package | L40: In Progress | M40: ลูกค้าใหม่ยังไม่จอง | N40: ส่ง File วอลล์เปเปอร์ให้ลูกค้าเลือก / รอสรุปวัสดุ
A41: 2 | D41: OPA | F41: Origin Place Khon Kaen-Kanlapaphruek | G41: A702-A703 | H41: คุณทิรา | I41: Built-in | K41: ส่ง QT & Package | L41: In Progress | M41: ลูกค้าใหม่ยังไม่จอง | N41: ทักสอบถามเพิ่มเติมเรื่อง Package ที่ส่งให้
A42: 48 | F42: Origin Place Khon Kaen-Kanlapaphruek | G42: B516 | H42: คุณกัญญาณัฐ โคโตศรี | I42: Built-in, Loose furniture | J42: 87400 | K42: 0.5 | L42: In Progress | M42: ลูกค้าใน Backlog | N42: คุยเรื่องการเข้าตกแต่ง/เสร็จช่วงไหน กำหนดต้องเสร็จ พ.ค.
A43: 3 | F43: Origin Place Khon Kaen-Kanlapaphruek | G43: A825 | H43: คุณธีรวัฒน์ | I43: Built-in | J43: 250000 | K43: ส่ง QT & Package | L43: In Progress | M43: ลูกค้าใหม่ยังไม่จอง | N43: ส่ง Package ห้องตัวอย่าง เลือกทำบางรายการ มีงบ 100,000 บ.
A44: 4 | L44: In Progress
F45: 46123 | L45: =iferror(vlookup(#REF!,'Back up'!$B$2:$C$18,2),"")
A46: 1 | D46: OPA | F46: Origin Place Khon Kaen-Kanlapaphruek | G46: A413 | H46: สมหญิง สมทรัพย์สิน | I46: Built-in | L46: In Progress | M46: ลูกค้าใหม่ยังไม่จอง | N46: สนใจติดวอลล์ เเละตกเเต่งภายใน
A47: 2 | D47: OPA | F47: Origin Place Khon Kaen-Kanlapaphruek | G47: B534 | H47: สุกันยา นาตาล | I47: Built-in | L47: In Progress | M47: ลูกค้าใหม่ยังไม่จอง | N47: เเละตกเเต่งภายใน
A48: 3 | D48: OPA | F48: Origin Place Khon Kaen-Kanlapaphruek | G48: B811 | H48: คุณจันทนา | I48: Built-in | K48: ส่ง QT & Package | L48: In Progress | M48: ลูกค้าใหม่ยังไม่จอง | N48: สนใจแต่งตามห้องตัวอย่าง
A49: 4 | D49: OPA | F49: Origin Place Khon Kaen-Kanlapaphruek | G49: A825 | H49: ธีรวัฒน์ มณีวัฒน์ | I49: Built-in, Curtain, wallcovering | K49: ส่ง QT & Package | L49: In Progress | M49: ลูกค้าใหม่ยังไม่จอง | N49: ติดตามต่อ สนใจบางรายการ
A50: 5 | D50: OPA | F50: Origin Place Khon Kaen-Kanlapaphruek | G50: A832 | H50: อ้อมทิพย์ ศรีจันทะ | I50: Built-in | K50: ส่ง QT & Package | L50: In Progress | M50: ลูกค้าใหม่ยังไม่จอง | N50: หาข้อมูลที่นอนที่ดีกว่าใน Package ให้ลูกค้า
A51: 6 | D51: OPA | F51: Origin Place Khon Kaen-Kanlapaphruek | G51: B710-13 | H51: คุณ เมธา รักแก้ว | I51: Built-in | M51: ลูกค้าใหม่ยังไม่จอง
F53: 13/04/26 Holidy | L53: =iferror(vlookup(#REF!,'Back up'!$B$2:$C$18,2),"")
F54: 14/04/26 Holidy | L54: =iferror(vlookup(#REF!,'Back up'!$B$2:$C$18,2),"")
F55: 15/04/26 Holidy | L55: =iferror(vlookup(#REF!,'Back up'!$B$2:$C$18,2),"")
F56: 16/04/26 Holidy | L56: =iferror(vlookup(#REF!,'Back up'!$B$2:$C$18,2),"")
A57: 1 | D57: OPA | F57: Origin Place Khon Kaen-Kanlapaphruek | G57: A702 | H57: คุณทิรา | I57: Built-in | J57: 80000 | K57: ส่ง QT & Package | L57: In Progress | M57: ลูกค้าใหม่ยังไม่จอง | N57: ลูกค้าสนใจให้ส่งราคาตามที่ส่ง Line มา
A58: 2 | D58: OPA | F58: Origin Place Khon Kaen-Kanlapaphruek | G58: A703 | H58: คุณทิรา | I58: Built-in | J58: 80000 | K58: ส่ง QT & Package | L58: In Progress | M58: ลูกค้าใหม่ยังไม่จอง | N58: ลูกค้าสนใจให้ส่งราคาตามที่ส่ง Line มา
F60: 17/04/26 Holidy | L60: =iferror(vlookup(#REF!,'Back up'!$B$2:$C$18,2),"")
A61: 1 | D61: OPA | F61: Origin Place Khon Kaen-Kanlapaphruek | G61: A832 | H61: อ้อมทิพย์ ศรีจันทะ | I61: Built-in, Loose furniture | J61: 91800 | K61: ส่ง QT & Package | L61: In Progress | M61: ลูกค้าใหม่ยังไม่จอง | N61: สรุป Package กำลังจะจอง
F63: 46130 | L63: =iferror(vlookup(#REF!,'Back up'!$B$2:$C$18,2),"")
A64: 1 | D64: OPA | F64: Origin Place Khon Kaen-Kanlapaphruek | G64: A624 | H64: คุณพิชิต | I64: Built-in | K64: ส่ง QT & Package | L64: In Progress | M64: ลูกค้าใหม่ยังไม่จอง | N64: สนใจตกแต่งห้อง ขอคุยรายละเอียดเพิ่มเติม
A65: 2 | D65: OPA | F65: SO Origin Siriraj | G65: 716 | H65: คุณเสาวลักษณ์ พันธ์เรืองวงศ์ | I65: Curtain | J65: 300000 | K65: ส่ง QT & Package | L65: In Progress | M65: ลูกค้าจองสิทธิ์ | N65: อาจจะเปลี่ยนเป็นงานม่านอย่างเดียว
A66: 3 | D66: OPA | F66: SO Origin Siriraj | G66: 1111 | H66: คุณปวีณา อมรรัตนกุล | I66: Built-in | J66: 1000000 | K66: ส่ง QT & Package | L66: In Progress | M66: ลูกค้าจองสิทธิ์ | N66: ขอตรวจห้องก่อนแล้วจะแจ้งกลับ
A67: 4 | D67: OPA | F67: SO Origin Siriraj | G67: 1808 | H67: คุณเจตนา เจียมพฤกษ์วัฒนา | I67: Built-in | J67: 800000 | K67: ส่ง QT & Package | L67: In Progress | M67: ลูกค้าจองสิทธิ์ | N67: กำลังเปรียบกับอีกเจ้า
A68: 5 | D68: OPA | F68: SO Origin Siriraj | G68: 714 | H68: คุณอนงค์ ลีละเศรษฐกุล | I68: Built-in | J68: 53760 | K68: ส่ง QT & Package | L68: In Progress | M68: ลูกค้าจองสิทธิ์ | N68: ขอตรวจห้องก่อนแล้วจะแจ้งกลับ
A69: 6 | D69: OPA | F69: Origin Place Khon Kaen-Kanlapaphruek | G69: A832 | H69: อ้อมทิพย์ ศรีจันทะ | I69: Loose furniture | J69: 91800 | K69: 1 | L69: In Progress | M69: ลูกค้าใหม่ยังไม่จอง | N69: รอชำระ 50%
A70: 7 | D70: OPA | F70: SO Origin Phahol 69 | G70: 614 | H70: คุณเมยวดี ศรีดี | I70: Curtain | J70: 35360 | K70: 0.5 | L70: In Progress | M70: ลูกค้าใน Backlog | N70: ติดตามเรื่องติดตั้งม่าน
A71: 8 | D71: OPA | F71: Origin Place Khon Kaen-Kanlapaphruek | G71: A414 | H71: คุณพีรพล จ่าเคน | I71: Curtain, Built-in | J71: 300000 | K71: 0.5 | L71: In Progress | M71: ลูกค้าจองสิทธิ์
F73: 46132 | L73: =iferror(vlookup(#REF!,'Back up'!$B$2:$C$18,2),"")
A74: 1 | D74: OPA | F74: Origin Place Khon Kaen-Kanlapaphruek | G74: A832 | H74: อ้อมทิพย์ ศรีจันทะ | I74: Loose furniture | J74: 91800 | K74: 1 | L74: In Progress | M74: ลูกค้าใน Backlog | N74: ชำระ 50% ติดตามงานต่อ
A75: 2 | D75: OPA | F75: Origin Place Khon Kaen-Kanlapaphruek | G75: A702 | H75: คุณทิรา | I75: Loose furniture | K75: 1 | L75: In Progress | M75: สถานะลูกค้า | N75: ส่งใบเสนอราคา
A76: 3 | D76: OPA | F76: Origin Place Khon Kaen-Kanlapaphruek | G76: A703 | H76: คุณทิรา | I76: Loose furniture | K76: 1 | L76: In Progress | M76: สถานะลูกค้า | N76: ส่งใบเสนอราคา
A77: 4 | D77: OPA | F77: Origin Place Khon Kaen-Kanlapaphruek | G77: A624 | H77: คุณพิชิต | I77: Loose furniture | K77: 1 | L77: In Progress | M77: ลูกค้าใหม่ยังไม่จอง | N77: อยู่ระหว่างดูราคา
I78: Loose furniture | K78: 1 | L78: In Progress | M78: สถานะลูกค้า
F79: 46134 | L79: =iferror(vlookup(#REF!,'Back up'!$B$2:$C$18,2),"")
A80: 1 | D80: OPA | F80: Kampus Khonkaen | H80: คุณชัยณรงค์ | I80: Loose furniture | K80: 1 | L80: In Progress | M80: สถานะลูกค้า | N80: วันนี้ส่งใบเสนอราคา
A81: 2 | D81: OPA | F81: Origin Place Khon Kaen-Kanlapaphruek | G81: B526 | H81: พิลาวรรณ | I81: Loose furniture, Built-in | K81: 1 | L81: In Progress | M81: สถานะลูกค้า | N81: นัดส่งลามิเนตให้เลือกก่อนติดตั้ง
A82: 3 | D82: OPA | F82: Origin Place Khon Kaen-Kanlapaphruek | G82: B412 | H82: กนกวรรณ | I82: Loose furniture | K82: 1 | L82: In Progress | M82: สถานะลูกค้า | N82: ส่งลามิเนตให้เลือก เพื่อ CF
I83: Loose furniture | K83: 1 | L83: In Progress | M83: สถานะลูกค้า
F84: 46135 | L84: =iferror(vlookup(#REF!,'Back up'!$B$2:$C$18,2),"")
A85: 1 | D85: หาเอง | F85: SO Origin Phromphong (Park24) | G85: 50307 | H85: คุณดีมาก | I85: EQ ซ่อมแผ่นดินไหว | K85: 0.5 | L85: In Progress | M85: สถานะลูกค้า | N85: Revise ราคาใหม่
A86: 2 | D86: OPA | F86: Origin Place Khon Kaen-Kanlapaphruek | G86: B506 | H86: คุุณมนัสนันท์ | I86: Loose furniture, Curtain, Design | K86: 0.2 | L86: In Progress | M86: สถานะลูกค้า | N86: อยู่ในระหว่างสอบถาม
A87: 3 | D87: OPA | F87: Origin Kampus Khonkaen | H87: คุณชัยณรงค์ | I87: Loose furniture | K87: 1 | L87: In Progress | M87: สถานะลูกค้า | N87: โทรแนะนำเรื่องวัสดุกรุผนัง
A88: 4 | D88: LINE OA | F88: The Origin Phahol 57 | G88: B302 | I88: Loose furniture | K88: 1 | L88: In Progress | M88: สถานะลูกค้า | N88: ทักไลน์ OA แจ้ง Summer Specail Promotion Voucher 3,000 บ. เพื่อให้ลูกค้าสนใจ / ไม่ตอบรับ
A89: 5 | D89: LINE OA | F89: The Origin Phahol 57 | G89: A305 | I89: Curtain | K89: 0.2 | L89: In Progress | M89: สถานะลูกค้า | N89: ทักไลน์ OA แจ้ง Summer Specail Promotion Voucher 3,000 บ. เพื่อให้ลูกค้าสนใจ / ไม่ตอบรับ
A90: 6 | D90: LINE OA | F90: The Origin Phahol 57 | G90: B306 | I90: Curtain | K90: 0.2 | L90: In Progress | M90: สถานะลูกค้า | N90: ทักไลน์ OA แจ้ง Summer Specail Promotion Voucher 3,000 บ. เพื่อให้ลูกค้าสนใจ / ไม่ตอบรับ
A91: 7 | D91: LINE OA | F91: The Origin Phahol 57 | G91: B322 | H91: คุณโบว์ | I91: Curtain | K91: 0.2 | L91: In Progress | M91: สถานะลูกค้า | N91: ทักไลน์ OA แจ้ง Summer Specail Promotion Voucher 3,000 บ. เพื่อให้ลูกค้าสนใจ / ไม่ตอบรับ
A92: 8 | D92: LINE OA | F92: The Origin Phahol 57 | G92: B403 | H92: คุณจีราพร ป่าหวาย | I92: Curtain | K92: 0.2 | L92: In Progress | M92: สถานะลูกค้า | N92: ทักไลน์ OA แจ้ง Summer Specail Promotion Voucher 3,000 บ. เพื่อให้ลูกค้าสนใจ / ไม่ตอบรับ
A93: 10 | D93: LINE OA | F93: The Origin Phahol 57 | G93: B601 | H93: ภีรดา ตรันเจริญ | I93: Curtain | K93: 0.2 | L93: In Progress | M93: สถานะลูกค้า | N93: ทักไลน์ OA แจ้ง Summer Specail Promotion Voucher 3,000 บ. เพื่อให้ลูกค้าสนใจ / ไม่ตอบรับ
A94: 11 | D94: LINE OA | F94: The Origin Phahol 57 | G94: B304 | H94: แบม | I94: Curtain | K94: 0.2 | L94: In Progress | M94: สถานะลูกค้า | N94: ทักไลน์ OA แจ้ง Summer Specail Promotion Voucher 3,000 บ. เพื่อให้ลูกค้าสนใจ / ไม่ตอบรับ
A95: 12 | D95: LINE OA | F95: The Origin Phahol 57 | G95: B222 | I95: Curtain | K95: 0.2 | L95: In Progress | M95: สถานะลูกค้า | N95: ทักไลน์ OA แจ้ง Summer Specail Promotion Voucher 3,000 บ. เพื่อให้ลูกค้าสนใจ / ไม่ตอบรับ
A96: 13 | D96: LINE OA | F96: The Origin Phahol 57 | G96: A603 | I96: Curtain | K96: 0.2 | L96: In Progress | M96: สถานะลูกค้า | N96: ทักไลน์ OA แจ้ง Summer Specail Promotion Voucher 3,000 บ. เพื่อให้ลูกค้าสนใจ / ไม่ตอบรับ
A97: 14 | D97: LINE OA | F97: The Origin Phahol 57 | G97: A507 | I97: Curtain | K97: 0.2 | L97: In Progress | M97: สถานะลูกค้า | N97: ทักไลน์ OA แจ้ง Summer Specail Promotion Voucher 3,000 บ. เพื่อให้ลูกค้าสนใจ / ไม่ตอบรับ
A98: 15 | D98: LINE OA | F98: The Origin Phahol 57 | G98: A604 | I98: Curtain | K98: 0.2 | L98: In Progress | M98: สถานะลูกค้า | N98: ทักไลน์ OA แจ้ง Summer Specail Promotion Voucher 3,000 บ. เพื่อให้ลูกค้าสนใจ / ไม่ตอบรับ
A99: 16 | D99: LINE OA | F99: The Origin Phahol 57 | G99: B632 | I99: Curtain | K99: 0.2 | L99: In Progress | M99: สถานะลูกค้า | N99: ทักไลน์ OA แจ้ง Summer Specail Promotion Voucher 3,000 บ. เพื่อให้ลูกค้าสนใจ / ไม่ตอบรับ
A100: 17 | D100: LINE OA | F100: The Origin Phahol 57 | G100: A829 | I100: Curtain | K100: 0.2 | L100: In Progress | M100: สถานะลูกค้า | N100: ทักไลน์ OA แจ้ง Summer Specail Promotion Voucher 3,000 บ. เพื่อให้ลูกค้าสนใจ / ตอบรับ
A101: 18 | D101: LINE OA | F101: The Origin Phahol 57 | G101: B421 | I101: Curtain | K101: 0.2 | L101: In Progress | M101: สถานะลูกค้า | N101: ทักไลน์ OA แจ้ง Summer Specail Promotion Voucher 3,000 บ. เพื่อให้ลูกค้าสนใจ / ไม่ตอบรับ
A102: 19 | D102: LINE OA | F102: The Origin Phahol 57 | G102: B311 | I102: Curtain | K102: 0.2 | L102: In Progress | M102: สถานะลูกค้า | N102: ทักไลน์ OA แจ้ง Summer Specail Promotion Voucher 3,000 บ. เพื่อให้ลูกค้าสนใจ / ไม่ตอบรับ
A103: 20 | D103: LINE OA | F103: The Origin Phahol 57 | G103: A525 | I103: Curtain | K103: 0.2 | L103: In Progress | M103: สถานะลูกค้า | N103: ทักไลน์ OA แจ้ง Summer Specail Promotion Voucher 3,000 บ. เพื่อให้ลูกค้าสนใจ / ไม่ตอบรับ
A104: 21 | D104: LINE OA | F104: The Origin Phahol 57 | G104: B329 | I104: Curtain | K104: 0.2 | L104: In Progress | M104: สถานะลูกค้า | N104: ทักไลน์ OA แจ้ง Summer Specail Promotion Voucher 3,000 บ. เพื่อให้ลูกค้าสนใจ / ไม่ตอบรับ
...

Sheet Yingเก่า
A2: SALES : YING
A3: **** WEEKLY REPORT : รายงานการทำงานรายสัปดาห์ ระบุการทำงานเกี่ยวกับ ลูกค้าใหม่ที่ยังไม่จอง และ ลูกค้าใน Backlog + งานอื่นๆที่ทำอยู่ ****
A5: No. | B5: วันที่เจอลูกคัาครั้งแรก | C5: Close date | D5: วันล่าสุดที่ติดต่อ/ แผนติดต่อ | E5: Clients type | F5: Project | G5: Name | H5: Room | I5: สถานะลูกค้า | J5: สถานะปัจจุบัน | K5: รายละเอียดการทำงาน | L5: Next Update | M5: คาดยอดขาย | N5: ช่องทาง | O5: Phone | P5: Product Type | Q5: Design Package | R5: โอกาสปิด (%) | S5: SALES | T5: สถานะปัจจุบัน | U5: Close/Inprogress | V5: Follow up | W5: Status | X5: Follow up | Y5: Status
A6: 4 | F6: Origin Play Bangkunnon | G6: พงษ์พัฒน์ (โอม) | H6: 2301 | I6: ลููกค้าไม่ซื้อแล้ว | K6: ส่งใบเสนอราคาแล้ว / ไม่สนใจ | M6: 1052000 | N6: OPA | P6: Built-in | Q6: Fully design(L) | R6: 0.2 | S6: Yingying | T6: Quotation | U6: =iferror(vlookup(W6,'Back up'!$B$2:$C$18,2,0),"") -> Inprogress | V6: Line | W6: เสนอราคาแล้ว รอตัดสินใจ เปรียบเทียบกับคู่แข่ง
A7: 5 | F7: Knights Bridge Space Sukhumvit-Rama4 | G7: คุณ คูณ | H7: 1812 | I7: ลููกค้าไม่ซื้อแล้ว | K7: ส่งใบเสนอราคาแล้ว / ไม่สนใจ | M7: 100000 | N7: OPA | P7: ready | Q7: Investor Pro(M) | R7: 0.2 | S7: Yingying | T7: Quotation | U7: =iferror(vlookup(W7,'Back up'!$B$2:$C$18,2,0),"") -> Inprogress | V7: Line | W7: เสนอราคาแล้ว ทำนัดลูกค้าอีกรอบ
A8: 11 | D8: 46116 | F8: Aspire Onnuch station | G8: Ms. Ko Han | H8: 335 | I8: ลููกค้าไม่ซื้อแล้ว | K8: ส่งใบเสนอราคาแล้ว / ไม่สนใจ | M8: 100000 | N8: หาเอง | P8: ready | Q8: Investor Pro(M) | R8: 0.2 | S8: Yingying | T8: Quotation | U8: =iferror(vlookup(W8,'Back up'!$B$2:$C$18,2,0),"") -> Inprogress | V8: Line | W8: เสนอราคาแล้ว รอตัดสินใจ เปรียบเทียบกับคู่แข่ง
A9: 12 | F9: Park Origin Thonglor | G9: ธนินทร์ | H9: B2513 | I9: ลููกค้าไม่ซื้อแล้ว | K9: ส่งใบเสนอราคาแล้ว / รอพิจารณา | M9: 300000 | N9: OPA | P9: EQ ซ่อมแผ่นดินไหว | Q9: Fully design(L) | R9: 0.2 | S9: Yingying | T9: Quotation | U9: =iferror(vlookup(W9,'Back up'!$B$2:$C$18,2,0),"") -> Inprogress | V9: Line | W9: เสนอราคาแล้ว รอตัดสินใจ เปรียบเทียบกับคู่แข่ง
A10: 13 | F10: Origin Plug&Play Sirindhorn Station | G10: คุ๊กกี้ | H10: B2402 | I10: ลููกค้าไม่ซื้อแล้ว | K10: ส่งใบเสนอราคาแล้ว / รอพิจารณา | M10: 200000 | N10: OPA | P10: Built-in | Q10: Fully design(L) | R10: 0.2 | S10: Yingying | T10: Quotation | U10: =iferror(vlookup(W10,'Back up'!$B$2:$C$18,2,0),"") -> Inprogress | V10: Line | W10: เสนอราคาแล้ว รอตัดสินใจ เปรียบเทียบกับคู่แข่ง
A11: 14 | F11: Park Origin Thonglor | G11: สปัน เติมศักดิ์ | H11: B4008 | I11: ลููกค้าไม่ซื้อแล้ว | K11: ส่งใบเสนอราคาแล้ว / รอพิจารณา | M11: 300000 | N11: OPA | P11: EQ ซ่อมแผ่นดินไหว | Q11: Fully design(L) | R11: 0.2 | S11: Yingying | T11: Quotation | U11: =iferror(vlookup(W11,'Back up'!$B$2:$C$18,2,0),"") -> Inprogress | V11: Line | W11: เสนอราคาแล้ว รอตัดสินใจ เปรียบเทียบกับคู่แข่ง
A12: 16 | D12: 46116 | F12: Origin Play Bangkunnon | G12: เต็ม | H12: 919 | I12: ลูกค้าตามซื้อเพิ่ม | K12: ส่งใบเสนอราคาแล้ว / รอพิจารณา | M12: 13100 | N12: หาเอง | P12: wallcovering | R12: 0.9 | S12: Yingying | T12: Quotation | V12: Line | W12: ระหว่างคุยรายละเอียด
A13: 18 | D13: 46122 | F13: Origin Place Bangna | G13: เมเม่ | H13: 532 | I13: ลูกค้าในBacklog | K13: คุยบรีฟออกแบบ | M13: 300000 | N13: OPA | P13: Built-in | R13: 0.9 | S13: Yingying | T13: Quotation | U13: =iferror(vlookup(W13,'Back up'!$B$2:$C$18,2),"") -> Close Lead | V13: Call | W13: ลูกค้าชำระเงินเรียบร้อย
A14: 20 | D14: 46120 | F14: Plug ang Play Srinakarin | G14: อัลชลี | H14: 1615 | I14: ลูกค้าใหม่ยังไม่จอง | K14: ลค นัดเลือกผ้าม่าน | M14: 22100 | N14: OPA | P14: Curtain | R14: 0.5 | S14: Yingying | T14: Quotation | U14: =iferror(vlookup(W14,'Back up'!$B$2:$C$18,2),"") -> Close Lead | V14: Line | W14: เสนอราคาแล้ว แต่ขอเวลาตัดสินใจก่อน7
A15: 21 | D15: 46116 | F15: Origin Play Bangkhunnon | G15: นวชน | H15: 12A03 | I15: ลูกค้าในBacklog | K15: นัดลูกค้าตรวจรับมอบงาน / รับชำระ / ทำเอกสารส่งมอบงาน | N15: OPA | P15: Built-in | U15: =iferror(vlookup(W15,'Back up'!$B$2:$C$18,2),"")
A16: 22 | D16: 46116 | F16: Origin Play Bangkhunnon | G16: บัณฑิตา ทิพย์จักษุ | H16: 812 | I16: ลูกค้าในBacklog | K16: ตรวจรับมอบงาน // ผ่านไม่มีแก้ดีเฟค // รับชำระงวดสุดท้าย | N16: OPA | P16: Built-in | U16: =iferror(vlookup(W16,'Back up'!$B$2:$C$18,2),"")
A17: 24 | D17: 46122 | F17: Origin Play Bangkhunnon | G17: วรณี ศิริจงมีชัย | H17: 1418 | I17: ลูกค้าในBacklog | K17: คุยปรับรายการใบเสนอราคา | M17: 98000 | N17: OPA | P17: Built-in | U17: =iferror(vlookup(W17,'Back up'!$B$2:$C$18,2),"")
A18: 25 | D18: 46123 | F18: Origin Play Bangkhunnon | G18: ชโลธร | H18: 802 | I18: ลูกค้าในBacklog | K18: นัดเลือกม่านวอลล์ 05/04/26 | N18: OPA | U18: =iferror(vlookup(W18,'Back up'!$B$2:$C$18,2),"")
A19: 23 | D19: 46117 | F19: Origin Play Bangkhunnon | G19: อาทิตย์ ภูเกียรติก้อง | H19: 2707 | I19: ลูกค้าในBacklog | K19: นัด คุยบรีฟออกแบบ เพื่อปรับแบบ 05/04/26 | N19: OPA | P19: Built-in | U19: =iferror(vlookup(W19,'Back up'!$B$2:$C$18,2),"")
A20: 18 | D20: 46123 | F20: Origin Place Bangna | G20: ผสุดี สินธนานุกูล | H20: 532 | I20: ลูกค้าในBacklog | K20: คุยบรีฟออกแบบ / เสนอแบบเฟอร์นิเจอร์เพิ่มเติม | M20: 300000 | N20: OPA | P20: Built-in | R20: 0.9 | S20: Yingying | T20: Quotation | U20: =iferror(vlookup(W20,'Back up'!$B$2:$C$18,2),"") -> Close Lead | V20: Call | W20: ลูกค้าชำระเงินเรียบร้อย
A21: 29 | D21: 46121 | F21: Origin Play Bangkhunnon | G21: ณัฐชพร พรหมคำ | H21: 1909 | I21: ลูกค้าในBacklog | K21: นัดสรุปรายละเอียดสี วัสดุ/ ม่านวอลล | N21: OPA | P21: Built-in | U21: =iferror(vlookup(W21,'Back up'!$B$2:$C$18,2),"")
A22: 30 | D22: 46122 | F22: Origin Play Bangkhunnon | G22: หทัยชนก โมเรโน | H22: 2207 | I22: ลูกค้าในBacklog | K22: นัด คุยแบบครั้งสุดท้าย และ สรุปรายการตกแต่ง เลือกม่าน | N22: OPA | P22: Built-in | U22: =iferror(vlookup(W22,'Back up'!$B$2:$C$18,2),"")
A23: 31 | D23: 46120 | F23: Origin Place Bangna | H23: 710 | I23: ลูกค้าใหม่ยังไม่จอง | K23: เสนอราคาม่าน | N23: OPA | P23: Curtain | U23: =iferror(vlookup(W23,'Back up'!$B$2:$C$18,2),"")
A24: 32 | D24: 46120 | F24: Origin Place Bangna | H24: 810 | I24: ลูกค้าใหม่ยังไม่จอง | K24: เสนอราคาม่าน | N24: OPA | P24: Curtain | U24: =iferror(vlookup(W24,'Back up'!$B$2:$C$18,2),"")
A25: 34 | D25: 46123 | F25: Origin Play Bangkhunnon | H25: 1703 | I25: ลูกค้าในBacklog | K25: นัดส่งมอบงาน | N25: OPA | P25: Curtain | U25: =iferror(vlookup(W25,'Back up'!$B$2:$C$18,2),"")
A26: 35 | D26: 46123 | F26: Origin Play Bangkhunnon | H26: 919 | I26: ลูกค้าในBacklog | K26: นัดส่งมอบงาน | N26: OPA | P26: Curtain | U26: =iferror(vlookup(W26,'Back up'!$B$2:$C$18,2),"")
A27: 36 | D27: 46122 | F27: Prodigy | H27: 642 | I27: ลูกค้าในBacklog | K27: นัดคุยบรีฟเพิ่มเติมหน้างาน | N27: OPA | P27: Built-in | U27: =iferror(vlookup(W27,'Back up'!$B$2:$C$18,2),"")
A28: 37 | D28: 46124 | F28: Park Origin Thonglor | H28: C4207 | I28: ลูกค้าในBacklog | K28: ลค นัดดูความคืบหน้างานซ่อมแผ่นดินไหว | N28: OPA | P28: EQ ซ่อมแผ่นดินไหว | U28: =iferror(vlookup(W28,'Back up'!$B$2:$C$18,2),"")
A29: 38 | D29: 46124 | F29: KNB space SK- rama 4 | H29: 2008 | I29: ลูกค้าในBacklog | K29: อัพเดตหน้างานให้ลูกค้า / นัดเลือกสีม่าน | N29: OPA | P29: Built-in | U29: =iferror(vlookup(W29,'Back up'!$B$2:$C$18,2),"")
A30: 39 | D30: 46132 | F30: Origin Place Bangna | H30: 708 | I30: ลูกค้าใหม่ยังไม่จอง | K30: นัดคุยบรีฟงานตกแต่ง วีดพื้นที่ | N30: OPA | P30: Loose furniture | U30: =iferror(vlookup(W30,'Back up'!$B$2:$C$18,2),"")
D31: 46128 | F31: วันหยุดประจำสัปดาห์
B32: วันหยุด | D32: 46129 | F32: Origin Play Bangkhunnon | G32: วรณี ศิริจงมีชัย | H32: 1418 | I32: ลูกค้าในBacklog | K32: ตาม ลค คุยปรับรายการใบเสนอราคา / แก้ไขใบเสนอราคา
B33: วันหยุด | D33: 46129 | F33: ออริจิ้น บางแค | H33: A228 | I33: ลูกค้าในBacklog | K33: คุยลูกค้าเสนอแพ็คปล่อยเช่า
B34: วันหยุด | D34: 46129 | F34: Place bangna | H34: 532 | I34: ลูกค้าในBacklog | K34: ทำบรีฟออกแบบ ส่งทีมดีไซน์เนอร์
A35: 45 | B35: วันหยุด | D35: 46129 | F35: Origin Play Bangkhunnon | H35: 2513 | I35: ลูกค้าในBacklog | K35: คอลตามลูกค้า / ผล : | U35: =iferror(vlookup(W35,'Back up'!$B$2:$C$18,2),"")
B36: วันหยุด | D36: 46130 | F36: Origin Play Bangkhunnon | H36: 2707 | I36: ลูกค้าในBacklog | K36: ตาม ลูกค้า คุยรับบรีฟปรับแบบ
A37: 46 | B37: วันหยุด | D37: 46130 | F37: Origin Place Bangna | H37: 1239 | I37: ลูกค้าในBacklog | K37: ตามอัพเดต ความคืบหน้า | U37: =iferror(vlookup(W37,'Back up'!$B$2:$C$18,2),"")
A38: 57 | D38: 46132 | F38: Origin Place Bangna | H38: 708 | I38: ลูกค้าใหม่ยังไม่จอง | K38: นัดคุยบรีฟงานตกแต่ง วีดพื้นที่ | U38: =iferror(vlookup(W38,'Back up'!$B$2:$C$18,2),"")
A39: 58 | D39: 46132 | F39: Origin Place Bangna | H39: 1239 | I39: ลูกค้าในBacklog | K39: ตามอัพเดต ความคืบหน้า | U39: =iferror(vlookup(W39,'Back up'!$B$2:$C$18,2),"")
A40: 59 | D40: 46132 | F40: Origin Play Bangkhunnon | H40: 1418 | I40: ลูกค้าในBacklog | K40: ทำใบเสนอราคา / นัดเก็บเงิน | U40: =iferror(vlookup(W40,'Back up'!$B$2:$C$18,2),"")
A41: 60 | D41: 46132 | F41: KNB rama 4 | H41: 2008 | I41: ลูกค้าในBacklog | K41: ตามอัพเดต ความคืบหน้า | U41: =iferror(vlookup(W41,'Back up'!$B$2:$C$18,2),"")
D42: 46133 | F42: so kaset | H42: 1406 | I42: ลูกค้าใหม่ยังไม่จอง | K42: ตาม คุยลค รับรีควายเม้นต์
A43: 61 | D43: 46133 | F43: Origin Play Bangkhunnon | H43: 2513 | I43: ลูกค้าในBacklog | K43: นัดเลือกม่านวอล | U43: =iferror(vlookup(W43,'Back up'!$B$2:$C$18,2),"")
A44: 64 | D44: 46134 | F44: prodigy โครงนอก | H44: 642 | I44: ลูกค้าในBacklog | K44: รับบรีฟแก้แบบแล้ว | U44: =iferror(vlookup(W44,'Back up'!$B$2:$C$18,2),"")
A45: 65 | D45: 46134 | F45: Origin Play Bangkhunnon | H45: 2111 | I45: ลูกค้าใหม่ยังไม่จอง | K45: ตามนัดคุย หน้างาน | U45: =iferror(vlookup(W45,'Back up'!$B$2:$C$18,2),"")
A46: 66 | D46: 46134 | F46: Origin Play Bangkhunnon | H46: 2707 | I46: ลูกค้าในBacklog | K46: รับบรีฟแก้แบบ | U46: =iferror(vlookup(W46,'Back up'!$B$2:$C$18,2),"")
A47: 68 | D47: 46135 | F47: สิรินธร | H47: A1415 | I47: ลูกค้าในBacklog | K47: นัดส่งมอบงาน/ นัดรับชำระ | U47: =iferror(vlookup(W47,'Back up'!$B$2:$C$18,2),"")
A48: 70 | D48: 46135 | F48: Origin Play Bangkunnon | G48: กระแต | H48: 1412 | I48: ลูกค้าใหม่ยังไม่จอง | K48: ตามลค= รอตตรวจห้อง | U48: =iferror(vlookup(W48,'Back up'!$B$2:$C$18,2),"")
A49: 71 | D49: 46135 | F49: Origin Play Bangkhunnon | G49: กระแต | H49: 2804 | I49: ลูกค้าใหม่ยังไม่จอง | U49: =iferror(vlookup(W49,'Back up'!$B$2:$C$18,2),"")
A50: 74 | D50: 46135 | F50: Origin Play Bangkunnon | G50: รัตน์ | H50: 1822 | I50: ลูกค้าใหม่ยังไม่จอง | U50: =iferror(vlookup(W50,'Back up'!$B$2:$C$18,2),"")
B51: คอลลูกค้าโครงเก่า | D51: 46135 | F51: soho bangkok ratchada | H51: 2021 | I51: ลููกค้าไม่ซื้อแล้ว | K51: ตามลค = ซื้อเองแล้ว
B52: คอลลูกค้าโครงเก่า | D52: 46135 | F52: Plug ang Play Nonthaburi Station | G52: อภิชาติ | H52: 2437 | I52: ลูกค้าใหม่ยังไม่จอง | K52: ตามลค = กำลังพิจารณา เดี๋ยวแจ้งกลับ
B53: คอลลูกค้าโครงเก่า | D53: 46135 | F53: Park Origin Chula Samyan | G53: เคส พี่มด | H53: 3707 | I53: ลูกค้าใหม่ยังไม่จอง | K53: ตามลค = ตามนัดลูกค้าคุยหน้างาน 18/04/26
B54: คอลลูกค้าโครงเก่า | D54: 46135 | F54: Nonthaburi station | G54: อรณิชา จิระอุปการ | H54: 2139 | I54: ลููกค้าไม่ซื้อแล้ว | K54: หาซื้อเอง
B55: คอลลูกค้าโครงเก่า | D55: 46135 | F55: Knights Bridge Space Sukhumvit-Rama4 | G55: Ms.Yuen Yee Ada NGAN | H55: 1905 | I55: ลููกค้าไม่ซื้อแล้ว | K55: ไม่อยากทำแล้ว
B56: คอลลูกค้าโครงเก่า | D56: 46135 | F56: Park Origin Thonglor | G56: Mr. Sing Yung sen | H56: B2610 | I56: ลููกค้าไม่ซื้อแล้ว | K56: ตามลค = หาผรมเองแล้ว
B57: คอลลูกค้าโครงเก่า | D57: 46135 | F57: Origin Plug&Play Sirindhorn Station | G57: คุ๊กกี้ | H57: B2402 | I57: ลููกค้าไม่ซื้อแล้ว | K57: ตกแต่งแล้ว
B58: คอลลูกค้าโครงเก่า | D58: 46135 | F58: Origin Plug&Play Sirindhorn Station | H58: A712 | I58: ลูกค้าใหม่ยังไม่จอง | K58: ไม่่สนใจ อยู่ไปแล้ว
B59: คอลลูกค้าโครงเก่า | D59: 46135 | F59: Origin Plug&Play Sirindhorn Station | H59: C1905 | I59: ลูกค้าใหม่ยังไม่จอง | K59: ไม่่สนใจ อยู่ไปแล้ว
B60: คอลลูกค้าโครงเก่า | D60: 46135 | F60: Origin Plug&Play Sirindhorn Station | H60: A1106 | I60: ลูกค้าใหม่ยังไม่จอง | K60: ยังไม่สนใจ
B61: คอลลูกค้าโครงเก่า | D61: 46135 | F61: Origin Plug&Play Sirindhorn Station | H61: B1016 | I61: ลูกค้าใหม่ยังไม่จอง | K61: ซื้อของแต่งเองแล้ว
B62: คอลลูกค้าโครงเก่า | D62: 46135 | F62: Origin Plug&Play Sirindhorn Station | H62: B905 | I62: ลูกค้าใหม่ยังไม่จอง | K62: ลคเก่า / ตามซื้อเพิ่ม = ยังไม่สนใจ
B63: คอลลูกค้าโครงเก่า | D63: 46135 | F63: Origin Plug&Play Sirindhorn Station | H63: C2001 | I63: ลูกค้าใหม่ยังไม่จอง | K63: ไม่ตอบ
B64: คอลลูกค้าโครงเก่า | D64: 46135 | F64: Origin Plug&Play Sirindhorn Station | H64: C12A17 | I64: ลูกค้าใหม่ยังไม่จอง | K64: ไม่่สนใจ อยู่ไปแล้ว
B65: คอลลูกค้าโครงเก่า | D65: 46135 | F65: Origin Plug&Play Sirindhorn Station | H65: B701 | I65: ลูกค้าใหม่ยังไม่จอง | K65: ไม่ตอบ
B66: คอลลูกค้าโครงเก่า | D66: 46135 | F66: Origin Plug&Play Sirindhorn Station | H66: C1612 | I66: ลูกค้าใหม่ยังไม่จอง | K66: ไม่ตอบ
B67: คอลลูกค้าโครงเก่า | D67: 46135 | F67: Origin Plug&Play Sirindhorn Station | H67: C2003 | I67: ลูกค้าใหม่ยังไม่จอง | K67: ลคเก่า / ตามซื้อเพิ่ม = ยังไม่สนใจ
B68: คอลลูกค้าโครงเก่า | D68: 46135 | F68: Origin Plug&Play Sirindhorn Station | H68: C2018 | I68: ลูกค้าใหม่ยังไม่จอง | K68: ลคเก่า / ตามซื้อเพิ่ม = ยังไม่สนใจ
B69: คอลลูกค้าโครงเก่า | D69: 46135 | F69: Origin Plug&Play Sirindhorn Station | H69: A714 | I69: ลูกค้าใหม่ยังไม่จอง | K69: ติดต่อไม่ได้
B70: คอลลูกค้าโครงเก่า | D70: 46135 | F70: Origin Plug&Play Sirindhorn Station | H70: 1005 | I70: ลูกค้าใหม่ยังไม่จอง | K70: ขอคิดดูก่อน / สนใจเมื่อไร จะติดต่อ
D71: 46136 | F71: KNB rama 4 | H71: 2008 | I71: ลูกค้าในBacklog | K71: คุยแบบหน้างานเพิ่มกับช่าง/ ดูความคืบหน้า | U71: =iferror(vlookup(W71,'Back up'!$B$2:$C$18,2),"")
D72: 46136 | F72: ทองหล่อ | H72: B2511 | I72: ลูกค้าในBacklog | K72: ลคเก่า/ ตามเลื่อนโคมไฟ
D73: 46136 | F73: เพลส บางนา | H73: 532 | I73: ลูกค้าในBacklog | K73: นัดลูกค้าเสนอแบบครั้งที่ 1 รับบรีฟแก้แบบ
B74: คอลลูกค้าโครงเก่า | D74: 46136 | F74: so kaset | H74: 1406 | I74: ลูกค้าใหม่ยังไม่จอง | K74: ทำใบเสนอราคาเสนอลูกค้า
B75: คอลลูกค้าโครงเก่า | D75: 46136 | F75: Origin Plug&Play Sirindhorn Station | H75: A1016 | I75: ลูกค้าใหม่ยังไม่จอง | K75: ตามลค = ทำไปแล้ว ไม่สนใจทำเพิ่ม
B76: คอลลูกค้าโครงเก่า | D76: 46136 | F76: Origin Plug&Play Sirindhorn Station | H76: A1701 | I76: ลูกค้าใหม่ยังไม่จอง | K76: ตามลค = ไม่ตกแต่ง ซื้อของเอง
B77: คอลลูกค้าโครงเก่า | D77: 46136 | F77: Origin Plug&Play Sirindhorn Station | H77: A2114 | I77: ลูกค้าใหม่ยังไม่จอง | K77: ตามลค = ปล่อยเช่าไปแล้ว
B78: คอลลูกค้าโครงเก่า | D78: 46136 | F78: Srinakarin | H78: 1912 | I78: ลูกค้าใหม่ยังไม่จอง | K78: ตามลค = ยังไม่สนใจ ถ้าสนใจจะติดต่อ
B79: คอลลูกค้าโครงเก่า | D79: 46136 | F79: Srinakarin | H79: 2303 | I79: ลูกค้าใหม่ยังไม่จอง | K79: ตามลค = ต่างชาติ ตแต่งห้องเอง
B80: คอลลูกค้าโครงเก่า | D80: 46136 | F80: Srinakarin | H80: 2707 | I80: ลูกค้าใหม่ยังไม่จอง | K80: ตามลค = ติดต่อไม่ได้
B81: คอลลูกค้าโครงเก่า | D81: 46136 | F81: Srinakarin | H81: 2716 | I81: ลูกค้าใหม่ยังไม่จอง | K81: ตามลค = ไม่ตกแต่ง งบน้อย
B82: คอลลูกค้าโครงเก่า | D82: 46136 | F82: Srinakarin | H82: 2012 | I82: ลูกค้าใหม่ยังไม่จอง | K82: ตามลค = ไม่่ตกแต่ง
B83: คอลลูกค้าโครงเก่า | D83: 46136 | F83: Srinakarin | H83: 1423 | I83: ลูกค้าใหม่ยังไม่จอง | K83: ตามลค = ตามซื้อเพิ่ม ยังไม่สนใจ
B84: คอลลูกค้าโครงเก่า | D84: 46136 | F84: Srinakarin | H84: 1919 | I84: ลูกค้าใหม่ยังไม่จอง | K84: ตามลค = ตามซื้อเพิ่ม ยังไม่สนใจ
B85: คอลลูกค้าโครงเก่า | D85: 46136 | F85: Srinakarin | H85: 2215 | I85: ลูกค้าใหม่ยังไม่จอง | K85: ตามลค = ไม่ตกแต่่ง เคยติดม่านไปแล้ว
B86: คอลลูกค้าโครงเก่า | D86: 46136 | F86: Srinakarin | H86: 2802 | I86: ลูกค้าใหม่ยังไม่จอง | K86: ตามลค = ไม่ตกแต่งอะไร หาซื้อเฟอร์เอง
D87: 46137 | F87: KNB rama 4 | H87: 2106 | I87: ลูกค้าในBacklog | K87: คุยลค เสนอ งานตกแต่งเพิ่มเติม
A88: 76 | D88: 46137 | F88: Origin Play Bangkunnon | H88: 802 | I88: ลูกค้าในBacklog | K88: นัดคุยที่โครงการ / เลือกวอลล์เพิ่ม | U88: =iferror(vlookup(W88,'Back up'!$B$2:$C$18,2),"")
D89: 46137 | F89: Origin Play Bangkunnon | H89: 1909 | I89: ลูกค้าในBacklog | K89: นัดคุย ผรม / วัดที่หน้างาน
D90: 46137 | F90: Origin Play Bangkunnon | H90: 1418 | I90: ลูกค้าในBacklog | K90: นัดคุย ผรม / วัดที่หน้างาน
B91: คอลลูกค้าโครงเก่า | D91: 46137 | F91: KNB rama 4 | H91: 1403 | I91: ลูกค้าใหม่ยังไม่จอง | K91: ตามลค = ขอราคากระจกเงาบันได
B92: คอลลูกค้าโครงเก่า | D92: 46137 | F92: KNB rama 4 | H92: 1908 | I92: ลูกค้าใหม่ยังไม่จอง | K92: ตามลค = ไม่สนใจ
B93: คอลลูกค้าโครงเก่า | D93: 46137 | F93: so kaset | H93: 1404 | I93: ลูกค้าใหม่ยังไม่จอง | K93: ตามลค = ติดต่อไม่ได้
B94: คอลลูกค้าโครงเก่า | D94: 46137 | F94: KNB rama 4 | H94: 2509 | I94: ลูกค้าใหม่ยังไม่จอง | K94: ตามลค = ไม่อยู่ห้อง ยังไม่มีแพลนจะอยู่
B95: คอลลูกค้าโครงเก่า | D95: 46137 | F95: KNB rama 4 | H95: 1408 | I95: ลูกค้าใหม่ยังไม่จอง | K95: ตามลค = สนใจแต่เดี๋ยวสะดวกจะติดต่อกลับ
B96: ทำเอกสาร | D96: 46137 | F96: ทำใบส่งมอบ | H96: - | K96: ทำใบส่งมอบงานต่างๆของ เดือน เมษา
D97: 46138 | F97: Origin Play Bangkunnon | G97: รัตน์ | H97: 1520 | I97: ลูกค้าใหม่ยังไม่จอง | K97: นัดคุยลคใหม่ | U97: =iferror(vlookup(W97,'Back up'!$B$2:$C$18,2),"")
D98: 46138 | F98: สาทร | H98: 3124 | I98: ลูกค้าในBacklog | K98: นัดส่งมอบงาน= ตรวจงานแล้ว / จะชำระ วันที่ 28-29
D99: 46138 | F99: Origin Play Bangkunnon | H99: 2224 | I99: ลูกค้าใหม่ยังไม่จอง | K99: นัดรับชำระ งานกรุกระจกเงา
D100: 46138 | F100: so kaset | H100: 807 | I100: ลูกค้าในBacklog | K100: นัดรับชำระส่งมอบงาน
B101: คอลลูกค้าโครงเก่า | D101: 46138 | F101: so kaset | H101: 1014 | I101: ลูกค้าใหม่ยังไม่จอง | K101: ตามลค = ติดต่อไม่ได้
B102: คอลลูกค้าโครงเก่า | D102: 46138 | F102: so kaset | H102: 1916 | I102: ลูกค้าใหม่ยังไม่จอง | K102: ตามลค = ปล่่อยเช่าไปแล้ว ไม่สนใจ
...

Sheet Hack1
A1: No. | B1: Contact date | C1: Close date | D1: Where | E1: Clients type | F1: Project | G1: Room no. | H1: Name (Customer) | I1: UPDATE | J1: Phone / Line id | K1: โอกาสปิด (%) | L1: คาดยอดขาย | M1: สถานะปัจจุบัน | N1: Product Type | O1: Design Package | P1: SALES | Q1: Close/Inprogress | R1: Follow up | S1: Status | T1: Next Update
A2: 1 | B2: 46096 | D2: LINE OA | K2: 0.5 | M2: Briefing | N2: Design&turnkey | O2: Investor Pro(M) | P2: AUN | Q2: =iferror(vlookup(S2,'Back up'!$B$2:$C$18,2,0),"") -> Inprogress | R2: Call | S2: ส่งใบราคาหรือ ข้อมูลแพ็คเกจให้กับลูกค้าแล้ว
A3: 2 | D3: LINE OA | M3: Contract | O3: Investor Pro(M) | P3: PON | Q3: =iferror(vlookup(S3,'Back up'!$B$2:$C$18,2,0),"") -> Inprogress | R3: Line | S3: เสนอราคาแล้ว แต่ขอเวลาตัดสินใจก่อน7
A4: 3 | D4: Facebook | M4: Quotation | O4: Starter set (S) | P4: AUN | Q4: =iferror(vlookup(S4,'Back up'!$B$2:$C$18,2,0),"") -> Inprogress | R4: E-mail | S4: เสนอราคาแล้ว หรือ พอร์ตบริษัทแล้วรอทำนัดลูกค้าแล้ว รอลูกค้าไปสำรวจหน้าSite
A5: 4 | D5: Instagram | M5: Closed | O5: Investor Pro(M) | P5: AUN | Q5: =iferror(vlookup(S5,'Back up'!$B$2:$C$18,2,0),"") -> Inprogress | S5: เสนอราคาแล้ว ทำนัดลูกค้าอีกรอบ
A6: 5 | D6: OPA | M6: Lead | O6: Fully design(L) | P6: AUN | Q6: =iferror(vlookup(S6,'Back up'!$B$2:$C$18,2,0),"") -> Inprogress | S6: เสนอราคาแล้ว รอลูกค้าเลือกวันเข้าเลือกวัสดุ
A7: 6 | D7: หาเอง | O7: Starter set (S) | P7: AUN | Q7: =iferror(vlookup(S7,'Back up'!$B$2:$C$18,2,0),"") -> Inprogress | S7: เสนอราคาแล้ว รอตัดสินใจ เปรียบเทียบกับคู่แข่ง
A8: 7 | P8: HACK | Q8: =iferror(vlookup(S8,'Back up'!$B$2:$C$18,2,0),"") -> Inprogress | S8: เสนอราคาแล้ว รอส่วนลด
A9: 8 | Q9: =iferror(vlookup(S9,'Back up'!$B$2:$C$18,2,0),"") -> Inprogress | S9: ออกแบบในเสนอราคาให้ลูกค้าเรียบร้อยแล้ว
A10: 9 | F10: Origin Plug&Play Ramintra | G10: A1801 | H10: คุณภาณุวัฒน์ วงษ์วัฒนะ | Q10: =iferror(vlookup(S10,'Back up'!$B$2:$C$18,2,0),"") -> Inprogress | S10: ไม่มีคนตอบแชท facebook / instagram รอบที่ 1 >> start conversation
A11: 10 | F11: Origin Play Bangkhunnon | G11: 1623 | H11: คุณ วิภา ทองรอด | Q11: =iferror(vlookup(S11,'Back up'!$B$2:$C$18,2,0),"") -> Inprogress | S11: ไม่มีคนตอบแชท facebook / instagram รอบที่ 2 >> next day
A12: 11 | B12: 46096 | D12: OPA | F12: So Origin Siriraj | G12: 906 | H12: คุณ วรพล อัศวเทษานนท์ | M12: Briefing | N12: Design&turnkey | O12: Fully design(L) | P12: HACK | Q12: =iferror(vlookup(S12,'Back up'!$B$2:$C$18,2,0),"") -> Close Lead | R12: Line | S12: ไม่มีคนตอบแชท facebook / instagram รอบที่ 3 >> เว้นสองวัน (วันที่ 5 หลังจากทักแชทรอบที่ 1)
A13: 12 | B13: 46096 | D13: OPA | F13: So Origin Siriraj | G13: 612 | H13: คุณ กวีโชค เลิศวัชรา | M13: Briefing | N13: Design&turnkey | O13: Fully design(L) | P13: HACK | Q13: =iferror(vlookup(S13,'Back up'!$B$2:$C$18,2,0),"") -> Close Lead | R13: Line | S13: เบอร์ผิด/เบอร์นี้ไม่สามารถติดต่อได้ แต่ยังมีข้อมูลช่องทาง Email/Line/Facebook caht
A14: 13 | B14: 46096 | D14: OPA | F14: So Origin Siriraj | G14: 606 | H14: คุณ สุดารัตน์ ศรีวิบูลย์ | M14: Briefing | N14: Design&turnkey | O14: Fully design(L) | P14: HACK | Q14: =iferror(vlookup(S14,'Back up'!$B$2:$C$18,2,0),"") -> Close Lead | R14: Line | S14: สอบถามสินค้าอื่นที่ไม่มีในโชว์รูม
A15: 14 | B15: 46110 | D15: OPA | F15: So Origin Siriraj | G15: 1707 | H15: คุณ กิตติพศ เกียรติพัฒนาชัย | M15: Briefing | N15: Design&turnkey | O15: Fully design(L) | P15: HACK | Q15: =iferror(vlookup(S15,'Back up'!$B$2:$C$18,2,0),"") -> Inprogress | R15: Line | S15: ไม่มีคนรับสาย/สายไม่ว่าง สาย 1 >> วันแรกที่ลูกค้าให้โทร หรือ วันที่ลูกค้าแจ้งเบอร์มา
A16: 15 | B16: 46111 | D16: OPA | F16: Origin Play Bangkhunnon | G16: 1525 | H16: คุณอรุณ งามวิชัยกิจ | M16: Briefing | N16: Loose furniture | O16: Starter set (S) | P16: HACK | Q16: =iferror(vlookup(S16,'Back up'!$B$2:$C$18,2,0),"") -> Inprogress | R16: Line | S16: ไม่มีคนรับสาย/สายไม่ว่าง สาย 2 >> 3 วัน นับจากวันแรก
A17: 16 | B17: 46111 | D17: OPA | F17: The Origin Bangkae | G17: A309 | H17: คุณกมลรัตน์ ประชุมรัตน์ | M17: Quotation | N17: Curtain | O17: Starter set (S) | P17: HACK | Q17: =iferror(vlookup(S17,'Back up'!$B$2:$C$18,2,0),"") -> Inprogress | R17: Line | S17: ไม่มีคนรับสาย/สายไม่ว่าง สาย 3 >> 7 วัน นับจากวันแรก
A18: 17 | B18: 46112 | F18: The origin Bangkae | G18: A509 | H18: คุณ วินนรี | S18: ลูกค้าชำระเงินเรียบร้อย
A19: 18 | B19: 46112 | F19: Origin Play Bangkhunnon | G19: 1611 | H19: คุณ ชาติสยาม นาสูง | Q19: =iferror(vlookup(S19,'Back up'!$B$2:$C$18,2),"")
A20: 19 | B20: 46112 | F20: Origin Play Bangkhunnon | G20: 1113 | H20: คุณ ชนาชลภ์ เงินประเสิรฐศรี | Q20: =iferror(vlookup(S20,'Back up'!$B$2:$C$18,2),"")
A21: 20 | B21: 46112 | F21: Origin Play Bangkhunnon | G21: 1404 | H21: คุณวิศิษฎ์ ตันติสังวรากูร | Q21: =iferror(vlookup(S21,'Back up'!$B$2:$C$18,2),"")
A22: 21 | B22: 46112 | F22: Origin Play Bangkhunnon | G22: 1505 | H22: คุณอรุณ งามวิชัยกิจ | Q22: =iferror(vlookup(S22,'Back up'!$B$2:$C$18,2),"")
A23: 22 | B23: 46112 | F23: The origin Bangkae | G23: D620 | H23: คุณ ธนิดา พีระชัยกุล | Q23: =iferror(vlookup(S23,'Back up'!$B$2:$C$18,2),"")
A24: 23 | B24: 46113 | F24: Origin Play Bangkhunnon | G24: 911 | N24: Design&turnkey | Q24: =iferror(vlookup(S24,'Back up'!$B$2:$C$18,2),"")
A25: 24 | B25: 46113 | F25: The origin Bangkae | G25: A204 | H25: คุณ พราวพิชชา ไชยบุตร | I25: ลูกค้าจอง / ตัดรายการ เหลือแค่ฟูก | L25: 10000 | N25: Loose furniture | P25: HACK | Q25: =iferror(vlookup(S25,'Back up'!$B$2:$C$18,2),"")
A26: 25 | B26: 46113 | F26: Origin Play Bangkhunnon | G26: 1418 | H26: คุณ วรุณี ศิริจงมีชัย | I26: นัดคุยรายละเอียดที่โครงบางขุนนนท์ วันที่4-04-26 | L26: 96000 | N26: Loose furniture | P26: HACK | Q26: =iferror(vlookup(S26,'Back up'!$B$2:$C$18,2),"")
A27: 26 | B27: 46113 | F27: Origin Play Bangkhunnon | G27: 817 | H27: คุณ รวิสรา | I27: เข้าแก้ไขงาน DF สง่มอบแล้ว | L27: 135000 | N27: Loose furniture | P27: HACK | Q27: =iferror(vlookup(S27,'Back up'!$B$2:$C$18,2),"")
A28: 27 | B28: 46113 | F28: Park Origin Chula Samyan | G28: 3807 | H28: คุณ กรรณิกา สโมสร | I28: ส่งใบเสนอราคางานม่าน / ลูกค้าต้องการเพิ่ม Chandelier | L28: 150000 | N28: Curtain | P28: HACK | Q28: =iferror(vlookup(S28,'Back up'!$B$2:$C$18,2),"")
A29: 28 | B29: 46113 | F29: The Origin Ramintra 83 Station | G29: H517 | H29: คุณ ฐิตาพร เขียนวงษ์ | I29: ส่งใบเสนอราคางาน LF (Voucher) | L29: 160000 | N29: Loose furniture | P29: HACK | Q29: =iferror(vlookup(S29,'Back up'!$B$2:$C$18,2),"")
A30: 29 | B30: 46113 | F30: The origin Bangkae | G30: A605 | H30: คุณจาตุรงค์ | I30: นัดเลือกผ้าม่านวันที่ 3-04-26 | L30: 135000 | P30: HACK | Q30: =iferror(vlookup(S30,'Back up'!$B$2:$C$18,2),"")
A31: 30 | B31: 46113 | F31: Origin Play Bangkhunnon | G31: 1902 | H31: คุณ อรุษา รัตนะพิสิฐ | I31: จัดรายการ Prop ให้ลุกค้าเลือก | L31: 10000 | N31: Loose furniture | P31: HACK | Q31: =iferror(vlookup(S31,'Back up'!$B$2:$C$18,2),"")
A32: 31 | B32: 46114 | F32: Origin Play Bangkhunnon | G32: 1616 | H32: คุณ ปาณิสรา ชาญประโคน | I32: ส่งใบเสนอราคางานม่าน | L32: 36540 | N32: Curtain | P32: HACK | Q32: =iferror(vlookup(S32,'Back up'!$B$2:$C$18,2),"")
A33: 32 | B33: 46114 | F33: The origin Bangkae | G33: A818 | H33: คุณ สุรีรัตน์ ศีลศร | I33: นัดเลือกผ้าม่านวันที่ 4-04-26 | L33: 62000 | N33: Loose furniture | P33: HACK | Q33: =iferror(vlookup(S33,'Back up'!$B$2:$C$18,2),"")
A34: 33 | Q34: =iferror(vlookup(S34,'Back up'!$B$2:$C$18,2),"")
A35: 34 | B35: 46115 | F35: The origin Bangkae | G35: A309 | H35: คุณกมลรัตน์ | I35: ลูกค้าจองแพ็คเก็จม่าน-วอล / ลูกค้าเพิ่มรายการกรุผนังยิปซั่มหัวเตียง | L35: 66000 | N35: Design | P35: HACK | Q35: =iferror(vlookup(S35,'Back up'!$B$2:$C$18,2),"")
A36: 35 | B36: 46115 | F36: The origin Bangkae | G36: A605 | H36: คุณจาตุรงค์ | I36: นัดเลือกผ้าม่านที่โครงบางแค | L36: 135000 | N36: Curtain | P36: HACK | Q36: =iferror(vlookup(S36,'Back up'!$B$2:$C$18,2),"")
A37: 36 | B37: 46115 | F37: Origin Play Bangkhunnon | G37: 1902 | H37: คุณ อรุษา รัตนะพิสิฐ | I37: ส่งรายการพร็อพให้ลูกค้าเลือก | L37: 10000 | N37: Loose furniture | P37: HACK | Q37: =iferror(vlookup(S37,'Back up'!$B$2:$C$18,2),"")
A38: 37 | B38: 46115 | F38: The origin Bangkae | G38: D620 | H38: คุณ ธนิดา | I38: ลูกค้าซื้อแพ็คเกจผ้าม่านจ่าย 100% ในวันงานอีเวนท์ / ลูกค้าขอตัดออก 1 รายการและขอคืนเงิน | L38: 16600 | N38: Curtain | P38: HACK | Q38: =iferror(vlookup(S38,'Back up'!$B$2:$C$18,2),"")
A39: 38 | B39: 46115 | F39: Origin Play Bangkhunnon | G39: 1616 | H39: คุณ ปาณิสรา ชาญประโคน | I39: Update ใบเสนอราคางานม่าน Rev.1 | L39: 36540 | N39: Curtain | P39: HACK
A40: 39 | Q40: =iferror(vlookup(S40,'Back up'!$B$2:$C$18,2),"")
A41: 40 | B41: 46116 | F41: Origin Play Bangkhunnon | G41: 1418 | H41: คุณ วรุณี ศิริจงมีชัย | I41: นัดคุยรายละเอียดที่โครงบางขุนนนท์ | L41: 96000 | N41: Curtain | P41: HACK | Q41: =iferror(vlookup(S41,'Back up'!$B$2:$C$18,2),"")
A42: 41 | B42: 46116 | F42: The Origin Bangkae | G42: A818 | H42: คุณสุรีรัตน์ ศีลศร | I42: นัดเลือกผ้าม่านที่โครงบางแค / ลค.ขอเพิ่มรายการ Wallpaper + เครื่องใช้ไฟฟ้า | L42: 100,000+ | N42: Curtain | P42: HACK | Q42: =iferror(vlookup(S42,'Back up'!$B$2:$C$18,2),"")
A43: 42 | B43: 46116 | F43: The Origin Bangkae | G43: A707 | H43: คุณ อุทัย ศุภโชคพาณิชย์ | I43: ติดต่อลูกค้าจากพี่อาย Ori / เตรียมจ่าย 50% พร้อมเข้าหน้างาน | L43: 99800 | N43: Built-in | P43: HACK | Q43: =iferror(vlookup(S43,'Back up'!$B$2:$C$18,2),"")
A44: 43 | B44: 46116 | F44: The Origin Ramintra | G44: A1801 | H44: คุณ ภาณุวัฒน์ วงษ์วัฒนะ | I44: นำส่งใบส่งมอบ / คงเหลืองานทำความสะอาดพื้นที่เลอะจากงานพ่นสีบันได | L44: 840000 | N44: Built-in | P44: HACK | Q44: =iferror(vlookup(S44,'Back up'!$B$2:$C$18,2),"")
A45: 44 | Q45: =iferror(vlookup(S45,'Back up'!$B$2:$C$18,2),"")
A46: 45 | B46: 46117 | F46: Origin Play Bangkhunnon | G46: 1616 | H46: คุณ ปาณิสรา ชาญประโคน | I46: คุยรายละเอียดเพิ่มเติมงาน BF ห้องนอน+ห้องนั่งเล่น | L46: 250,000+ | N46: Design | P46: HACK | Q46: =iferror(vlookup(S46,'Back up'!$B$2:$C$18,2),"")
A47: 46 | Q47: =iferror(vlookup(S47,'Back up'!$B$2:$C$18,2),"")
A48: 47 | B48: 46119 | F48: The Origin Bangkae | G48: A605 | H48: คุณจาตุรงค์ | I48: เก็บเงินลูกค้า 50% | Q48: =iferror(vlookup(S48,'Back up'!$B$2:$C$18,2),"")
A49: 48 | B49: 46119 | F49: The Origin Bangkae | G49: A309 | H49: คุณ กมลรัตน์ ประชุมรัตน์ | I49: คุยรายละเอียดปรับลดรายการ | Q49: =iferror(vlookup(S49,'Back up'!$B$2:$C$18,2),"")
A50: 49 | B50: 46119 | F50: The Origin Bangkae | G50: D620 | H50: คุณ ธนิดา | I50: คุยรายละเอียดปรับรายการ | Q50: =iferror(vlookup(S50,'Back up'!$B$2:$C$18,2),"")
A51: 50 | B51: 46119 | F51: The Origin Bangkae | G51: A628 | H51: คุณ ญาดา เจริญจงวิทยา | I51: คุยรายละเอียดการติดตั้งผ้าม่าน | Q51: =iferror(vlookup(S51,'Back up'!$B$2:$C$18,2),"")
A52: 51 | B52: 46119 | F52: Origin Play Bangkhunnon | G52: 809 | H52: คุณ อิศรีย์ | I52: คุยรายละเอียดการติดตั้งผ้าม่าน | Q52: =iferror(vlookup(S52,'Back up'!$B$2:$C$18,2),"")
A53: 52 | B53: 46119 | Q53: =iferror(vlookup(S53,'Back up'!$B$2:$C$18,2),"")
A54: 53 | Q54: =iferror(vlookup(S54,'Back up'!$B$2:$C$18,2),"")
A55: 54 | B55: 46120 | F55: The Origin Bangkae | G55: A727 | H55: คุณ อุทัย ศุภโชคพาณิชย์ | I55: สรุปรายการ / ลูกค้าชำระ 100% | L55: 99500 | Q55: =iferror(vlookup(S55,'Back up'!$B$2:$C$18,2),"")
A56: 55 | B56: 46120 | F56: The Origin Bangkae | G56: A309 | H56: คุณ กมลรัตน์ ประชุมรัตน์ | I56: ตัดรายการเหลือแค่ฉากกั้นห้อง / ลูกค้าชำระ 100% | L56: 25000 | Q56: =iferror(vlookup(S56,'Back up'!$B$2:$C$18,2),"")
A57: 56 | B57: 46120 | F57: Origin Play Bangkhunnon | G57: 809 | H57: คุณ อิศรีย์ | I57: ทำใบเสนาราคางานม่าน | L57: 14910 | Q57: =iferror(vlookup(S57,'Back up'!$B$2:$C$18,2),"")
A58: 57 | B58: 46120 | F58: Origin Play Bangkhunnon | G58: 1616 | H58: คุณ ปาณิสรา ชาญประโคน | I58: คุยรายละเอียดเสนอราคางานตกแต่ง | L58: 150000 | Q58: =iferror(vlookup(S58,'Back up'!$B$2:$C$18,2),"")
A59: 58 | B59: 46120 | F59: The Origin Bangkae | G59: A818 | H59: คุณสุรีรัตน์ ศีลศร | I59: Revise ใบเสนอราคา | L59: 100000 | Q59: =iferror(vlookup(S59,'Back up'!$B$2:$C$18,2),"")
A60: 59 | B60: 46120 | F60: Park Origin Chula Samyan | G60: 2505 | H60: คุณ ฐิติรัตน์ นนท์ธนปรัชญ์ | I60: ติดตามเรื่องส่งมอบ | L60: 120000 | Q60: =iferror(vlookup(S60,'Back up'!$B$2:$C$18,2),"")
A61: 60 | B61: 46120 | F61: Park Origin Phayathai | G61: 616 | H61: คุณ รินทร์ บุญวณิชวัฒน์ | I61: ติดตามเรื่องส่งมอบ | L61: 73152.9 | Q61: =iferror(vlookup(S61,'Back up'!$B$2:$C$18,2),"")
A62: 61 | B62: 46120 | F62: The Origin Ramintra 83 Station | G62: H517 | H62: คุณ ฐิตาพร เขียนวงษ์ | I62: ติดตามเรื่อง PO / แก้ไขใบเสนอราคา | L62: 160000 | Q62: =iferror(vlookup(S62,'Back up'!$B$2:$C$18,2),"")
A63: 62
A64: 63 | Q64: =iferror(vlookup(S64,'Back up'!$B$2:$C$18,2),"")
A65: 64 | B65: 46122 | F65: Origin Play Bangkhunnon | G65: 1616 | H65: คุณแพรว | I65: ส่งใบเสนอราคางานออกแบบ (ลูกค้าใหม่) | K65: 0.9 | L65: 150000 | M65: Quotation | N65: Design | Q65: =iferror(vlookup(S65,'Back up'!$B$2:$C$18,2),"")
A66: 65 | B66: 46122 | F66: Origin Play Bangkhunnon | G66: 1810 | H66: คุณ สาริส | I66: ส่งใบเสนอราคางานออกแบบ (ลูกค้าใหม่) | K66: 0.5 | L66: 115090 | M66: Quotation | N66: Design | Q66: =iferror(vlookup(S66,'Back up'!$B$2:$C$18,2),"")
A67: 66 | B67: 46122 | F67: The Origin Bangkae | G67: A308 | H67: คุณ นพมาศ | I67: ติดต่อลูกค้าจากคุณเยลลี่ Ori / เตรียมจ่าย 50% พร้อมเข้าหน้างาน (ลูกค้าเก่า) | K67: 0.9 | L67: 70000 | M67: Quotation | N67: Design | Q67: =iferror(vlookup(S67,'Back up'!$B$2:$C$18,2),"")
A68: 67 | B68: 46122 | F68: The Origin Bangkae | G68: A510 | H68: คุณ กัณฑ์สรวีย์ สวัสดี | I68: ติดต่อลูกค้า / เตรียมจ่าย 50% พร้อมเข้าหน้างาน (ลูกค้าเก่า) | K68: 0.9 | L68: 149900 | M68: Quotation | N68: Design | Q68: =iferror(vlookup(S68,'Back up'!$B$2:$C$18,2),"")
A69: 68 | Q69: =iferror(vlookup(S69,'Back up'!$B$2:$C$18,2),"")
A70: 69 | B70: 46123 | F70: So Origin Siriraj | G70: 906 | H70: คุณ วรพล อัศวเทษานนท์ | I70: ติดต่อลูกค้า (ลูกค้าเก่า) | K70: 0.5 | L70: 386240 | M70: Quotation | N70: Design | Q70: =iferror(vlookup(S70,'Back up'!$B$2:$C$18,2),"")
A71: 70 | B71: 46123 | F71: So Origin Siriraj | G71: 612 | H71: คุณ กวีโชค เลิศวัชรา | I71: ติดต่อลูกค้า (ลูกค้าเก่า) | K71: 0.5 | L71: 300000 | M71: Quotation | N71: Design | Q71: =iferror(vlookup(S71,'Back up'!$B$2:$C$18,2),"")
A72: 71 | B72: 46123 | F72: So Origin Siriraj | G72: 606 | H72: คุณ สุดารัตน์ ศรีวิบูลย์ | I72: ติดต่อลูกค้า (ลูกค้าเก่า) | K72: 0.5 | L72: 260000 | M72: Quotation | N72: Design | Q72: =iferror(vlookup(S72,'Back up'!$B$2:$C$18,2),"")
A73: 72 | B73: 46123 | F73: So Origin Siriraj | G73: 1707 | H73: คุณ กิตติพศ เกียรติพัฒนาชัย | I73: ติดต่อลูกค้า (ลูกค้าเก่า) | K73: 0.5 | L73: 400000 | M73: Quotation | N73: Design | Q73: =iferror(vlookup(S73,'Back up'!$B$2:$C$18,2),"")
A74: 73 | Q74: =iferror(vlookup(S74,'Back up'!$B$2:$C$18,2),"")
A75: 74 | B75: 46128 | F75: Park Origin Phayathai | G75: 728 | H75: คุณ สแตมป์ | I75: ลูกค้าชำระ 100% | L75: 103000 | Q75: =iferror(vlookup(S75,'Back up'!$B$2:$C$18,2),"")
A76: 75 | Q76: =iferror(vlookup(S76,'Back up'!$B$2:$C$18,2),"")
A77: 76 | B77: 46129 | F77: The Origin Bangkae | G77: A308 | H77: คุณ นพมาศ | I77: ลูกค้าต้องการชำระ 50% ด้วยการรูดบัตร | K77: 0.9 | L77: 70000 | M77: Quotation | Q77: =iferror(vlookup(S77,'Back up'!$B$2:$C$18,2),"")
A78: 77 | B78: 46129 | F78: The Origin Bangkae | G78: 12900 | H78: คุณ ญาดา เจริญจงวิทยา | I78: แจ้งคิวช่าง | K78: 0.9 | L78: 12900 | Q78: =iferror(vlookup(S78,'Back up'!$B$2:$C$18,2),"")
A79: 78 | B79: 46129 | F79: The Origin Bangkae | G79: A510 | H79: คุณ กัณฑ์สรวีย์ สวัสดี | K79: 0.5 | L79: 149900 | Q79: =iferror(vlookup(S79,'Back up'!$B$2:$C$18,2),"")
A80: 79 | B80: 46129 | F80: The Origin Bangkae | G80: A818 | H80: คุณสุรีรัตน์ ศีลศร | I80: ส่งใบเสนอราคางานเพิ่ม | K80: 0.5 | L80: 100000 | Q80: =iferror(vlookup(S80,'Back up'!$B$2:$C$18,2),"")
A81: 80 | B81: 46129 | F81: Park Origin Phayathai | G81: 728 | H81: คุณ สแตมป์ | I81: ลูกค้าชำระ 100% | K81: 0.9 | L81: 103000 | Q81: =iferror(vlookup(S81,'Back up'!$B$2:$C$18,2),"")
A82: 81 | B82: 46129 | F82: The Origin Bangkae | G82: D620 | H82: คุณ ธนิดา | I82: แจ้งคิวช่างม่าน | K82: 0.9 | L82: 15000 | Q82: =iferror(vlookup(S82,'Back up'!$B$2:$C$18,2),"")
A83: 82 | B83: 46129 | F83: The Origin Ramintra | G83: A1801 | H83: คุณ ภาณุวัฒน์ วงษ์วัฒนะ | I83: ส่งลิงค์จ่ายเงินให้ลูกค้า / คงเหลืองานทำความสะอาดพื้นที่เลอะจากงานเก็บสีพื้น | K83: 0.9 | L83: 840000 | N83: Built-in | Q83: =iferror(vlookup(S83,'Back up'!$B$2:$C$18,2),"")
A84: 83 | Q84: =iferror(vlookup(S84,'Back up'!$B$2:$C$18,2),"")
A85: 84 | B85: 46130 | F85: Park Origin Chula Samyan | G85: 2505 | H85: คุณ ฐิติรัตน์ นนท์ธนปรัชญ์ | I85: นำส่งใบส่งมอบงาน | K85: 0.9 | L85: 120000 | Q85: =iferror(vlookup(S85,'Back up'!$B$2:$C$18,2),"")
A86: 85 | B86: 46130 | F86: Park Origin Phayathai | G86: 616 | H86: คุณ รินทร์ บุญวณิชวัฒน์ | I86: นำส่งใบส่งมอบงาน | K86: 0.9 | L86: 73152.9 | Q86: =iferror(vlookup(S86,'Back up'!$B$2:$C$18,2),"")
A87: 86 | B87: 46130 | F87: Origin Play Bangkhunnon | G87: 1701 | H87: คุณ เอ | I87: โทรคุย | K87: 0.5 | Q87: =iferror(vlookup(S87,'Back up'!$B$2:$C$18,2),"")
A88: 87 | B88: 46130 | F88: Origin Play Bangkhunnon | G88: 1611 | H88: คุณ ชาติสยาม นาสูง | I88: ติดตามลูกค้างานม่าน | K88: 0.9 | L88: 15800 | Q88: =iferror(vlookup(S88,'Back up'!$B$2:$C$18,2),"")
A89: 88 | B89: 46130 | F89: Park Origin Phayathai | G89: 924 | H89: คุณ ศุภฤกษ์ กมลานนท์ | I89: ติดต่อลูกค้าแผ่นดินไหว นัดเริ่มงานต้นเดือน พ.ค. | K89: 0.9 | L89: 155500 | Q89: =iferror(vlookup(S89,'Back up'!$B$2:$C$18,2),"")
A90: 89 | Q90: =iferror(vlookup(S90,'Back up'!$B$2:$C$18,2),"")
A91: 90 | B91: 46132 | F91: Park Origin Phayathai | G91: 616 | H91: คุณ รินทร์ บุญวณิชวัฒน์ | I91: ติิดตามลูกค้าเรื่องส่งมอบงาน | K91: 0.9 | L91: 73152.9 | Q91: =iferror(vlookup(S91,'Back up'!$B$2:$C$18,2),"")
A92: 91 | B92: 46132 | F92: The Origin Bangkae | G92: D620 | H92: คุณ ธนิดา | I92: นัดลูกค้าวัดพื้นที่ | K92: 0.9 | L92: 15000 | Q92: =iferror(vlookup(S92,'Back up'!$B$2:$C$18,2),"")
A93: 92 | B93: 46132 | F93: The Origin Bangkae | G93: A828 | H93: คุณ สุธีป | I93: ติดต่อลูกค้าเตรียมเริ่มงาน เริ่มวัดพื้นที่ | K93: 0.9 | L93: 43000 | Q93: =iferror(vlookup(S93,'Back up'!$B$2:$C$18,2),"")
A94: 93 | B94: 46132 | F94: The Origin Bangkae | G94: A518 | H94: คุณ แอปเปิ้ล | I94: ติดต่อลูกค้าใหม่ | K94: 0.5 | Q94: =iferror(vlookup(S94,'Back up'!$B$2:$C$18,2),"")
A95: 94 | B95: 46132 | F95: Origin Play Bangkhunnon | G95: 1701 | H95: , | I95: เสนอราคางานออกแบบ | K95: 0.5 | L95: 30000 | Q95: =iferror(vlookup(S95,'Back up'!$B$2:$C$18,2),"")
A96: 95 | Q96: =iferror(vlookup(S96,'Back up'!$B$2:$C$18,2),"")
A97: 96 | B97: 46133 | F97: The Origin Bangkae | G97: D620 | H97: คุณ ธนิดา | I97: นัดลูกค้าวัดพื้นที่ | K97: 0.9 | L97: 15000 | Q97: =iferror(vlookup(S97,'Back up'!$B$2:$C$18,2),"")
A98: 97 | B98: 46133 | F98: The Origin Bangkae | G98: A828 | H98: คุณ สุธีป | I98: ติดต่อลูกค้าเตรียมเริ่มงาน เริ่มวัดพื้นที่ | K98: 0.9 | L98: 43000 | Q98: =iferror(vlookup(S98,'Back up'!$B$2:$C$18,2),"")
A99: 98 | B99: 46133 | F99: The Origin Bangkae | G99: D628 | H99: คุณ ญาดา เจริญจงวิทยา | I99: นัดลูกค้าวัดพื้นที่ | K99: 0.9 | L99: 12900 | Q99: =iferror(vlookup(S99,'Back up'!$B$2:$C$18,2),"")
A100: 99 | B100: 46133 | F100: The Origin Bangkae | G100: D330 | H100: คุณ เหมียวตี้ | I100: ติดต่อลูกค้าใหม่ | K100: 0.5 | L100: 28600 | Q100: =iferror(vlookup(S100,'Back up'!$B$2:$C$18,2),"")
...

Sheet Hack
A1: 421 | C1: Date | D1: Where | E1: คอลัมน์ 3 | F1: Project | G1: Room no. | H1: Name | I1: Phone / Line id | J1: Type Product | K1: UPDATE | L1: Status/โอกาสปิด | M1: คาดยอดขาย | N1: โอกาสปิด
A2: 424 | C2: JUNE
A3: 422 | C3: 46174 | D3: ลูกค้าใหม่ | F3: Park Origin Chula Samyan | G3: 3707 | J3: Design&turnkey | K3: ส่งทำราคา | L3: กำลังคุย
A4: 423 | F4: So Origin Siriraj | G4: 1908 | J4: Design&turnkey | K4: สรุป Brift | L4: จองสิทธิ์
A5: 425 | C5: 46175 | F5: Origin Play Bangkhunnon | G5: 901 | J5: Curtain | K5: นัดลูกค้าเลือกผ้าม่านที่หน้างาน / คุยรายละเอียดงานเพิ่ม | L5: จองสิทธิ์
A6: 426 | F6: Park Origin Chula Samyan | G6: 3707 | J6: Design&turnkey | K6: สรุป Brift | L6: PO มาแล้ว
A7: 427 | C7: 46176 | F7: Origin Play Bangkhunnon | G7: 901 | J7: Curtain | K7: สรุปรายการงานเพิ่ม / ทำใบเสนอราคา | L7: จองสิทธิ์
A8: 428 | F8: Origin Play Bangkhunnon | G8: 1908 | J8: Design&turnkey | K8: สรุป Brift Design ตามข้อมูล Update จากลูกค้า | L8: จองสิทธิ์
A9: 429 | C9: 46177 | F9: Park Origin Chula Samyan | G9: 3807 | J9: Curtain | K9: นัดลูกค้าเข้าหน้างาน | L9: PO มาแล้ว
A10: 430 | F10: Origin Play Bangkhunnon | G10: 2208 | J10: Design&turnkey | K10: สรุป Brift Sketchc แบบคร่าวๆ | L10: จองสิทธิ์
A11: 431 | F11: Origin Play Bangkhunnon | G11: 2210 | K11: โทรคุยเสนอแพ็คเกจและงานออกแบบ | L11: กำลังคุย
A12: 432 | C12: 46178 | F12: Origin Play Bangkhunnon | G12: 2423 | J12: Curtain | K12: โทรคุุยเสนองานม่าน / ส่งใบเสนอราคา | L12: กำลังคุย
A13: 433 | F13: Park Origin Chula Samyan | G13: 3707 | J13: Design&turnkey | K13: แก้ไขข้อมูลส่งทำราคา | L13: PO มาแล้ว
A14: 434 | C14: 46179 | F14: So Origin Siriraj | K14: เข้าโครงการ | L14: -
A15: 435 | F15: Park Origin Chula Samyan | G15: 3707 | J15: Design&turnkey | K15: ตามราคา | L15: PO มาแล้ว
A16: 436 | C16: 46183 | F16: Origin Play Bangkhunnon | G16: 901 | J16: Curtain | K16: ทำราคา | L16: จองสิทธิ์
A17: 437 | F17: Origin Play Bangkhunnon | G17: 1201 | J17: Design&turnkey | K17: ติดตามลูกค้า | L17: จองสิทธิ์
A18: 438 | F18: The Origin Bangkae | G18: A502 | J18: Curtain | K18: ส่งใบเสนอราคางานม่าน / ชำระ 50% | L18: จ่าย 50%
A19: 439 | F19: Origin Play Bangkhunnon | G19: 1616 | H19: คุณ ปาณิสรา | I19: 093-549-6442 | J19: Curtain | K19: ติดตามลูกค้าจองสิทธิ์ | L19: จองสิทธิ์ | N19: 0.2
A20: 440 | F20: Origin Place Phetkasem | G20: 1813 | H20: คุณ ขวัญชนก | I20: 082-493-2354 | J20: Design&turnkey | K20: ติดตามลูกค้าจองสิทธิ์ | L20: จองสิทธิ์ | M20: 200000 | N20: 0.5
A21: 441 | F21: Origin Place Phetkasem | G21: 910 | H21: คุณ ภูกิจ | I21: 090-235-4924 | J21: Design&turnkey | K21: ห้องยังไม่พร้อม / รอนัดคุย | L21: จองสิทธิ์ | M21: 100000 | N21: 0.5
A22: 442 | C22: 46184 | F22: Origin Place Phetkasem | G22: 1105 | H22: คุณ ตวงพร | I22: 090-235-4924 | J22: Design&turnkey | K22: ห้องยังไม่พร้อม / รอนัดคุย | L22: จองสิทธิ์ | M22: 200000 | N22: 0.5
A23: 443 | F23: SO Origin Siriraj | G23: 612 | H23: คุณ กิตติพศ | I23: 083-049-8765 | J23: Design&turnkey | K23: ห้องยังไม่พร้อม / รอนัดคุย | L23: จองสิทธิ์ | M23: 386240 | N23: 0.9
A24: 444 | F24: SO Origin Siriraj | G24: 606 | H24: คุณ กวีโชค | I24: 061-836-6978 | J24: Design&turnkey | K24: ห้องยังไม่พร้อม / รอนัดคุย | L24: จองสิทธิ์ | M24: 300000 | N24: 0.9
A25: 445 | F25: SO Origin Siriraj | G25: 906 | H25: คุณ สุดารัตน์ | I25: 081-375-2488 | J25: Design&turnkey | K25: ห้องยังไม่พร้อม / รอนัดคุย / ส่ง ref ให้ลูกค้า ธีมอวกาศ | L25: จองสิทธิ์ | M25: 200000 | N25: 0.9
A26: 446 | F26: SO Origin Siriraj | G26: 1707 | H26: คุณ วรพล | I26: 083-891-5533 | J26: Design&turnkey | K26: ห้องยังไม่พร้อม / รอนัดคุย / โทรนัดอีกครั้งช่วงสิ้นเดือน มิ.ย. | L26: จองสิทธิ์ | M26: 400000 | N26: 0.9
A27: 447 | F27: SO Origin Siriraj | G27: 1908 | J27: Design&turnkey | K27: ทำ Blank BOQ ส่งทำราคา / ส่ง Brift ทำแบบ 3D | L27: จองสิทธิ์ | N27: 0.9
A28: 448 | D28: Call | F28: Origin Play Bangkhunnon | G28: 1703 | H28: คุณ ศิริอร ลิ่มวงศ์ | I28: 080-065-4656 | K28: ไม่สนใจ | L28: โทรแล้ว/ไม่สนใจ | N28: 0
A29: 449 | D29: Call | F29: Origin Play Bangkhunnon | G29: 1706 | H29: คุณ นุสรา สุนทรพลิน | I29: 062-227-5965 | K29: ไม่รับสาย | L29: โทรแล้ว/ไม่สนใจ | N29: 0
A30: 450 | C30: 46185 | D30: Call | F30: Origin Play Bangkhunnon | G30: 1709 | H30: คุณ ปาณชีวา กันภัย | I30: 095-289-3069 | K30: ไม่รับสาย | L30: โทรแล้ว/ไม่สนใจ | N30: 0
A31: 451 | D31: Call | F31: Origin Play Bangkhunnon | G31: 1710 | H31: คุณ รมัณยา จตุรภัทรไพบูลย์ | I31: 086-393-9502 | K31: ยังไม่ได้ตกแต่ง / ยังไม่ Add Line / ถ้าสนใจจะติดต่อกลับ | L31: - | N31: 0.2
A32: 457 | D32: Call | F32: Origin Play Bangkhunnon | G32: 1711 | H32: คุณ ดาวประกาย สุขสี | I32: 086-938-1223 | K32: ไม่สนใจ | L32: โทรแล้ว/ไม่สนใจ | N32: 0
A33: 458 | C33: 46186 | F33: SO Origin Siriraj | G33: 911 | K33: EVENT TRANSFER
A34: 459 | F34: SO Origin Siriraj | G34: 1607
A35: 460 | F35: SO Origin Siriraj | G35: 709
A36: 461 | F36: SO Origin Siriraj
A37: 462 | C37: 46187 | F37: SO Origin Siriraj | K37: EVENT TRANSFER
A38: 463
A39: 464
A40: 465
A41: 466 | C41: 46188 | D41: ลูกค้าใหม่ | F41: SO Origin Siriraj | G41: 705 | H41: คุณ เฉลิมชัย ประเสริฐวุฒิ | K41: ส่งใบเสนอราคางานออกแบบ | L41: จองสิทธิ์ | N41: 0.9
A42: 467
A43: 468 | D43: Call | F43: Origin Play Bangkhunnon | G43: 1713 | H43: คุณ จิราพร สิงห์โตทอง | I43: 092-272-2751 | K43: ไม่รับสาย | L43: โทรแล้ว/ไม่สนใจ | N43: 0
A44: 469 | D44: Call | F44: Origin Play Bangkhunnon | G44: 1714 | H44: คุณ โชติรส หุตังคบดี | I44: 086-333-3603 | K44: ไม่สนใจ | L44: โทรแล้ว/ไม่สนใจ | N44: 0
A45: 470 | C45: 46189 | D45: Call | F45: Origin Play Bangkhunnon | G45: 1716 | H45: คุณ บุษกร พีระพงษ์ | I45: 083-910-4269 | K45: Add Line / เสนอ Package ออกแบบ | L45: โทรแล้ว/Add line | N45: 0.2
A46: 471 | D46: Call | F46: Origin Play Bangkhunnon | G46: 1717 | H46: คุณ สรณ วิริยะประสิทธิ์ | I46: 080-506-0508 | K46: ไม่สนใจ | L46: โทรแล้ว/ไม่สนใจ | N46: 0
A47: 472 | D47: Call | F47: Origin Play Bangkhunnon | G47: 1718 | H47: คุณ จุฑาภรณ์ หนูมี | I47: 097-016-3742 | K47: Add Line / ส่ง Voucher ETH | L47: โทรแล้ว/Add line | N47: 0.2
A48: 473
A49: 474 | C49: 46190 | F49: Park Origin Chula Samyan | G49: 3807 | K49: ยกเลิกวอลเปเปอร์ / ติดตั้ง Chandelier
A50: 475 | F50: The Seed Memories Siam | G50: 60/38 | K50: สำรวจพื้นที่หน้างาน
A51: 476 | F51: Park Origin Chula Samyan | G51: 3707 | K51: ราคาเกินงบ / แก้ไขราคา | L51: PO มาแล้ว
A52: 477 | C52: 46191 | F52: The Origin Bangkae | G52: A605 | K52: ติดต่อลูกค้า / ออกหนังสือกำหนดการและรายละเอียดงาน
A53: 478 | F53: SO Origin Siriraj | G53: 911 | K53: เสนอ Package / มัดจำ 10,000 บาท | L53: จองสิทธิ์
A54: 480 | F54: Origin Play Bangkhunnon | G54: 901 | K54: ส่งใบเสนอราคา | L54: จองสิทธิ์
A55: 482 | C55: 46193 | F55: SO Origin Siriraj | G55: 507 | K55: ลูกค้าอยากทำแบบห้องตัวอย่าง Duo 501
A56: 484 | C56: 46194 | F56: SO Origin Siriraj | G56: 1207 | K56: ลูกค้าอยากทำแบบห้องตัวอย่าง Simplex 12A | L56: จองสิทธิ์
A57: 485 | C57: 46195 | F57: SO Origin Siriraj | G57: 507 | K57: ลูกค้าอยากทำแบบห้องตัวอย่าง (ทำราคา Duo 501)
A58: 486 | F58: Origin Play Bangkhunnon | G58: 2208 | K58: ติดต่อลูกค้า / Packae ห้องตัวอย่าง 156,000 (FND) | L58: จองสิทธิ์
A59: 487 | F59: Origin Play Bangkhunnon | G59: 1111 | K59: ลงข้อมูลลูกค้าชำระ 100% Backsplash | L59: จ่าย 100%ก่อนตกแต่ง
A60: 488 | C60: 46196 | F60: SO Origin Siriraj | G60: 1908 | K60: ส่งแบบ 3D 1st Draft
A61: 490 | F61: SO Origin Siriraj | G61: 1002 | K61: นัดคุยรายละเอียดที่โครงการ
A62: 491 | C62: 46197 | F62: Park Origin Chula Samyan | G62: 3707 | K62: ส่งแบบ 3D 1st Draft
A63: 493 | C63: 46198 | F63: SO Origin Siriraj | G63: 507 | K63: ส่งใบเสนอราคาตามแบบห้องตัวอย่าง (ไม่รวม Built-in)
A64: 494 | F64: SO Origin Siriraj | G64: 1207 | K64: ทำใบเสนอราคาตามห้องตัวอย่าง Simplex
F65: The Origin Bangkae | G65: A333 | K65: แก้ใบเสนอราคางานม่าน
F66: The Origin Bangkae | K66: เคลียร์ใบส่งมอบ
F67: The Origin Ramintra 83 | G67: H517 | K67: เคลียร์ใบส่งมอบ
A69: 495 | C69: 46198 | F69: The Origin Bangkae | K69: เคลียร์ใบส่งมอบ
A70: 496
A71: 497 | C71: 46200 | F71: The Origin Bangkae | K71: เคลียร์ใบส่งมอบ
A72: 498
A73: 499 | C73: 46201
A74: 500 | C74: 46202
A75: 501
A76: 502 | C76: 46203
A77: 503
A78: 504 | C78: JULY
A79: 505 | C79: 46204
A80: 506
A81: 507
A82: 508
A83: 509
A84: 510
A85: 511
A86: 512
A87: 513
A88: 514
A89: 515
A90: 516
A91: 517
... A104: 530
H116: 1719 | I116: เจษฎา จำปาหอม | J116: 096-939-6243
H117: 1720 | I117: สรินดา ศาตะมาน | J117: 092-268-6939
H118: 1721 | I118: กฤติยาภรณ์ บุญวิศิษฏ์ | J118: 095-764-1706
H119: 1722 | I119: อานนท์ ธนสินเกษตรชัย | J119: 080-261-7176
H120: 1723 | I120: สิรวุฒิ ลิ้มฬหะพันธ์ | J120: 084-979-7987
H121: 1724 | I121: พิทยสันต์ วัตตะยัง | J121: 081-646-9679
H122: 1725 | I122: รังษิยา ชูขันธ์ | J122: 096-850-5588
H123: 1801 | I123: ณัฐนนท์ นามจันทรา | J123: 084-544-1778
H124: 1803 | I124: ปัญจรัตน์ สมาธิ | J124: 065-341-1161
...

Sheet Back up
B2: ส่งใบราคาหรือ ข้อมูลแพ็คเกจให้กับลูกค้าแล้ว | C2: Inprogress
B3: เสนอราคาแล้ว แต่ขอเวลาตัดสินใจก่อน7 | C3: Inprogress
B4: เสนอราคาแล้ว หรือ พอร์ตบริษัทแล้วรอทำนัดลูกค้าแล้ว รอลูกค้าไปสำรวจหน้าSite | C4: Inprogress
B5: เสนอราคาแล้ว ทำนัดลูกค้าอีกรอบ | C5: Inprogress
B6: เสนอราคาแล้ว รอลูกค้าเลือกวันเข้าเลือกวัสดุ | C6: Inprogress
B7: เสนอราคาแล้ว รอตัดสินใจ เปรียบเทียบกับคู่แข่ง | C7: Inprogress
B8: เสนอราคาแล้ว รอส่วนลด | C8: Inprogress
B9: ออกแบบในเสนอราคาให้ลูกค้าเรียบร้อยแล้ว | C9: Inprogress
B10: ไม่มีคนตอบแชท facebook / instagram รอบที่ 1 >> start conversation | C10: Inprogress
B11: ไม่มีคนตอบแชท facebook / instagram รอบที่ 2 >> next day | C11: Inprogress
B12: ไม่มีคนตอบแชท facebook / instagram รอบที่ 3 >> เว้นสองวัน (วันที่ 5 หลังจากทักแชทรอบที่ 1) | C12: Close Lead
B13: เบอร์ผิด/เบอร์นี้ไม่สามารถติดต่อได้ แต่ยังมีข้อมูลช่องทาง Email/Line/Facebook caht | C13: Close Lead
... B18: ลูกค้าชำระเงินเรียบร้อย | C18: Close Lead

Sheet เพชเกษม
A1: 📋 ตารางสรุปรายการโทรลูกค้า — WYDE Interior Deposit | Origin Place เพชรเกษม
A2: ลูกค้าทั้งหมด 353 ราย | Deposit ห้องละ 10,000 บาท | Package เริ่มต้น 100,000 บาท
A3: ลำดับ | B3: ชื่อ-สกุล | C3: เบอร์โทร | D3: Email | E3: ห้อง | F3: ชั้น | G3: ประเภทห้อง | H3: อายุ | I3: จำนวนห้อง | J3: Deposit คาดได้ (฿) | K3: Package (฿) | L3: มูลค่าคาดปิด (฿) | M3: สถานะ | N3: หมายเหตุ
A4: 🔴 กลุ่ม 1 — Tag cross_sales (10 ราย) | M4: ORDER
A5: 1 | B5: เตชภณ ชุมวรฐายี | C5: 909691996 | D5: techaphon.chum@gmail.com | E5: 1010 | F5: 10 | G5: 1 Bedroom Duo | H5: 30 | I5: 1 | J5: 10000 | K5: 100000 | L5: 100000
A6: 2 | B6: สหัสณัฐ สหัสองศ์สห | C6: 616055499 | D6: sahatnut95@gmail.com | E6: 1106 | F6: 11 | G6: 1 Bedroom Duo | H6: 30 | I6: 1 | J6: 10000 | K6: 100000 | L6: 100000
A7: 3 | B7: กัลยาณี บุญรอด | C7: 885055968 | D7: kanlayanee.charoenrit@gmail.com | E7: 1917 | F7: 19 | G7: 1 Bedroom Duo | H7: 27 | I7: 1 | J7: 10000 | K7: 100000 | L7: 100000
A8: 4 | B8: ปัทมวรรณ ชุ่มชิต | C8: 875173972 | D8: pattamawan.chu@gmail.com | E8: 1920 | F8: 19 | G8: 1 Bedroom Duo | H8: 28 | I8: 1 | J8: 10000 | K8: 100000 | L8: 100000
A9: 5 | B9: รัชนีวรรณ ทรัพย์วงศ์เด่น | C9: 806692455 | D9: nong_sap@hotmail.com | E9: 609 | F9: 6 | G9: 1 Bedroom Duo | H9: 45 | I9: 1 | J9: 10000 | K9: 100000 | L9: 100000
A10: 6 | B10: ปิยะภรณ์ สุภาษิต | C10: 991651996 | D10: pc.creationindustry@gmail.com | E10: 704 | F10: 7 | G10: 1 Bedroom | H10: 48 | I10: 1 | J10: 10000 | K10: 100000 | L10: 100000
A11: 7 | B11: กิตติพิชญ์ สีห์อนุกุล | C11: 824789155 | D11: Kitsank@gmail.com | E11: 706 | F11: 7 | G11: 1 Bedroom | H11: 43 | I11: 1 | J11: 10000 | K11: 100000 | L11: 100000
A12: 8 | B12: PHYU THAZIN THIN | C12: 954916728 | D12: phyuthazinthin@gmail.com | E12: 709 | F12: 7 | G12: 1 Bedroom Kitchen | H12: 35 | I12: 1 | J12: 10000 | K12: 100000 | L12: 100000
A13: 9 | B13: รัฐวิกา ทองมอญ | C13: 936699041 | E13: 909 | F13: 9 | G13: 1 Bedroom Duo | H13: 27 | I13: 1 | J13: 10000 | K13: 100000 | L13: 100000
A14: 10 | B14: เนติพงษ์ สมัครการไถ | C14: 926947744 | D14: natipong906@gmail.com | E14: 913 | F14: 9 | G14: 1 Bedroom Duo | H14: 30 | I14: 1 | J14: 10000 | K14: 100000 | L14: 100000
A15: 🟠 กลุ่ม 2 — Tag everyonecansell (5 ราย)
A16: 11 | B16: กรรัตน์ สกลรักษ์ | C16: 877171525 | D16: warayupas.bugel@gmail.com | E16: 1107 | F16: 11 | G16: 1 Bedroom Plus Duo | H16: 52 | I16: 1 | J16: 10000 | K16: 100000 | L16: 100000 | M16: FND WYDE
A17: 12 | B17: จิรชาติ นีมะโยธิน | C17: 945522456 | D17: jirachart.nee@gmail.com | E17: 1517 | F17: 15 | G17: 1 Bedroom Duo | H17: 42 | I17: 2 | J17: 20000 | K17: 100000 | L17: 100000
A18: 13 | B18: จิรชาติ นีมะโยธิน | C18: 945522456 | D18: jirachart.nee@gmail.com | E18: 1518 | F18: 15 | G18: 1 Bedroom Duo | H18: 42 | I18: 2 | J18: 20000 | K18: 100000 | L18: 100000
A19: 14 | B19: รวิสรา อัยยะภาคย์ | C19: 884105543 | D19: ravisara.aiy@gmail.com | E19: 2015 | F19: 20 | G19: 1 Bedroom Plus Duo | H19: 27 | I19: 1 | J19: 10000 | K19: 100000 | L19: 100000
A20: 15 | B20: สมพงษ์ อมรสมานกุล | C20: 818581179 | D20: nkpyoao@gmail.com | E20: 2102 | F20: 21 | G20: 1 Bedroom Duo | H20: 62 | I20: 1 | J20: 10000 | K20: 100000 | L20: 100000
A21: 🏆 VIP — ซื้อ 10 ห้อง (10 ราย)
A22: 16 | B22: ทัศนีย์ คงวัดใหม่ | C22: 869617619 | E22: 1716 | F22: 17 | G22: 1 Bedroom Duo | H22: 68 | I22: 10 | J22: 100000 | K22: 100000 | L22: 100000
A23: 17 | B23: ทัศนีย์ คงวัดใหม่ | C23: 869617619 | E23: 1717 | F23: 17 | G23: 1 Bedroom Duo | H23: 68 | I23: 10 | J23: 100000 | K23: 100000 | L23: 100000
A24: 18 | B24: ทัศนีย์ คงวัดใหม่ | C24: 869617619 | E24: 716 | F24: 7 | G24: 1 Bedroom | H24: 68 | I24: 10 | J24: 100000 | K24: 100000 | L24: 100000
A25: 19 | B25: ทัศนีย์ คงวัดใหม่ | C25: 869617619 | E25: 717 | F25: 7 | G25: 1 Bedroom Kitchen | H25: 68 | I25: 10 | J25: 100000 | K25: 100000 | L25: 100000
A26: 20 | B26: ทัศนีย์ คงวัดใหม่ | C26: 869617619 | E26: 718 | F26: 7 | G26: 1 Bedroom Kitchen | H26: 68 | I26: 10 | J26: 100000 | K26: 100000 | L26: 100000
A27: 21 | B27: ทัศนีย์ คงวัดใหม่ | C27: 869617619 | E27: 719 | F27: 7 | G27: 1 Bedroom | H27: 68 | I27: 10 | J27: 100000 | K27: 100000 | L27: 100000
A28: 22 | B28: ทัศนีย์ คงวัดใหม่ | C28: 869617619 | E28: 720 | F28: 7 | G28: 1 Bedroom Kitchen | H28: 68 | I28: 10 | J28: 100000 | K28: 100000 | L28: 100000
A29: 23 | B29: ทัศนีย์ คงวัดใหม่ | C29: 869617619 | E29: 816 | F29: 8 | G29: 1 Bedroom | H29: 68 | I29: 10 | J29: 100000 | K29: 100000 | L29: 100000
A30: 24 | B30: ทัศนีย์ คงวัดใหม่ | C30: 869617619 | E30: 817 | F30: 8 | G30: 1 Bedroom Kitchen | H30: 68 | I30: 10 | J30: 100000 | K30: 100000 | L30: 100000
A31: 25 | B31: ทัศนีย์ คงวัดใหม่ | C31: 869617619 | E31: 820 | F31: 8 | G31: 1 Bedroom Kitchen | H31: 68 | I31: 10 | J31: 100000 | K31: 100000 | L31: 100000
A32: ⭐ ลูกค้าซื้อหลายห้อง (ชื่อซ้ำ) (36 ราย)
A33: 26 | B33: ภัทรชนน วารินทร์ | C33: 849243913 | D33: wpalm2013@gmail.com | E33: 12A12 | F33: 12A | G33: 1 Bedroom Duo | H33: 28 | I33: 2 | J33: 20000 | K33: 100000 | L33: 100000
A34: 27 | B34: เบญจวรรณ ไชยเสนา | C34: 841398677 | D34: amp_benjawan@hotmail.com | E34: 1405 | F34: 14 | G34: 1 Bedroom Duo | H34: 42 | I34: 2 | J34: 20000 | K34: 100000 | L34: 100000
A35: 28 | B35: ปริยา เสิศนำกุล | C35: 897859575 | E35: 1419 | F35: 14 | G35: 1 Bedroom Duo | H35: 39 | I35: 2 | J35: 20000 | K35: 100000 | L35: 100000
A36: 29 | B36: เบญจวรรณ ไชยเสนา | C36: 841398677 | D36: amp_benjawan@hotmail.com | E36: 1507 | F36: 15 | G36: 1 Bedroom Plus Duo | H36: 42 | I36: 2 | J36: 20000 | K36: 100000 | L36: 100000
A37: 30 | B37: ภัทรชนน วารินทร์ | C37: 849243913 | D37: wpalm2013@gmail.com | E37: 1509 | F37: 15 | G37: 1 Bedroom Duo | H37: 28 | I37: 2 | J37: 20000 | K37: 100000 | L37: 100000
A38: 31 | B38: พิมพ์มาดา แซ่หลี่ | C38: 818466583 | D38: yingzhu.wu@gmail.com | E38: 1617 | F38: 16 | G38: 1 Bedroom Duo | H38: 55 | I38: 2 | J38: 20000 | K38: 100000 | L38: 100000
A39: 32 | B39: ดุษฎี ขำประไพ | C39: 843341144 | D39: isue88@hotmail.com | E39: 1705 | F39: 17 | G39: 1 Bedroom Duo | H39: 45 | I39: 2 | J39: 20000 | K39: 100000 | L39: 100000
A40: 33 | B40: ดุษฎี ขำประไพ | C40: 843341144 | D40: isue88@hotmail.com | E40: 1706 | F40: 17 | G40: 1 Bedroom Duo | H40: 45 | I40: 2 | J40: 20000 | K40: 100000 | L40: 100000
A41: 34 | B41: ชลิต ติรชูพันธ์ | C41: 983525959 | D41: chalit.tr@gmail.com | E41: 1714 | F41: 17 | G41: 1 Bedroom Plus Duo | H41: 35 | I41: 2 | J41: 20000 | K41: 100000 | L41: 100000 | M41: FND WYDE
A42: 35 | B42: ชลิต ติรชูพันธ์ | C42: 983525959 | D42: chalit.tr@gmail.com | E42: 1715 | F42: 17 | G42: 1 Bedroom Plus Duo | H42: 35 | I42: 2 | J42: 20000 | K42: 100000 | L42: 100000 | M42: FND WYDE
A43: 36 | B43: ชุติรัตน์ ฉัตรศรีสัมฤทธิ์ | C43: 869549446 | D43: chutiratc@yahoo.com | E43: 1718 | F43: 17 | G43: 1 Bedroom Duo | H43: 34 | I43: 2 | J43: 20000 | K43: 100000 | L43: 100000
A44: 37 | B44: ภัทรวัฒน์ ดีสวาท | C44: 877676995 | D44: m4ii_month@hotmail.co.th | E44: 1915 | F44: 19 | G44: 1 Bedroom Plus Duo | H44: 33 | I44: 2 | J44: 20000 | K44: 100000 | L44: 100000
A45: 38 | B45: DANIEL LAWRENCE DI PIRO | C45: 923898322 | D45: ddipiro@gmail.com | E45: 2004 | F45: 20 | G45: 1 Bedroom Duo | H45: 61 | I45: 2 | J45: 20000 | K45: 100000 | L45: 100000
A46: 39 | B46: DANIEL LAWRENCE DI PIRO | C46: 923898322 | D46: ddipiro@gmail.com | E46: 2005 | F46: 20 | G46: 1 Bedroom Duo | H46: 61 | I46: 2 | J46: 20000 | K46: 100000 | L46: 100000
A47: 40 | B47: ชุติรัตน์ ฉัตรศรีสัมฤทธิ์ | C47: 869549446 | D47: chutiratc@yahoo.com | E47: 2008 | F47: 20 | G47: 1 Bedroom Duo | H47: 34 | I47: 2 | J47: 20000 | K47: 100000 | L47: 100000
A48: 41 | B48: ภัทรวัฒน์ ดีสวาท | C48: 877676995 | D48: m4ii_month@hotmail.co.th | E48: 2108 | F48: 21 | G48: 1 Bedroom Duo | H48: 33 | I48: 2 | J48: 20000 | K48: 100000 | L48: 100000
A49: 42 | B49: วัชพล นิรันดรางกูร | C49: 894455573 | E49: 2201 | F49: 22 | G49: 1 Bedroom Duo H | H49: 42 | I49: 2 | J49: 20000 | K49: 100000 | L49: 100000
A50: 43 | B50: จักษ์กฤษณ์ พลอยบูรณินทร์ | C50: 867779444 | E50: 2214 | F50: 22 | G50: 1 Bedroom Plus Duo H | H50: 44 | I50: 2 | J50: 20000 | K50: 100000 | L50: 100000
A51: 44 | B51: เสริมภูมิ พัฒนาพงษ์สถิตย์ | C51: 850958888 | E51: 2215 | F51: 22 | G51: 1 Bedroom Plus Duo H | H51: 51 | I51: 2 | J51: 20000 | K51: 100000 | L51: 100000
A52: 45 | B52: เสริมภูมิ พัฒนาพงษ์สถิตย์ | C52: 850958888 | E52: 2216 | F52: 22 | G52: 1 Bedroom Duo H | H52: 51 | I52: 2 | J52: 20000 | K52: 100000 | L52: 100000
A53: 46 | B53: ประยุทธ์ ตระกูลชวนดี | C53: 961624782 | D53: yoot_5@hotmail.com | E53: 2219 | F53: 22 | G53: 1 Bedroom Duo H | H53: 43 | I53: 2 | J53: 20000 | K53: 100000 | L53: 100000
A54: 47 | B54: ประยุทธ์ ตระกูลชวนดี | C54: 961624782 | D54: yoot_5@hotmail.com | E54: 2220 | F54: 22 | G54: 1 Bedroom Duo H | H54: 43 | I54: 2 | J54: 20000 | K54: 100000 | L54: 100000
A55: 48 | B55: วัชพล นิรันดรางกูร | C55: 894455573 | E55: 501 | F55: 5 | G55: 1 Bedroom Duo | H55: 42 | I55: 2 | J55: 20000 | K55: 100000 | L55: 100000
A56: 49 | B56: ณัฐญา วิลาวัณย์เวชยันต์ | C56: 949656464 | D56: Natthayatarn1@gmail.com | E56: 510 | F56: 5 | G56: 1 Bedroom Duo | H56: 31 | I56: 2 | J56: 20000 | K56: 100000 | L56: 100000
A57: 50 | B57: ณัฐญา วิลาวัณย์เวชยันต์ | C57: 949656464 | D57: Natthayatarn1@gmail.com | E57: 512 | F57: 5 | G57: 1 Bedroom Duo | H57: 31 | I57: 2 | J57: 20000 | K57: 100000 | L57: 100000
A58: 51 | B58: รัสรินทร์ พรพันธ์วรกิจ | C58: 938941944 | D58: rasrintr@gmail.com | E58: 517 | F58: 5 | G58: 1 Bedroom Duo | H58: 47 | I58: 2 | J58: 20000 | K58: 100000 | L58: 100000
A59: 52 | B59: รัสรินทร์ พรพันธ์วรกิจ | C59: 938941944 | D59: rasrintr@gmail.com | E59: 518 | F59: 5 | G59: 1 Bedroom Duo | H59: 47 | I59: 2 | J59: 20000 | K59: 100000 | L59: 100000
A60: 53 | B60: พิมพ์ภัทรา คชพงศ์ธนาดุล | C60: 820541444 | D60: gnova_00@hotmail.com | E60: 615 | F60: 6 | G60: 1 Bedroom Plus Duo | H60: 39 | I60: 2 | J60: 20000 | K60: 100000 | L60: 100000
A61: 54 | B61: พิมพ์ภัทรา คชพงศ์ธนาดุล | C61: 820541444 | D61: gnova_00@hotmail.com | E61: 616 | F61: 6 | G61: 1 Bedroom Duo | H61: 39 | I61: 2 | J61: 20000 | K61: 100000 | L61: 100000
A62: 55 | B62: ปริยา เสิศนำกุล | C62: 897859575 | E62: 620 | F62: 6 | G62: 1 Bedroom Duo | H62: 39 | I62: 2 | J62: 20000 | K62: 100000 | L62: 100000
A63: 56 | B63: ปภาวดี ศรีอภิรักษา | C63: 825599156 | E63: 710 | F63: 7 | G63: 1 Bedroom | H63: 32 | I63: 2 | J63: 20000 | K63: 100000 | L63: 100000
A64: 57 | B64: ปภาวดี ศรีอภิรักษา | C64: 825599156 | E64: 711 | F64: 7 | G64: 1 Bedroom | H64: 32 | I64: 2 | J64: 20000 | K64: 100000 | L64: 100000
A65: 58 | B65: พิมพ์มาดา แซ่หลี่ | C65: 818466583 | D65: yingzhu.wu@gmail.com | E65: 810 | F65: 8 | G65: 1 Bedroom | H65: 55 | I65: 2 | J65: 20000 | K65: 100000 | L65: 100000
A66: 59 | B66: พิชญ์ศุภา ศุภเศรษฐอนันต์ | C66: 948190444 | D66: scspsan@gmail.com | E66: 811 | F66: 8 | G66: 1 Bedroom | H66: 31 | I66: 2 | J66: 20000 | K66: 100000 | L66: 100000
A67: 60 | B67: พิชญ์ศุภา ศุภเศรษฐอนันต์ | C67: 948190444 | D67: scspsan@gmail.com | E67: 812 | F67: 8 | G67: 1 Bedroom | H67: 31 | I67: 2 | J67: 20000 | K67: 100000 | L67: 100000
A68: 61 | B68: จักษ์กฤษณ์ พลอยบูรณินทร์ | C68: 867779444 | E68: 814 | F68: 8 | G68: 1 Bedroom Plus | H68: 44 | I68: 2 | J68: 20000 | K68: 100000 | L68: 100000
A69: 👨‍👩‍👦 กลุ่มครอบครัว (เบอร์เดียวกัน) (6 ราย)
A70: 62 | B70: ปรายฟ้า แซ่แต้ | C70: 819144451 | E70: 1402 | F70: 14 | G70: 1 Bedroom Duo | H70: 21 | I70: 1 | J70: 10000 | K70: 100000 | L70: 100000
A71: 63 | B71: ฟ้าใส แซ่แต้ | C71: 819144451 | E71: 1502 | F71: 15 | G71: 1 Bedroom Duo | H71: 24 | I71: 1 | J71: 10000 | K71: 100000 | L71: 100000
A72: 64 | B72: สิทธินนท์ ลาภเรืองอนันต์ | C72: 949292509 | D72: jackowolap@hotmail.com | E72: 1603 | F72: 16 | G72: 1 Bedroom Plus Duo | H72: 32 | I72: 1 | J72: 10000 | K72: 100000 | L72: 100000
A73: 65 | B73: วันเพ็ญ จงขจรสุวรรณ | C73: 850654626 | D73: wanpen_pig@hotmail.co.th | E73: 1817 | F73: 18 | G73: 1 Bedroom Duo | H73: 51 | I73: 1 | J73: 10000 | K73: 100000 | L73: 100000
A74: 66 | B74: พลอยไพลิน แซ่ลิ้ม | C74: 850654626 | D74: pailinsployss@gmail.com | E74: 2017 | F74: 20 | G74: 1 Bedroom Duo | H74: 26 | I74: 1 | J74: 10000 | K74: 100000 | L74: 100000
A75: 67 | B75: ชุติมา ลาภเรืองอนันต์ | C75: 949292509 | D75: jingnakamaru@gmail.com | E75: 2111 | F75: 21 | G75: 1 Bedroom Duo | H75: 39 | I75: 1 | J75: 10000 | K75: 100000 | L75: 100000
A76: 📋 ลูกค้าทั่วไป (286 ราย)
A77: 68 | B77: กรกมล กีรติเตชากร | C77: 867506770 | D77: ning_kornkamon@hotmail.com | E77: 1001 | F77: 10 | G77: 1 Bedroom Duo | H77: 31 | I77: 1 | J77: 10000 | K77: 100000 | L77: 100000
A78: 69 | B78: สุเทพ เจตธำรงชัย | C78: 661688181 | E78: 1002 | F78: 10 | G78: 1 Bedroom Duo | H78: 38 | I78: 1 | J78: 10000 | K78: 100000 | L78: 100000
A79: 70 | B79: อนิวัช ทั้งวงศ์สกุล | C79: 819719829 | D79: Aniwat.tang@live.com | E79: 1003 | F79: 10 | G79: 1 Bedroom Plus Duo | H79: 42 | I79: 1 | J79: 10000 | K79: 100000 | L79: 100000 | M79: FND WYDE
A80: 71 | B80: วิมลรัตน์ เศารยะ | C80: 813623636 | E80: 1004 | F80: 10 | G80: 1 Bedroom Duo | H80: 73 | I80: 1 | J80: 10000 | K80: 100000 | L80: 100000
A81: 72 | B81: พิมพ์นารา ธีระดวงมณี | C81: 830666691 | D81: njane_@hotmail.com | E81: 1005 | F81: 10 | G81: 1 Bedroom Duo | H81: 29 | I81: 1 | J81: 10000 | K81: 100000 | L81: 100000
A82: 73 | B82: จินตนา เอื้อรักษ์โอฬาร | C82: 894986043 | D82: natakran.pimthong@gmail.com | E82: 1006 | F82: 10 | G82: 1 Bedroom Duo | H82: 36 | I82: 1 | J82: 10000 | K82: 100000 | L82: 100000
A83: 74 | B83: ณฐกานต์ พิมพ์ทอง | C83: 880250500 | D83: natakran.pimthong@gmail.com | E83: 1007 | F83: 10 | G83: 1 Bedroom Plus Duo | H83: 34 | I83: 1 | J83: 10000 | K83: 100000 | L83: 100000
A84: 75 | B84: ปวีณณัฏฐ์ ชำนาญ | C84: 863586661 | D84: paween.nut@hotmail.com | E84: 1008 | F84: 10 | G84: 1 Bedroom Duo | H84: 30 | I84: 1 | J84: 10000 | K84: 100000 | L84: 100000
A85: 76 | B85: ศิรวิชญ์ งามพันธุ์ดิศร | C85: 908147663 | D85: sirawit.engineer@gmail.com | E85: 1009 | F85: 10 | G85: 1 Bedroom Duo | H85: 33 | I85: 1 | J85: 10000 | K85: 100000 | L85: 100000
A86: 77 | B86: ศรุตา บุญรอด | C86: 953282665 | E86: 1011 | F86: 10 | G86: 1 Bedroom Duo | H86: 29 | I86: 1 | J86: 10000 | K86: 100000 | L86: 100000
A87: 78 | B87: ธนภัทร กมลโสภณวศิน | C87: 809199198 | D87: thanapat.kamol@gmail.com | E87: 1012 | F87: 10 | G87: 1 Bedroom Duo | H87: 33 | I87: 1 | J87: 10000 | K87: 100000 | L87: 100000
A88: 79 | B88: นิศากร น้อยมาลา | C88: 965850358 | D88: nisakornnoimala@gmail.com | E88: 1013 | F88: 10 | G88: 1 Bedroom Duo | H88: 31 | I88: 1 | J88: 10000 | K88: 100000 | L88: 100000
A89: 80 | B89: พรนัชชา ศุภเวสารัช | C89: 863789857 | D89: pnatcha_1337@hotmail.com | E89: 1014 | F89: 10 | G89: 1 Bedroom Plus Duo | H89: 32 | I89: 1 | J89: 10000 | K89: 100000 | L89: 100000
A90: 81 | B90: สันต์วิชญ์ วัฒนพรมมงคล | C90: 622244256 | D90: sunwishnan@gmail.com | E90: 1015 | F90: 10 | G90: 1 Bedroom Plus Duo | H90: 44 | I90: 1 | J90: 10000 | K90: 100000 | L90: 100000
A91: 82 | B91: เรวดี พูลพุฒ | C91: 895164244 | D91: iamray_d@yahoo.com | E91: 1016 | F91: 10 | G91: 1 Bedroom Duo | H91: 56 | I91: 1 | J91: 10000 | K91: 100000 | L91: 100000
A92: 83 | B92: ศิริวัฒน์ ศรีนวลมาก | C92: 944828919 | E92: 1017 | F92: 10 | G92: 1 Bedroom Duo | H92: 50 | I92: 1 | J92: 10000 | K92: 100000 | L92: 100000
A93: 84 | B93: ญานิดา ธารรำลึก | C93: 880096971 | D93: buatarnrumluek@icloud.com | E93: 1018 | F93: 10 | G93: 1 Bedroom Duo | H93: 26 | I93: 1 | J93: 10000 | K93: 100000 | L93: 100000
A94: 85 | B94: นวพร ดาราศิลป์ | C94: 861654687 | D94: nawaporn.drs@gmail.com | E94: 1019 | F94: 10 | G94: 1 Bedroom Duo | H94: 35 | I94: 1 | J94: 10000 | K94: 100000 | L94: 100000
A95: 86 | B95: สุภาพร ฉันทิยานนท์ | C95: 897949025 | D95: ffaaim.me@gmail.com | E95: 1020 | F95: 10 | G95: 1 Bedroom Duo | H95: 63 | I95: 1 | J95: 10000 | K95: 100000 | L95: 100000
A96: 87 | B96: พีรพงศ์ เย็นบ้านควน | C96: 814297825 | D96: perapongy@icloud.com | E96: 1101 | F96: 11 | G96: 1 Bedroom Duo | H96: 38 | I96: 1 | J96: 10000 | K96: 100000 | L96: 100000
A97: 88 | B97: ชินพัฒน์ สวัสดีจุ้ย | C97: 943271819 | D97: chinnapat.jui@gmail.com | E97: 1102 | F97: 11 | G97: 1 Bedroom Duo | H97: 26 | I97: 1 | J97: 10000 | K97: 100000 | L97: 100000
A98: 89 | B98: วงศกร รูโปบล | C98: 613914291 | D98: mibukyo13@gmail.com | E98: 1103 | F98: 11 | G98: 1 Bedroom Plus Duo | H98: 35 | I98: 1 | J98: 10000 | K98: 100000 | L98: 100000 | M98: Event 1
A99: 90 | B99: พลวัฒน์ จุลละครินทร์ | C99: 969517951 | D99: benz_14@hotmail.com | E99: 1104 | F99: 11 | G99: 1 Bedroom Duo | H99: 47 | I99: 1 | J99: 10000 | K99: 100000 | L99: 100000
A100: 91 | B100: ตวงพร ตรองตรง | C100: 835450770 | D100: minemail.taung@gmail.com | E100: 1105 | F100: 11 | G100: 1 Bedroom Duo | H100: 41 | I100: 1 | J100: 10000 | K100: 100000 | L100: 100000
...

Sheet ติดตามต่อกระทู้
A1: สรุปลูกค้าโอนกรรมสิทธิ์แล้ว — ยังไม่ได้ซื้อ WYDE
A2: The Origin Kathu Pathong | โอนแล้ว 325 ราย | เป็น WYDE แล้ว 15 ราย | ยังไม่ซื้อ WYDE 310 ราย
A3: # | B3: ตึก | C3: ชั้น | D3: ห้อง | E3: ชื่อ-สกุล | F3: เบอร์โทร | G3: Email | H3: Line ID | I3: Sale | J3: วันโอน | K3: ประเภทห้อง | L3: ราคาขาย | M3: สถานะสินเชื่อ
A4: 1 | B4: A | C4: 2 | D4: A201 | E4: ณภัทร พงศพรธาดา | F4: 917894653 | G4: coolphuket@gmail.com | H4: - | I4: หลิน | J4: 46076 | K4: BP1-09 | L4: 3450000 | M4: ต้องการยกเลิก | O4: สถานะลูกค้า | P4: รายการการทำงาน | Q4: Next Update | R4: ช่องทาง | S4: Phone | T4: Product Type | U4: Design Package | V4: คาดยอดขาย | W4: โอกาสปิด (%) | X4: SALES | Y4: สถานะปัจจุบัน | Z4: Close/Inprogress | AA4: Follow up | AB4: Status | AC4: Remark
A5: 2 | B5: A | C5: 2 | D5: A204 | E5: ธนัช ธนวันต์ปภังกร | F5: 956629445 | G5: doungporn.freedom@gmail.com | H5: - | I5: ใบขิง | K5: B2-04 | L5: 2399000 | M5: Agent - รอขาย
A6: 3 | B6: A | C6: 2 | D6: A205 | E6: ธนัช ธนวันต์ปภังกร | F6: 956629445 | G6: doungporn.freedom@gmail.com | H6: - | I6: ใบขิง | K6: B2-05M | L6: 2399000 | M6: Agent - รอขาย
A7: 4 | B7: A | C7: 2 | D7: A206 | E7: ขนิษฐา ทัพใจหาญ | F7: 884523952 | G7: Jam_khanitta@icloud.com | H7: - | I7: ฟ้า | K7: B2-05 | L7: 2360000 | M7: ยื่นแล้ว - ไม่ผ่าน(รอแก้เคส)
A8: 5 | B8: A | C8: 2 | D8: A207 | E8: ณัฎฐ์ชญาภา ปิยะวงค์วาณิชย์ | F8: 655361666 | G8: Suree116@hotmail.co.th | H8: - | I8: ใบขิง | K8: B2-05M | L8: 2299000 | M8: Agent - รอขาย
A9: 6 | B9: A | C9: 2 | D9: A208 | E9: ธนัช ธนวันต์ปภังกร | F9: 956629445 | G9: doungporn.freedom@gmail.com | H9: - | I9: ใบขิง | K9: B2-05 | L9: 2399000 | M9: Agent - รอขาย
A10: 7 | B10: A | C10: 2 | D10: A209 | E10: ธนัช ธนวันต์ปภังกร | F10: 956629445 | G10: doungporn.freedom@gmail.com | H10: - | I10: ใบขิง | K10: B2-05M | L10: 2399000 | M10: Agent - รอขาย
A11: 8 | B11: A | C11: 2 | D11: A210 | E11: กุลชญา คีรีรักษ์ | F11: 966535462 | G11: kulchaya.k@outlook.co.th | H11: - | I11: วาวา | K11: B2-05 | L11: 2450000 | M11: ยื่นแล้ว - ไม่ผ่าน(ติดบูโร)
A12: 9 | B12: A | C12: 2 | D12: A211 | E12: ชาคริต คูศรีเทพประทาน | F12: 626394946 | H12: - | I12: วาวา | K12: B2-05M | L12: 2500000 | M12: ยื่นเอง
A13: 10 | B13: A | C13: 2 | D13: A212 | E13: วนิดา รัตนะ | F13: 828075850 | G13: wanida_ratt@hotmail.com | H13: - | I13: เตย | K13: B2-05 | L13: 2400000 | M13: ยื่นแล้ว - ไม่ผ่าน(ติดบูโร)
A14: 11 | B14: A | C14: 2 | D14: A215 | E14: สุทธิชัย ใจอู่ | F14: 881956414 | G14: suthichai.tae@gmail.com | H14: 881956414 | I14: ฝน | K14: B2-06 | L14: 2290000 | M14: ยื่นแล้ว - รอผล
A15: 12 | B15: A | C15: 2 | D15: A216 | E15: พัชรา ลักษณะพริ้ม | F15: 937944249 | G15: patcha-@hotmail.com | H15: - | I15: เตย | K15: B2-03 | L15: 2690000 | M15: ยื่นแล้ว - ไม่ผ่าน(ติดบูโร)
A16: 13 | B16: A | C16: 2 | D16: A218 | E16: ณภัทร พงศพรธาดา | F16: 917894653 | G16: coolphuket@gmail.com | H16: - | I16: เตย | K16: B3-07 | L16: 2200000 | M16: อนุมัติ
A17: 14 | B17: A | C17: 2 | D17: A219 | E17: ณภัทร พงศพรธาดา | F17: 917894653 | G17: coolphuket@gmail.com | H17: - | I17: เตย | K17: B3-02 | L17: 2200000 | M17: ยื่นแล้ว - รอผล
A18: 15 | B18: A | C18: 2 | D18: A220 | E18: ศิกานต์ มูลโพธิ์ | F18: 967592121 | G18: Sikarnjiewliw1703@yahoo.com | H18: 967592121 | I18: เอื้อง | K18: B1-03 | L18: 2440000 | M18: ต้องการยกเลิก
A19: 16 | B19: A | C19: 2 | D19: A222 | E19: คัมภี ทองสาริ | F19: 613849143 | G19: ken_t01@yahoo.com | H19: ken_tong | I19: ลีนา | K19: B3-19 | L19: 2610000 | M19: ต้องการยกเลิก
A20: 17 | B20: A | C20: 2 | D20: A224 | E20: ธนวัฒน์ บุญเกตุ | F20: 622324293 | G20: bunket.th@gmail.com | H20: - | I20: ใบขิง | K20: BP1-10 | L20: 3090000 | M20: ยื่นแล้ว - รอผล
A21: 18 | B21: A | C21: 2 | D21: A225 | E21: เพ็ญพักตร์ ทองนิ่ม | F21: 954925693 | G21: Phenphak1313@gmail.com | H21: added | I21: วาวา | K21: BP1-05M | L21: 3090000 | M21: ยื่นแล้ว - รอผล
A22: 19 | B22: A | C22: 2 | D22: A226 | E22: ปฏิยุทธ ปิ่นแก้ว | F22: 957945629 | H22: added | I22: วาวา | K22: BP1-05 | L22: 3190000 | M22: ยื่นแล้ว - ไม่ผ่าน(รอแก้เคส)
A23: 20 | B23: A | C23: 3 | D23: A301 | E23: พัชรพล ชาญอุไร | F23: 866079959 | G23: coachdinsor@gmail.com | H23: . | I23: เดย์ | K23: BP1-09 | L23: 3580000 | M23: ร้องเรียน - ยกเลิก
A24: 21 | B24: A | C24: 3 | D24: A302 | E24: วีรยา จงกลวานนท์ | F24: 943244244 | G24: weeraya.koi@gmail.com | H24: . | I24: ฝน | J24: 46111 | K24: 2BR1-04 | L24: 4900000 | M24: สดไทย(เงินพร้อม)
A25: 22 | B25: A | C25: 3 | D25: A304 | E25: อนันต์ ทองพยุง | F25: 896669276 | G25: tang2730@gmail.com | H25: - | I25: แหม่ม | K25: B2-07 | L25: 2400000 | M25: ยื่นแล้ว - ไม่ผ่าน(ติดบูโร)
A26: 23 | B26: A | C26: 3 | D26: A307 | E26: ภูเดชา ลีภูเขียว | F26: 818951363 | H26: - | I26: มีน | K26: B2-05M | L26: 2330000 | M26: ยื่นแล้ว - รอผล | N26: ซื้อแล้ว
A27: 24 | B27: A | C27: 3 | D27: A308 | E27: อธิปพัฒน์ ดวงแก้ว | F27: 854333541 | G27: atippat541@gmail.com | H27: . | I27: ฝน | J27: 46098 | K27: B2-05 | L27: 2480000 | M27: ขายดาวน์
A28: 25 | B28: A | C28: 3 | D28: A309 | E28: เอกชัย แซ่หว่าง | F28: 988073345 | G28: a.0988073345@gmail.com | H28: . | I28: ฝน | K28: B2-05M | L28: 2550000 | M28: ยื่นแล้ว - รอผล
A29: 26 | B29: A | C29: 3 | D29: A310 | E29: ธนัช ธนวันต์ปภังกร | F29: 956629445 | G29: doungporn.freedom@gmail.com | H29: . | I29: ใบขิง | K29: B2-05 | L29: 2460000 | M29: Agent - รอขาย
A30: 27 | B30: A | C30: 3 | D30: A311 | E30: กิติยา บุญศิริ | F30: 885249745 | G30: kitiya.bunsiri@gmail.com | H30: . | I30: โอ๊ต | K30: B2-05M | L30: 2550000 | M30: ค้างดาวน์
A31: 28 | B31: A | C31: 3 | D31: A313 | E31: พัชรินทร์ เอี่ยมสงคราม | F31: 926455743 | G31: patcharin140962@gmail.com | H31: - | I31: มีน | K31: B2-05M | L31: 2700000 | M31: ยื่นแล้ว - รอผล
A32: 29 | B32: A | C32: 3 | D32: A314 | E32: ปวริศา มิตรกูล | F32: 915664794 | H32: . | I32: ลีนา | K32: B2-02 | L32: 2290000 | M32: สดไทย
